Workbook

Sheet Отчет о фин.рез.
A1: Наименование статей | B1: январь | C1: февраль | D1: март | E1: апрель | F1: май | G1: июнь | H1: июль | I1: август | J1: сентябрь | K1: октябрь | L1: ноябрь | M1: декабрь | N1: Итого | O1: Проверка
A2: Выручка, всего, в т.ч. | B2: =SUM(B3:B5) -> 0 | C2: =SUM(C3:C5) -> 0 | D2: =SUM(D3:D5) -> 5929.9 | E2: =SUM(E3:E5) -> 13713.2 | F2: =SUM(F3:F5) -> 15712.59 | G2: =SUM(G3:G5) -> 14253.351 | H2: =SUM(H3:H5) -> 0 | I2: =SUM(I3:I5) -> 0 | ... N2: =SUM(N3:N5) -> 49609.041 | O2: =+SUM($B2:$M2)-N2 -> 0
A3: зал | B3: 0 | D3: 5929.9 | E3: 13713.2 | F3: 15712.59 | G3: 14253.351 | N3: =SUM(B3:M3) -> 49609.041 | O3: =+SUM($B3:$M3)-N3 -> 0
A4: доставка | B4: 0 | N4: =SUM(B4:M4) -> 0 | O4: =+SUM($B4:$M4)-N4 -> 0
A5: Доп подразделение (назвать по-своему или пустое) | N5: =SUM(B5:M5) -> 0 | O5: =+SUM($B5:$M5)-N5 -> 0
A6: Количество гостей/заказов: | B6: =+SUM(B7:B9) -> 0 | C6: =+SUM(C7:C9) -> 0 | D6: =+SUM(D7:D9) -> 3807 | E6: =+SUM(E7:E9) -> 8253 | F6: =+SUM(F7:F9) -> 9177 | G6: =+SUM(G7:G9) -> 9166 | H6: =+SUM(H7:H9) -> 0 | I6: =+SUM(I7:I9) -> 0 | ... N6: =+SUM(N7:N9) -> 30403 | O6: =+SUM($B6:$M6)-N6 -> 0
A7: зал | B7: 0 | D7: 3807 | E7: 8253 | F7: 9177 | G7: 9085 | N7: =SUM(B7:M7) -> 30322 | O7: =+SUM($B7:$M7)-N7 -> 0
A8: доставка | B8: 0 | G8: 81 | N8: =SUM(B8:M8) -> 81 | O8: =+SUM($B8:$M8)-N8 -> 0
A9: Доп подразделение (назвать по-своему или пустое) | N9: =SUM(B9:M9) -> 0 | O9: =+SUM($B9:$M9)-N9 -> 0
A10: Средний чек | B10: =IFERROR(B2*1000/B6,"") | C10: =IFERROR(C2*1000/C6,"") | D10: =IFERROR(D2*1000/D6,"") -> 1557.6307 | E10: =IFERROR(E2*1000/E6,"") -> 1661.6018 | F10: =IFERROR(F2*1000/F6,"") -> 1712.1706 | G10: =IFERROR(G2*1000/G6,"") -> 1555.0241 | H10: =IFERROR(H2*1000/H6,"") | I10: =IFERROR(I2*1000/I6,"") | ... N10: =IFERROR(N2*1000/N6,"") -> 1631.7153
A11: зал | B11: =IFERROR(B3*1000/B7,"-") -> - | C11: =IFERROR(C3*1000/C7,"-") -> - | D11: =IFERROR(D3*1000/D7,"-") -> 1557.6307 | E11: =IFERROR(E3*1000/E7,"-") -> 1661.6018 | F11: =IFERROR(F3*1000/F7,"-") -> 1712.1706 | G11: =IFERROR(G3*1000/G7,"-") -> 1568.8884 | H11: =IFERROR(H3*1000/H7,"-") -> - | I11: =IFERROR(I3*1000/I7,"-") -> - | ... N11: =IFERROR(N3*1000/N7,"-") -> 1636.0742
A12: доставка | B12: =IFERROR(B4*1000/B8,"-") -> - | C12: =IFERROR(C4*1000/C8,"-") -> - | D12: =IFERROR(D4*1000/D8,"-") -> - | E12: =IFERROR(E4*1000/E8,"-") -> - | F12: =IFERROR(F4*1000/F8,"-") -> - | G12: =IFERROR(G4*1000/G8,"-") -> 0 | H12: =IFERROR(H4*1000/H8,"-") -> - | I12: =IFERROR(I4*1000/I8,"-") -> - | ... N12: =IFERROR(N4*1000/N8,"-") -> 0
A13: Доп подразделение (назвать по-своему или пустое) | B13: =IFERROR(B5*1000/B9,"-") -> - | C13: =IFERROR(C5*1000/C9,"-") -> - | D13: =IFERROR(D5*1000/D9,"-") -> - | E13: =IFERROR(E5*1000/E9,"-") -> - | F13: =IFERROR(F5*1000/F9,"-") -> - | G13: =IFERROR(G5*1000/G9,"-") -> - | H13: =IFERROR(H5*1000/H9,"-") -> - | I13: =IFERROR(I5*1000/I9,"-") -> - | ... N13: =IFERROR(N5*1000/N9,"-") -> -
A14: Себестоимость ИТОГО | B14: =+B15+B19 -> 0 | C14: =+C15+C19 -> 0 | D14: =+D15+D19 -> 2056.6998 | E14: =+E15+E19 -> 3982.4001 | F14: =+F15+F19 -> 4620.2513 | G14: =+G15+G19 -> 4111.6563 | H14: =+H15+H19 -> 0 | I14: =+I15+I19 -> 0 | ... N14: =+N15+N19 -> 14771.008 | O14: =+SUM($B14:$M14)-N14 -> 0
A15: Себестоимость реализации, всего, в т.ч. | B15: =+SUM(B16:B18) -> 0 | C15: =+SUM(C16:C18) -> 0 | D15: =+SUM(D16:D18) -> 1600.561 | E15: =+SUM(E16:E18) -> 3746.317 | F15: =+SUM(F16:F18) -> 4343.27 | G15: =+SUM(G16:G18) -> 3960.784 | H15: =+SUM(H16:H18) -> 0 | I15: =+SUM(I16:I18) -> 0 | ... N15: =+SUM(N16:N18) -> 13650.932 | O15: =+SUM($B15:$M15)-N15 -> 0
A16: зал | B16: 0 | D16: =2056.7-456.139 -> 1600.561 | E16: =3982.4-236.083 -> 3746.317 | F16: 4343.27 | G16: 3960.784 | N16: =SUM(B16:M16) -> 13650.932 | O16: =+SUM($B16:$M16)-N16 -> 0
A17: доставка | B17: 0 | N17: =SUM(B17:M17) -> 0 | O17: =+SUM($B17:$M17)-N17 -> 0
A18: Доп подразделение (назвать по-своему или пустое) | B18: 0 | N18: =SUM(B18:M18) -> 0 | O18: =+SUM($B18:$M18)-N18 -> 0
A19: Производственные показатели | B19: =+Расходы!B269/1000 -> 0 | C19: =+Расходы!C269/1000 -> 0 | D19: =+Расходы!D269/1000 -> 456.13882 | E19: =+Расходы!E269/1000 -> 236.08315 | F19: =+Расходы!F269/1000 -> 276.98128 | G19: =+Расходы!G269/1000 -> 150.87233 | H19: =+Расходы!H269/1000 -> 0 | I19: =+Расходы!I269/1000 -> 0 | ... M19: =+Расходы!M269/1000 -> 0 | N19: =SUM(B19:M19) -> 1120.0756 | O19: =+SUM($B19:$M19)-N19 -> 0
A20: Валовая прибыль | B20: =SUM(B21:B23) -> 0 | C20: =SUM(C21:C23) -> 0 | D20: =SUM(D21:D23) -> 3873.2002 | E20: =SUM(E21:E23) -> 9730.7999 | F20: =SUM(F21:F23) -> 11092.339 | G20: =SUM(G21:G23) -> 10141.695 | H20: =SUM(H21:H23) -> 0 | I20: =SUM(I21:I23) -> 0 | ... N20: =SUM(N21:N23) -> 34838.033 | O20: =+SUM($B20:$M20)-N20 -> 0
A21: зал | B21: =SUM(B3-B16-B19) -> 0 | C21: =SUM(C3-C16-C19) -> 0 | D21: =SUM(D3-D16-D19) -> 3873.2002 | E21: =SUM(E3-E16-E19) -> 9730.7999 | F21: =SUM(F3-F16-F19) -> 11092.339 | G21: =SUM(G3-G16-G19) -> 10141.695 | H21: =SUM(H3-H16-H19) -> 0 | I21: =SUM(I3-I16-I19) -> 0 | ... N21: =SUM(N3-N16-N19) -> 34838.033 | O21: =+SUM($B21:$M21)-N21 -> 0
A22: доставка | B22: =SUM(B4-B17) -> 0 | C22: =SUM(C4-C17) -> 0 | D22: =SUM(D4-D17) -> 0 | E22: =SUM(E4-E17) -> 0 | F22: =SUM(F4-F17) -> 0 | G22: =SUM(G4-G17) -> 0 | H22: =SUM(H4-H17) -> 0 | I22: =SUM(I4-I17) -> 0 | ... N22: =SUM(N4-N17) -> 0 | O22: =+SUM($B22:$M22)-N22 -> 0
A23: Доп подразделение (назвать по-своему или пустое) | B23: =SUM(B5-B18) -> 0 | C23: =SUM(C5-C18) -> 0 | D23: =SUM(D5-D18) -> 0 | E23: =SUM(E5-E18) -> 0 | F23: =SUM(F5-F18) -> 0 | G23: =SUM(G5-G18) -> 0 | H23: =SUM(H5-H18) -> 0 | I23: =SUM(I5-I18) -> 0 | ... N23: =SUM(N5-N18) -> 0 | O23: =+SUM($B23:$M23)-N23 -> 0
A24: % наценки | B24: =IFERROR((B2/B15-1)*100,"-") -> - | C24: =IFERROR((C2/C15-1)*100,"-") -> - | D24: =IFERROR((D2/D15-1)*100,"-") -> 270.48885 | E24: =IFERROR((E2/E15-1)*100,"-") -> 266.04484 | F24: =IFERROR((F2/F15-1)*100,"-") -> 261.76867 | G24: =IFERROR((G2/G15-1)*100,"-") -> 259.86186 | H24: =IFERROR((H2/H15-1)*100,"-") -> - | I24: =IFERROR((I2/I15-1)*100,"-") -> - | ... N24: =IFERROR((N2/N15-1)*100,"-") -> 263.41138
A25: зал | B25: =IFERROR((B3/B16-1)*100,"-") -> - | C25: =IFERROR((C3/C16-1)*100,"-") -> - | D25: =IFERROR((D3/D16-1)*100,"-") -> 270.48885 | E25: =IFERROR((E3/E16-1)*100,"-") -> 266.04484 | F25: =IFERROR((F3/F16-1)*100,"-") -> 261.76867 | G25: =IFERROR((G3/G16-1)*100,"-") -> 259.86186 | H25: =IFERROR((H3/H16-1)*100,"-") -> - | I25: =IFERROR((I3/I16-1)*100,"-") -> - | ... N25: =IFERROR((N3/N16-1)*100,"-") -> 263.41138
A26: доставка | B26: =IFERROR((B4/B17-1)*100,"-") -> - | C26: =IFERROR((C4/C17-1)*100,"-") -> - | D26: =IFERROR((D4/D17-1)*100,"-") -> - | E26: =IFERROR((E4/E17-1)*100,"-") -> - | F26: =IFERROR((F4/F17-1)*100,"-") -> - | G26: =IFERROR((G4/G17-1)*100,"-") -> - | H26: =IFERROR((H4/H17-1)*100,"-") -> - | I26: =IFERROR((I4/I17-1)*100,"-") -> - | ... N26: =IFERROR((N4/N17-1)*100,"-") -> -
A27: Доп подразделение (назвать по-своему или пустое) | B27: =IFERROR((B5/B18-1)*100,"-") -> - | C27: =IFERROR((C5/C18-1)*100,"-") -> - | D27: =IFERROR((D5/D18-1)*100,"-") -> - | E27: =IFERROR((E5/E18-1)*100,"-") -> - | F27: =IFERROR((F5/F18-1)*100,"-") -> - | G27: =IFERROR((G5/G18-1)*100,"-") -> - | H27: =IFERROR((H5/H18-1)*100,"-") -> - | I27: =IFERROR((I5/I18-1)*100,"-") -> - | ... N27: =IFERROR((N5/N18-1)*100,"-") -> -
A28: Операционные расходы | B28: =SUM(B29:B31) -> 0 | C28: =SUM(C29:C31) -> 0 | D28: =SUM(D29:D31) -> 2581.3719 | E28: =SUM(E29:E31) -> 7143.4247 | F28: =SUM(F29:F31) -> 8278.0935 | G28: =SUM(G29:G31) -> 7690.9786 | H28: =SUM(H29:H31) -> 0 | I28: =SUM(I29:I31) -> 0 | ... N28: =SUM(N29:N31) -> 25693.869 | O28: =+SUM($B28:$M28)-N28 -> 0
A29: текущие расходы заведения | B29: =+Расходы!B178/1000 -> 0 | C29: =Расходы!C178/1000 -> 0 | D29: =Расходы!D178/1000 -> 2581.3719 | E29: =Расходы!E178/1000 -> 7143.4247 | F29: =Расходы!F178/1000 -> 8247.9887 | G29: =Расходы!G178/1000 -> 7678.8271 | H29: =Расходы!H178/1000 -> 0 | I29: =Расходы!I178/1000 -> 0 | J29: =Расходы!J178/1000 -> 0 | ... M29: =Расходы!M178/1000 -> 0 | N29: =SUM(B29:M29) -> 25651.612 | O29: =+SUM($B29:$M29)-N29 -> 0
A30: расходы доставки | B30: =+Расходы!B208/1000 -> 0 | C30: =Расходы!C208/1000 -> 0 | D30: =Расходы!D208/1000 -> 0 | E30: =Расходы!E208/1000 -> 0 | F30: =Расходы!F208/1000 -> 30.10478 | G30: =Расходы!G208/1000 -> 12.15149 | H30: =Расходы!H208/1000 -> 0 | I30: =Расходы!I208/1000 -> 0 | J30: =Расходы!J208/1000 -> 0 | ... M30: =Расходы!M208/1000 -> 0 | N30: =SUM(B30:M30) -> 42.25627 | O30: =+SUM($B30:$M30)-N30 -> 0
A31: текущие расходы "Доп.подразделение" | B31: =+'расходы Доп.подразделение'!B178/1000 -> 0 | C31: ='расходы Доп.подразделение'!C178 -> 0 | D31: ='расходы Доп.подразделение'!D178 -> 0 | E31: ='расходы Доп.подразделение'!E178 -> 0 | F31: ='расходы Доп.подразделение'!F178 -> 0 | G31: ='расходы Доп.подразделение'!G178 -> 0 | H31: ='расходы Доп.подразделение'!H178 -> 0 | I31: ='расходы Доп.подразделение'!I178 -> 0 | J31: ='расходы Доп.подразделение'!J178 -> 0 | ... M31: ='расходы Доп.подразделение'!M178 -> 0 | N31: =SUM(B31:M31) -> 0 | O31: =+SUM($B31:$M31)-N31 -> 0
A32: Операционная прибыль | B32: =B33+B34 -> 0 | C32: =+SUM(C33:C35) -> 0 | D32: =+SUM(D33:D35) -> 1291.8283 | E32: =+SUM(E33:E35) -> 2587.3752 | F32: =+SUM(F33:F35) -> 2814.2452 | G32: =+SUM(G33:G35) -> 2450.716 | H32: =+SUM(H33:H35) -> 0 | I32: =+SUM(I33:I35) -> 0 | J32: =+SUM(J33:J35) -> 0 | ... N32: =+SUM(N33:N35) -> 9144.1647 | O32: =+SUM($B32:$M32)-N32 -> 0
A33: по основной деятельности | B33: =+B21-B29 -> 0 | C33: =+C21-C29 -> 0 | D33: =+D21-D29 -> 1291.8283 | E33: =+E21-E29 -> 2587.3752 | F33: =+F21-F29 -> 2844.35 | G33: =+G21-G29 -> 2462.8675 | H33: =+H21-H29 -> 0 | I33: =+I21-I29 -> 0 | ... N33: =+N21-N29 -> 9186.4209 | O33: =+SUM($B33:$M33)-N33 -> 0
A34: доставка | B34: =+B22-B30 -> 0 | C34: =+C22-C30 -> 0 | D34: =+D22-D30 -> 0 | E34: =+E22-E30 -> 0 | F34: =+F22-F30 -> -30.10478 | G34: =+G22-G30 -> -12.15149 | H34: =+H22-H30 -> 0 | I34: =+I22-I30 -> 0 | ... N34: =+N22-N30 -> -42.25627 | O34: =+SUM($B34:$M34)-N34 -> 0
A35: Доп.подразделение | B35: =+B23-B31 -> 0 | C35: =+C23-C31 -> 0 | D35: =+D23-D31 -> 0 | E35: =+E23-E31 -> 0 | F35: =+F23-F31 -> 0 | G35: =+G23-G31 -> 0 | H35: =+H23-H31 -> 0 | I35: =+I23-I31 -> 0 | ... N35: =+N23-N31 -> 0 | O35: =+SUM($B35:$M35)-N35 -> 0
O36: =+SUM($B36:$M36)-N36 -> 0
A37: Неоперационные доходы | N37: =SUM(B37:M37) -> 0 | O37: =+SUM($B37:$M37)-N37 -> 0
A39: Неоперационные расходы | B39: =SUM(B40:B51) -> 0 | C39: =SUM(C40:C51) -> 0 | D39: =SUM(D40:D51) -> 95.47676 | E39: =SUM(E40:E51) -> 792.7881 | F39: =SUM(F40:F51) -> 741.42911 | G39: =SUM(G40:G51) -> 799.28149 | H39: =SUM(H40:H51) -> 0 | I39: =SUM(I40:I51) -> 0 | ... N39: =SUM(N40:N51) -> 2428.9755 | O39: =+SUM($B39:$M39)-N39 -> 0
A40: Расходы служб | B40: =Расходы!B211/1000 -> 0 | C40: =Расходы!C211/1000 -> 0 | D40: =Расходы!D211/1000 -> 0 | E40: =Расходы!E211/1000 -> 404.92417 | F40: =Расходы!F211/1000 -> 382.80317 | G40: =Расходы!G211/1000 -> 300.3714 | H40: =Расходы!H211/1000 -> 0 | I40: =Расходы!I211/1000 -> 0 | ... M40: =Расходы!M211/1000 -> 0 | N40: =SUM(B40:M40) -> 1088.0987 | O40: =+SUM($B40:$M40)-N40 -> 0
A41: Налоги | B41: =+Расходы!B224/1000 -> 0 | C41: =+Расходы!C224/1000 -> 0 | D41: =+Расходы!D224/1000 -> 95.47676 | E41: =+Расходы!E224/1000 -> 342.82981 | F41: =+Расходы!F224/1000 -> 316.9573 | G41: =+Расходы!G224/1000 -> 362.167 | H41: =+Расходы!H224/1000 -> 0 | I41: =+Расходы!I224/1000 -> 0 | ... M41: =+Расходы!M224/1000 -> 0 | N41: =SUM(B41:M41) -> 1117.4309 | O41: =+SUM($B41:$M41)-N41 -> 0
A42: Амортизация имущества | B42: =+Расходы!B235/1000 -> 0 | C42: =+Расходы!C235/1000 -> 0 | D42: =+Расходы!D235/1000 -> 0 | E42: =+Расходы!E235/1000 -> 0 | F42: =+Расходы!F235/1000 -> 0 | G42: =+Расходы!G235/1000 -> 0 | H42: =+Расходы!H235/1000 -> 0 | I42: =+Расходы!I235/1000 -> 0 | ... M42: =+Расходы!M235/1000 -> 0 | N42: =SUM(B42:M42) -> 0 | O42: =+SUM($B42:$M42)-N42 -> 0
A43: Благотворительность | B43: =+Расходы!B236/1000 -> 0 | C43: =+Расходы!C236/1000 -> 0 | D43: =+Расходы!D236/1000 -> 0 | E43: =+Расходы!E236/1000 -> 0 | F43: =+Расходы!F236/1000 -> 0 | G43: =+Расходы!G236/1000 -> 0 | H43: =+Расходы!H236/1000 -> 0 | I43: =+Расходы!I236/1000 -> 0 | ... M43: =+Расходы!M236/1000 -> 0 | N43: =SUM(B43:M43) -> 0 | O43: =+SUM($B43:$M43)-N43 -> 0
A44: Инвестиционные проекты | B44: =+Расходы!B237/1000 -> 0 | C44: =+Расходы!C237/1000 -> 0 | D44: =+Расходы!D237/1000 -> 0 | E44: =+Расходы!E237/1000 -> 0 | F44: =+Расходы!F237/1000 -> 0 | G44: =+Расходы!G237/1000 -> 0 | H44: =+Расходы!H237/1000 -> 0 | I44: =+Расходы!I237/1000 -> 0 | ... M44: =+Расходы!M237/1000 -> 0 | N44: =SUM(B44:M44) -> 0 | O44: =+SUM($B44:$M44)-N44 -> 0
A45: Лицензия | B45: =+Расходы!B238/1000 -> 0 | C45: =+Расходы!C238/1000 -> 0 | D45: =+Расходы!D238/1000 -> 0 | E45: =+Расходы!E238/1000 -> 12 | F45: =+Расходы!F238/1000 -> 13.78 | G45: =+Расходы!G238/1000 -> 12.89 | H45: =+Расходы!H238/1000 -> 0 | I45: =+Расходы!I238/1000 -> 0 | ... M45: =+Расходы!M238/1000 -> 0 | N45: =SUM(B45:M45) -> 38.67 | O45: =+SUM($B45:$M45)-N45 -> 0
A46: Проценты по кредитам* | B46: =+Расходы!B239/1000 -> 0 | C46: =+Расходы!C239/1000 -> 0 | D46: =+Расходы!D239/1000 -> 0 | E46: =+Расходы!E239/1000 -> 0 | F46: =+Расходы!F239/1000 -> 0 | G46: =+Расходы!G239/1000 -> 96.885 | H46: =+Расходы!H239/1000 -> 0 | I46: =+Расходы!I239/1000 -> 0 | ... M46: =+Расходы!M239/1000 -> 0 | N46: =SUM(B46:M46) -> 96.885 | O46: =+SUM($B46:$M46)-N46 -> 0
A47: Расходы по заготовительному цеху | B47: =+Расходы!B240/1000 -> 0 | C47: =+Расходы!C240/1000 -> 0 | D47: =+Расходы!D240/1000 -> 0 | E47: =+Расходы!E240/1000 -> 33.03412 | F47: =+Расходы!F240/1000 -> 27.88864 | G47: =+Расходы!G240/1000 -> 26.96809 | H47: =+Расходы!H240/1000 -> 0 | I47: =+Расходы!I240/1000 -> 0 | ... M47: =+Расходы!M240/1000 -> 0 | N47: =SUM(B47:M47) -> 87.89085 | O47: =+SUM($B47:$M47)-N47 -> 0
A48: Резервы на ремонт | B48: =+Расходы!B241/1000 -> 0 | C48: =+Расходы!C241/1000 -> 0 | D48: =+Расходы!D241/1000 -> 0 | E48: =+Расходы!E241/1000 -> 0 | F48: =+Расходы!F241/1000 -> 0 | G48: =+Расходы!G241/1000 -> 0 | H48: =+Расходы!H241/1000 -> 0 | I48: =+Расходы!I241/1000 -> 0 | ... M48: =+Расходы!M241/1000 -> 0 | N48: =SUM(B48:M48) -> 0 | O48: =+SUM($B48:$M48)-N48 -> 0
A49: Скидка учредителям 50% | B49: =+Расходы!B242/1000 -> 0 | C49: =+Расходы!C242/1000 -> 0 | D49: =+Расходы!D242/1000 -> 0 | E49: =+Расходы!E242/1000 -> 0 | F49: =+Расходы!F242/1000 -> 0 | G49: =+Расходы!G242/1000 -> 0 | H49: =+Расходы!H242/1000 -> 0 | I49: =+Расходы!I242/1000 -> 0 | ... M49: =+Расходы!M242/1000 -> 0 | N49: =SUM(B49:M49) -> 0 | O49: =+SUM($B49:$M49)-N49 -> 0
A50: Фин.мотивация | B50: =+Расходы!B243/1000 -> 0 | C50: =+Расходы!C243/1000 -> 0 | D50: =+Расходы!D243/1000 -> 0 | E50: =+Расходы!E243/1000 -> 0 | F50: =+Расходы!F243/1000 -> 0 | G50: =+Расходы!G243/1000 -> 0 | H50: =+Расходы!H243/1000 -> 0 | I50: =+Расходы!I243/1000 -> 0 | ... M50: =+Расходы!M243/1000 -> 0 | N50: =SUM(B50:M50) -> 0 | O50: =+SUM($B50:$M50)-N50 -> 0
A51: Чрезвычайная ситуация | B51: =+Расходы!B244/1000 -> 0 | C51: =+Расходы!C244/1000 -> 0 | D51: =+Расходы!D244/1000 -> 0 | E51: =+Расходы!E244/1000 -> 0 | F51: =+Расходы!F244/1000 -> 0 | G51: =+Расходы!G244/1000 -> 0 | H51: =+Расходы!H244/1000 -> 0 | I51: =+Расходы!I244/1000 -> 0 | ... M51: =+Расходы!M244/1000 -> 0 | N51: =SUM(B51:M51) -> 0 | O51: =+SUM($B51:$M51)-N51 -> 0
A52: Чистая прибыль | B52: =+B32+B37-B39 -> 0 | C52: =+C32+C37-C39 -> 0 | D52: =+D32+D37-D39 -> 1196.3515 | E52: =+E32+E37-E39 -> 1794.5871 | F52: =+F32+F37-F39 -> 2072.8161 | G52: =+G32+G37-G39 -> 1651.4345 | H52: =+H32+H37-H39 -> 0 | I52: =+I32+I37-I39 -> 0 | ... N52: =+N32+N37-N39 -> 6715.1892 | O52: =+SUM($B52:$M52)-N52 -> -7.2759576e-12
A53: Начислено дивидендов | N53: =SUM(B53:M53) -> 0 | O53: =+SUM($B53:$M53)-N53 -> 0
O54: =+SUM($B54:$M54)-N54 -> 0
A55: Итоговое изменение активов | B55: =+B52-B53 -> 0 | C55: =+C52-C53 -> 0 | D55: =+D52-D53 -> 1196.3515 | E55: =+E52-E53 -> 1794.5871 | F55: =+F52-F53 -> 2072.8161 | G55: =+G52-G53 -> 1651.4345 | H55: =+H52-H53 -> 0 | I55: =+I52-I53 -> 0 | ... N55: =+N52-N53 -> 6715.1892 | O55: =+SUM($B55:$M55)-N55 -> -7.2759576e-12
A56: Справочно: | O56: =+SUM($B56:$M56)-N56 -> 0
A57: Имущество, в т.ч.: | B57: =SUM(B58:B59) -> 0 | C57: =SUM(C58:C59) -> 22609.582 | D57: =SUM(D58:D59) -> 3691.9724 | E57: =SUM(E58:E59) -> 539.66688 | F57: =SUM(F58:F59) -> 5007.7595 | G57: =SUM(G58:G59) -> 689.74706 | H57: =SUM(H58:H59) -> 0 | I57: =SUM(I58:I59) -> 0 | ... N57: =SUM(N58:N59) -> 32538.728 | O57: =+SUM($B57:$M57)-N57 -> 0
A58: Имущество заведения | C58: =1/1000*22609581.71 -> 22609.582 | D58: =3704908.06/1000-12935.7/1000 -> 3691.9724 | E58: =(639261.19-99594.31)/1000 -> 539.66688 | F58: =(5133173.91-125414.4)/1000 -> 5007.7595 | G58: =(1194779.21-505032.15)/1000 -> 689.74706 | N58: =SUM(B58:M58) -> 32538.728 | O58: =+SUM($B58:$M58)-N58 -> 0
A59: Посуда заведения | D59: , | N59: =SUM(B59:M59) -> 0 | O59: =+SUM($B59:$M59)-N59 -> 0
A60: Инвестиционные расходы, в т.ч.: | B60: =SUM(B61:B63) -> 0 | C60: =SUM(C61:C63) -> 45981.733 | D60: =SUM(D61:D63) -> 7354.6223 | E60: =SUM(E61:E63) -> 1790.0968 | F60: =SUM(F61:F63) -> 1773.2444 | G60: =SUM(G61:G63) -> 601.84296 | H60: =SUM(H61:H63) -> 0 | I60: =SUM(I61:I63) -> 0 | ... N60: =SUM(N61:N63) -> 57501.539 | O60: =+SUM($B60:$M60)-N60 -> 0
A61: Инвестиционные расходы заведения | C61: =1/1000*45981732.94 -> 45981.733 | D61: =1/1000*7354622.35 -> 7354.6223 | E61: =1/1000*1790096.84 -> 1790.0968 | F61: =1773.247-2.65/1000 -> 1773.2444 | G61: =1/1000*601842.96 -> 601.84296 | N61: =SUM(B61:M61) -> 57501.539 | O61: =+SUM($B61:$M61)-N61 -> 0
A62: Предоплаты имущества | N62: =SUM(B62:M62) -> 0 | O62: =+SUM($B62:$M62)-N62 -> 0
A63: Инвестиционные расходы летней террасы | N63: =SUM(B63:M63) -> 0 | O63: =+SUM($B63:$M63)-N63 -> 0
A64: Кредиты, в т.ч.: | B64: =SUM(B65:B66) -> 0 | C64: =SUM(C65:C66) -> 0 | D64: =SUM(D65:D66) -> 0 | E64: =SUM(E65:E66) -> 0 | F64: =SUM(F65:F66) -> 0 | G64: =SUM(G65:G66) -> 0 | H64: =SUM(H65:H66) -> 0 | I64: =SUM(I65:I66) -> 0 | ... N64: =SUM(N65:N66) -> 0 | O64: =+SUM($B64:$M64)-N64 -> 0
N65: =SUM(B65:M65) -> 0 | O65: =+SUM($B65:$M65)-N65 -> 0
N66: =SUM(B66:M66) -> 0 | O66: =+SUM($B66:$M66)-N66 -> 0
N67: =SUM(B67:M67) -> 0 | O67: =+SUM($B67:$M67)-N67 -> 0
A68: Возврат вкладов в УК | C68: =SUM(C69) -> -70052.312 | D68: =SUM(D69) -> -7462.181 | E68: =SUM(E69) -> -115.12 | F68: =SUM(F69) -> 0 | G68: =SUM(G69) -> 0 | H68: =SUM(H69) -> 0 | I68: =SUM(I69) -> 0 | J68: =SUM(J69) -> 0 | K68: =SUM(K69) -> 0 | N68: =SUM(B68:M68) -> -77629.613 | O68: =+SUM($B68:$M68)-N68 -> 0
C69: =-1/1000*70052312.35 -> -70052.312 | D69: =-1/1000*7462181.04000001 -> -7462.181 | E69: -115.12 | N69: =SUM(B69:M69) -> -77629.613 | O69: =+SUM($B69:$M69)-N69 -> 0
A70: Итого "справочно": | B70: =B57+B60+B64+B68 -> 0 | C70: =C57+C60+C64+C68 -> -1460.9977 | D70: =D57+D60+D64+D68 -> 3584.4137 | E70: =E57+E60+E64+E68 -> 2214.6437 | F70: =F57+F60+F64+F68 -> 6781.0039 | G70: =G57+G60+G64+G68 -> 1291.59 | H70: =H57+H60+H64+H68 -> 0 | I70: =I57+I60+I64+I68 -> 0 | ... M70: =M57+M60+M64+M68 -> 0 | N70: =SUM(B70:M70) -> 12410.654 | O70: =+SUM($B70:$M70)-N70 -> 0
A72: Изменение средств в обороте за период | B72: =B55-B70 -> 0 | C72: =C55-C70 -> 1460.9977 | D72: =D55-D70 -> -2388.0622 | E72: =E55-E70 -> -420.05666 | F72: =F55-F70 -> -4708.1878 | G72: =G55-G70 -> 359.84452 | H72: =H55-H70 -> 0 | I72: =I55-I70 -> 0 | J72: =J55-J70 -> 0 | K72: =K55-K70+K61 -> 0 | L72: =L55-L70+L61 -> 0 | M72: =M55-M70+M61 -> 0
A73: Остаток средств в обороте на 01.01.2026 г. | B73: 0
A74: Остаток средств в обороте нарастающим итогом: | B74: =B73+B72 -> 0 | C74: =B74+C72 -> 1460.9977 | D74: =C74+D72 -> -927.06447 | E74: =D74+E72 -> -1347.1211 | F74: =E74+F72 -> -6055.3089 | G74: =F74+G72 -> -5695.4644 | H74: =G74+H72 -> -5695.4644 | I74: =H74+I72 -> -5695.4644 | J74: =I74+J72 -> -5695.4644 | ... M74: =L74+M72 -> -5695.4644
B75: =-баланс!C26/1000 -> 0 | C75: =-баланс!D26/1000 -> 0 | D75: =-баланс!E26/1000 -> 0 | E75: =-баланс!F26/1000 -> 0 | F75: =-баланс!G26/1000 -> 0 | G75: =-баланс!H26/1000 -> 0 | H75: =-баланс!I26/1000 -> 0 | I75: =-баланс!J26/1000 -> 0 | ... M75: =-баланс!N26/1000 -> 0
C77: 45981733

Sheet Расходы
A1: Статьи расходов | B1: январь | C1: февраль | D1: март | E1: апрель | F1: май | G1: июнь | H1: июль | I1: август | J1: сентябрь | K1: октябрь | L1: ноябрь | M1: декабрь | N1: Итого | O1: Проверка | P1: Код
A2: Расходы на персонал | B2: =+B3+B14+B18 -> 0 | C2: =+C3+C14+C18 -> 0 | D2: =+D3+D14+D18 -> 1595189 | E2: =+E3+E14+E18 -> 4034614.2 | F2: =+F3+F14+F18 -> 4515469.7 | G2: =+G3+G14+G18 -> 4392321.4 | H2: =+H3+H14+H18 -> 0 | I2: =+I3+I14+I18 -> 0 | ... N2: =+N3+N14+N18 -> 14537594 | O2: =+SUM($B2:$M2)-N2 -> 0 | P2: 00-000406 | S2: =H2/1000 -> 0
A3: Фонд оплаты труда | B3: =SUM(B4:B13) -> 0 | C3: =SUM(C4:C13) -> 0 | D3: =SUM(D4:D13) -> 1415086.2 | E3: =SUM(E4:E13) -> 3397840 | F3: =SUM(F4:F13) -> 3793805.5 | G3: =SUM(G4:G13) -> 3559808.4 | H3: =SUM(H4:H13) -> 0 | I3: =SUM(I4:I13) -> 0 | ... N3: =SUM(N4:N13) -> 12166540 | O3: =+SUM($B3:$M3)-N3 -> 0 | P3: 00-000174 | S3: =H3/1000 -> 0
A4: 01 ЗП Кухня | D4: 478220 | E4: 1469110 | F4: 1577040 | G4: 1453396 | N4: =SUM(B4:M4) -> 4977766 | O4: =+SUM($B4:$M4)-N4 -> 0 | P4: 00-000420 | S4: =H4/1000 -> 0
A5: 02 ЗП Зал | D5: 598690 | E5: 1112200.1 | F5: =1119464-18900 -> 1100564 | G5: 1107995.9 | N5: =SUM(B5:M5) -> 3919449.9 | O5: =+SUM($B5:$M5)-N5 -> 0 | P5: 00-000421 | S5: =H5/1000 -> 0
A6: 03 ЗП Клининг | D6: 167700 | E6: 447330 | F6: 466830 | G6: 469690 | N6: =SUM(B6:M6) -> 1551550 | O6: =+SUM($B6:$M6)-N6 -> 0 | P6: 00-000422 | S6: =H6/1000 -> 0
A7: 04 ЗП Прочие | D7: 170476.23 | E7: 369200 | F7: 563661.5 | G7: 520913 | N7: =SUM(B7:M7) -> 1624250.7 | O7: =+SUM($B7:$M7)-N7 -> 0 | P7: 00-000423 | S7: =H7/1000 -> 0
A8: Больничный | N8: =SUM(B8:M8) -> 0 | O8: =+SUM($B8:$M8)-N8 -> 0 | P8: 00-000221 | S8: =H8/1000 -> 0
A9: Доплаты индивидуальные | N9: =SUM(B9:M9) -> 0 | O9: =+SUM($B9:$M9)-N9 -> 0 | P9: 00-000259 | S9: =H9/1000 -> 0
A10: Материальная помощь | N10: =SUM(B10:M10) -> 0 | O10: =+SUM($B10:$M10)-N10 -> 0 | P10: 00-000270 | S10: =H10/1000 -> 0
A11: Отпускные | F11: 60000 | N11: =SUM(B11:M11) -> 60000 | O11: =+SUM($B11:$M11)-N11 -> 0 | P11: 00-000163 | S11: =H11/1000 -> 0
A12: Пособия | N12: =SUM(B12:M12) -> 0 | O12: =+SUM($B12:$M12)-N12 -> 0 | P12: 00-000250 | S12: =H12/1000 -> 0
A13: Премии | F13: 25710 | G13: 7813.53 | N13: =SUM(B13:M13) -> 33523.53 | O13: =+SUM($B13:$M13)-N13 -> 0 | P13: 00-000172 | S13: =H13/1000 -> 0
A14: Налоги ФОТ | B14: =SUM(B15:B17) -> 0 | C14: =SUM(C15:C17) -> 0 | D14: =SUM(D15:D17) -> 3180 | E14: =SUM(E15:E17) -> 179705.94 | F14: =SUM(F15:F17) -> 304912.9 | G14: =SUM(G15:G17) -> 375492.9 | H14: =SUM(H15:H17) -> 0 | I14: =SUM(I15:I17) -> 0 | ... N14: =SUM(N15:N17) -> 863291.74 | O14: =+SUM($B14:$M14)-N14 -> 0 | P14: 00-000424 | S14: =H14/1000 -> 0
A15: Взносы ФОТ | E15: 110870.94 | F15: 148335.9 | G15: 239893.9 | N15: =SUM(B15:M15) -> 499100.74 | O15: =+SUM($B15:$M15)-N15 -> 0 | P15: 00-000425 | S15: =H15/1000 -> 0
A16: НДФЛ ФОТ | E16: 65643 | F16: 153495 | G16: 135599 | N16: =SUM(B16:M16) -> 354737 | O16: =+SUM($B16:$M16)-N16 -> 0 | P16: 00-000069 | S16: =H16/1000 -> 0
A17: Самозанятые комиссия | D17: 3180 | E17: 3192 | F17: 3082 | N17: =SUM(B17:M17) -> 9454 | O17: =+SUM($B17:$M17)-N17 -> 0 | P17: 00-000005 | S17: =H17/1000 -> 0
A18: Затраты на персонал | B18: =SUM(B19:B28) -> 0 | C18: =SUM(C19:C28) -> 0 | D18: =SUM(D19:D28) -> 176922.75 | E18: =SUM(E19:E28) -> 457068.25 | F18: =SUM(F19:F28) -> 416751.32 | G18: =SUM(G19:G28) -> 457020.1 | H18: =SUM(H19:H28) -> 0 | I18: =SUM(I19:I28) -> 0 | ... N18: =SUM(N19:N28) -> 1507762.4 | O18: =+SUM($B18:$M18)-N18 -> 0 | P18: 00-000272 | S18: =H18/1000 -> 0
A19: Компенсация проезда | N19: =SUM(B19:M19) -> 0 | O19: =+SUM($B19:$M19)-N19 -> 0 | P19: 00-000343 | S19: =H19/1000 -> 0
A20: Медосмотр сотрудников | E20: 10500 | F20: 23000 | G20: 11700 | N20: =SUM(B20:M20) -> 45200 | O20: =+SUM($B20:$M20)-N20 -> 0 | P20: 00-000301 | S20: =H20/1000 -> 0
A21: Оплата проживания | N21: =SUM(B21:M21) -> 0 | O21: =+SUM($B21:$M21)-N21 -> 0 | P21: 00-000345 | S21: =H21/1000 -> 0
A22: Питание штата | D22: 67195.13 | E22: 91256.19 | F22: 94352.92 | G22: 108611.8 | N22: =SUM(B22:M22) -> 361416.04 | O22: =+SUM($B22:$M22)-N22 -> 0 | P22: 00-000061 | S22: =H22/1000 -> 0
A23: Подарки сотрудникам | D23: 37455.62 | E23: 2362.01 | F23: 5000 | N23: =SUM(B23:M23) -> 44817.63 | O23: =+SUM($B23:$M23)-N23 -> 0 | P23: 00-000025 | S23: =H23/1000 -> 0
A24: Содержание столовой | N24: =SUM(B24:M24) -> 0 | O24: =+SUM($B24:$M24)-N24 -> 0 | P24: 00-000303 | S24: =H24/1000 -> 0
A25: Сотовая связь | N25: =SUM(B25:M25) -> 0 | O25: =+SUM($B25:$M25)-N25 -> 0 | P25: 00-000095 | S25: =H25/1000 -> 0
A26: Спецодежда | D26: 5129 | E26: 49748 | F26: 19992 | G26: 5256 | N26: =SUM(B26:M26) -> 80125 | O26: =+SUM($B26:$M26)-N26 -> 0 | P26: 00-000094 | S26: =H26/1000 -> 0
A27: Такси | D27: 67143 | E27: 303202.05 | F27: 274406.4 | G27: 331452.3 | N27: =SUM(B27:M27) -> 976203.75 | O27: =+SUM($B27:$M27)-N27 -> 0 | P27: 00-000080 | S27: =H27/1000 -> 0
A28: Такси завтраки | N28: =SUM(B28:M28) -> 0 | O28: =+SUM($B28:$M28)-N28 -> 0 | P28: 00-000276 | S28: =H28/1000 -> 0
A30: Арендные платежи | B30: =SUM(B32:B42) -> 0 | C30: =SUM(C32:C42) -> 0 | D30: =SUBTOTAL(9,D31:D39) -> 195161.29 | E30: =SUBTOTAL(9,E31:E39) -> 576880.1 | F30: =SUBTOTAL(9,F31:F39) -> 561000 | G30: =SUM(G32:G42) -> 564348 | H30: =SUM(H32:H42) -> 0 | I30: =SUM(I32:I42) -> 0 | J30: =SUM(J32:J42) -> 0 | K30: =SUM(K32:K42) -> 0 | L30: =SUM(L32:L42) -> 0 | M30: =SUM(M32:M42) -> 0 | N30: =SUM(N32:N42) -> 1891389.4 | O30: =+SUM($B30:$M30)-N30 -> 6000 | P30: 00-000181 | S30: =H30/1000 -> 0
A31: Аренда алкогольного склада | F31: 6000 | N31: =SUM(B31:M31) -> 6000 | O31: =+SUM($B31:$M31)-N31 -> 0 | P31: 00-000187 | S31: =H31/1000 -> 0
A32: Аренда гаража | N32: =SUM(B32:M32) -> 0 | O32: =+SUM($B32:$M32)-N32 -> 0 | P32: 00-000298 | S32: =H32/1000 -> 0
A33: Аренда заведения | D33: 195161.29 | E33: 550000 | F33: 550000 | G33: 550000 | N33: =SUM(B33:M33) -> 1845161.3 | O33: =+SUM($B33:$M33)-N33 -> 0 | P33: 00-000026 | S33: =H33/1000 -> 0
A34: Аренда земельного участка | N34: =SUM(B34:M34) -> 0 | O34: =+SUM($B34:$M34)-N34 -> 0 | P34: 00-000348 | S34: =H34/1000 -> 0
A35: Аренда имущества | N35: =SUM(B35:M35) -> 0 | O35: =+SUM($B35:$M35)-N35 -> 0 | P35: 00-000312 | S35: =H35/1000 -> 0
A36: Аренда офисов | N36: =SUM(B36:M36) -> 0 | O36: =+SUM($B36:$M36)-N36 -> 0 | P36: 00-000182 | S36: =H36/1000 -> 0
A37: Аренда парковочных мест | N37: =SUM(B37:M37) -> 0 | O37: =+SUM($B37:$M37)-N37 -> 0 | P37: 00-000332 | S37: =H37/1000 -> 0
A38: Аренда помещения мусорокамеры (Капитанская 12) | N38: =SUM(B38:M38) -> 0 | O38: =+SUM($B38:$M38)-N38 -> 0 | P38: 00-000193 | S38: =H38/1000 -> 0
A39: Аренда склада | E39: 26880.1 | F39: 5000 | G39: 10000 | N39: =SUM(B39:M39) -> 41880.1 | O39: =+SUM($B39:$M39)-N39 -> 0 | P39: 00-000204 | S39: =H39/1000 -> 0
A40: Аренда склада Гладкова | G40: 4348 | N40: =SUM(B40:M40) -> 4348 | O40: =+SUM($B40:$M40)-N40 -> 0 | P40: 00-000215 | S40: =H40/1000 -> 0
A41: Аренда цеха | N41: =SUM(B41:M41) -> 0 | O41: =+SUM($B41:$M41)-N41 -> 0 | P41: 00-000203 | S41: =H41/1000 -> 0
A42: Услуги автопарковки | N42: =SUM(B42:M42) -> 0 | O42: =+SUM($B42:$M42)-N42 -> 0 | P42: 00-000341 | S42: =H42/1000 -> 0
A43: Коммунальные расходы | B43: =SUM(B44:B52) -> 0 | C43: =SUM(C44:C52) -> 0 | D43: =SUM(D44:D52) -> 2000 | E43: =SUM(E44:E52) -> 258463.25 | F43: =SUM(F44:F52) -> 256508.55 | G43: =SUM(G44:G52) -> 378485.25 | H43: =SUM(H44:H52) -> 0 | I43: =SUM(I44:I52) -> 0 | ... N43: =SUM(N44:N52) -> 895457.05 | O43: =+SUM($B43:$M43)-N43 -> 0 | P43: 00-000180 | S43: =H43/1000 -> 0
A44: Водоснабжение | N44: =SUM(B44:M44) -> 0 | O44: =+SUM($B44:$M44)-N44 -> 0 | P44: 00-000254 | S44: =H44/1000 -> 0
A45: Вывоз мусора | D45: 2000 | E45: 39292.9 | F45: 55602.58 | G45: 47602.58 | N45: =SUM(B45:M45) -> 144498.06 | O45: =+SUM($B45:$M45)-N45 -> 0 | P45: 00-000060 | S45: =H45/1000 -> 0
A46: Коммунальные платежи | E46: 219170.35 | F46: 200905.97 | G46: 330882.67 | N46: =SUM(B46:M46) -> 750958.99 | O46: =+SUM($B46:$M46)-N46 -> 0 | P46: 00-000027 | S46: =H46/1000 -> 0
A47: Коммунальные расходы офисы | N47: =SUM(B47:M47) -> 0 | O47: =+SUM($B47:$M47)-N47 -> 0 | P47: 00-000257 | S47: =H47/1000 -> 0
A48: Сброс отходов | N48: =SUM(B48:M48) -> 0 | O48: =+SUM($B48:$M48)-N48 -> 0 | P48: 00-000366 | S48: =H48/1000 -> 0
A49: Содержание мест общего пользования (эксплуатационные расходы) | N49: =SUM(B49:M49) -> 0 | O49: =+SUM($B49:$M49)-N49 -> 0 | P49: 00-000258 | S49: =H49/1000 -> 0
A50: Стоки. Водоотведение | N50: =SUM(B50:M50) -> 0 | O50: =+SUM($B50:$M50)-N50 -> 0 | P50: 00-000255 | S50: =H50/1000 -> 0
A51: Теплоснабжение | N51: =SUM(B51:M51) -> 0 | O51: =+SUM($B51:$M51)-N51 -> 0 | P51: 00-000256 | S51: =H51/1000 -> 0
A52: Электроэнергия | N52: =SUM(B52:M52) -> 0 | O52: =+SUM($B52:$M52)-N52 -> 0 | P52: 00-000253 | S52: =H52/1000 -> 0
A53: Прочие ОФР/Деко | B53: =B54+B61+B67+B72+B121+B147 -> 0 | C53: =C54+C61+C67+C72+C121+C147 -> 0 | D53: =D54+D61+D67+D72+D121+D147 -> 186305.21 | E53: =E54+E61+E67+E72+E121+E147 -> 776072.7 | F53: =F54+F61+F67+F72+F121+F147 -> 1190620.9 | G53: =G54+G61+G67+G72+G121+G147 -> 811868.25 | H53: =H54+H61+H67+H72+H121+H147 -> 0 | I53: =I54+I61+I67+I72+I121+I147 -> 0 | ... N53: =N54+N61+N67+N72+N121+N147 -> 2964867.1 | O53: =+SUM($B53:$M53)-N53 -> 0 | P53: 00-000344 | S53: =H53/1000 -> 0
A54: HR Маркетинг | B54: =SUM(B55:B60) -> 0 | C54: =SUM(C55:C60) -> 0 | D54: =SUM(D55:D60) -> 26226.43 | E54: =SUM(E55:E60) -> 3082.6 | F54: =SUM(F55:F60) -> 23079.25 | G54: =SUM(G55:G60) -> 17042.81 | H54: =SUM(H55:H60) -> 0 | I54: =SUM(I55:I60) -> 0 | ... N54: =SUM(N55:N60) -> 69431.09 | O54: =+SUM($B54:$M54)-N54 -> 0 | P54: 00-000339 | S54: =H54/1000 -> 0
A55: HR Маркетинг | G55: 7371 | N55: =SUM(B55:M55) -> 7371 | O55: =+SUM($B55:$M55)-N55 -> 0 | P55: 00-000329 | S55: =H55/1000 -> 0
A56: Командировочные расходы | N56: =SUM(B56:M56) -> 0 | O56: =+SUM($B56:$M56)-N56 -> 0 | P56: 00-000074 | S56: =H56/1000 -> 0
A57: Корпоративные мероприятия | D57: 13207.2 | N57: =SUM(B57:M57) -> 13207.2 | O57: =+SUM($B57:$M57)-N57 -> 0 | P57: 00-000293 | S57: =H57/1000 -> 0
A58: Обучение персонала | D58: 12019.23 | E58: 2977.82 | F58: 18064.25 | G58: 5776.98 | N58: =SUM(B58:M58) -> 38838.28 | O58: =+SUM($B58:$M58)-N58 -> 0 | P58: 00-000142 | S58: =H58/1000 -> 0
A59: Подбор персонала | D59: 1000 | E59: 104.78 | F59: 5015 | G59: 1226.83 | N59: =SUM(B59:M59) -> 7346.61 | O59: =+SUM($B59:$M59)-N59 -> 0 | P59: 00-000347 | S59: =H59/1000 -> 0
A60: Развитие насмотренности | G60: 2668 | N60: =SUM(B60:M60) -> 2668 | O60: =+SUM($B60:$M60)-N60 -> 0 | P60: 00-000340 | S60: =H60/1000 -> 0
A61: Праздники | B61: =SUM(B62:B66) -> 0 | C61: =SUM(C62:C66) -> 0 | D61: =SUM(D62:D66) -> 0 | E61: =SUM(E62:E66) -> 0 | F61: =SUM(F62:F66) -> 0 | G61: =SUM(G62:G66) -> 0 | H61: =SUM(H62:H66) -> 0 | I61: =SUM(I62:I66) -> 0 | ... N61: =SUM(N62:N66) -> 0 | O61: =+SUM($B61:$M61)-N61 -> 0 | P61: 00-000350 | S61: =SUM(S62:S66) -> 0
A62: 23 февраля | N62: =SUM(B62:M62) -> 0 | O62: =+SUM($B62:$M62)-N62 -> 0 | P62: 00-000355 | S62: =H62/1000 -> 0
A63: 8 марта | N63: =SUM(B63:M63) -> 0 | O63: =+SUM($B63:$M63)-N63 -> 0 | P63: 00-000354 | S63: =H63/1000 -> 0
A64: День рождения Беллини | N64: =SUM(B64:M64) -> 0 | O64: =+SUM($B64:$M64)-N64 -> 0 | P64: 00-000353 | S64: =H64/1000 -> 0
A65: Елка БГ | N65: =SUM(B65:M65) -> 0 | O65: =+SUM($B65:$M65)-N65 -> 0 | P65: 00-000358 | S65: =H65/1000 -> 0
A66: Новый Год | N66: =SUM(B66:M66) -> 0 | O66: =+SUM($B66:$M66)-N66 -> 0 | P66: 00-000356 | S66: =H66/1000 -> 0
A67: Транспортные расходы | B67: =SUM(B68:B71) -> 0 | C67: =SUM(C68:C71) -> 0 | D67: =SUM(D68:D71) -> 29717.34 | E67: =SUM(E68:E71) -> 61797.48 | F67: =SUM(F68:F71) -> 83380.35 | G67: =SUM(G68:G71) -> 48159.7 | H67: =SUM(H68:H71) -> 0 | I67: =SUM(I68:I71) -> 0 | ... N67: =SUM(N68:N71) -> 223054.87 | O67: =+SUM($B67:$M67)-N67 -> 0 | P67: 00-000150 | S67: =H67/1000 -> 0
A68: Амортизация машины экспедитора | N68: =SUM(B68:M68) -> 0 | O68: =+SUM($B68:$M68)-N68 -> 0 | P68: 00-000216 | S68: =H68/1000 -> 0
A69: Бензин | E69: 4064.62 | F69: 25473.78 | G69: 10806.5 | N69: =SUM(B69:M69) -> 40344.9 | O69: =+SUM($B69:$M69)-N69 -> 0 | P69: 00-000043 | S69: =H69/1000 -> 0
A70: Содержание а/м | E70: 4392.86 | F70: 1428.57 | G70: 375.7 | N70: =SUM(B70:M70) -> 6197.13 | O70: =+SUM($B70:$M70)-N70 -> 0 | P70: 00-000140 | S70: =H70/1000 -> 0
A71: Транспортные расходы текущие | D71: 29717.34 | E71: 53340 | F71: =58073-1595 -> 56478 | G71: 36977.5 | N71: =SUM(B71:M71) -> 176512.84 | O71: =+SUM($B71:$M71)-N71 -> 0 | P71: 00-000089 | S71: =H71/1000 -> 0
A72: Услуги | B72: =SUM(B73:B120) -> 0 | C72: =SUM(C73:C120) -> 0 | D72: =SUM(D73:D120) -> 92270.7 | E72: =SUM(E73:E120) -> 351126.06 | F72: =SUM(F73:F120) -> 434442.33 | G72: =SUM(G73:G120) -> 389181.97 | H72: =SUM(H73:H120) -> 0 | I72: =SUM(I73:I120) -> 0 | ... N72: =SUM(N73:N120) -> 1267021.1 | O72: =+SUM($B72:$M72)-N72 -> 0 | P72: 00-000136 | S72: =H72/1000 -> 0
A73: Авторское вознаграждение | N73: =SUM(B73:M73) -> 0 | O73: =+SUM($B73:$M73)-N73 -> 0 | P73: 00-000156 | S73: =H73/1000 -> 0
A74: Агентское вознаграждение | D74: 1905 | E74: 1132.11 | F74: 214 | N74: =SUM(B74:M74) -> 3251.11 | O74: =+SUM($B74:$M74)-N74 -> 0 | P74: 00-000179 | S74: =H74/1000 -> 0
A75: Аренда оборудования | N75: =SUM(B75:M75) -> 0 | O75: =+SUM($B75:$M75)-N75 -> 0 | P75: 00-000317 | S75: =H75/1000 -> 0
A76: Банковские расходы текущие | D76: 74874.63 | E76: 168938.29 | F76: 192155.06 | G76: 178960.55 | N76: =SUM(B76:M76) -> 614928.53 | O76: =+SUM($B76:$M76)-N76 -> 0 | P76: 00-000067 | S76: =H76/1000 -> 0
A77: Благоустройство | N77: =SUM(B77:M77) -> 0 | O77: =+SUM($B77:$M77)-N77 -> 0 | P77: 00-000313 | S77: =H77/1000 -> 0
A78: Вентиляция | N78: =SUM(B78:M78) -> 0 | O78: =+SUM($B78:$M78)-N78 -> 0 | P78: 00-000109 | S78: =H78/1000 -> 0
A79: Ветеринарные исследования | N79: =SUM(B79:M79) -> 0 | O79: =+SUM($B79:$M79)-N79 -> 0 | P79: 00-000300 | S79: =H79/1000 -> 0
A80: Вознаграждение | N80: =SUM(B80:M80) -> 0 | O80: =+SUM($B80:$M80)-N80 -> 0 | P80: 00-000175 | S80: =H80/1000 -> 0
A81: Вывоз масла | N81: =SUM(B81:M81) -> 0 | O81: =+SUM($B81:$M81)-N81 -> 0 | P81: 00-000268 | S81: =H81/1000 -> 0
A82: Госпошлины, разрешительная документация (в т.ч. лицензии), оформление деятельности | N82: =SUM(B82:M82) -> 0 | O82: =+SUM($B82:$M82)-N82 -> 0 | P82: 00-000032 | S82: =H82/1000 -> 0
A83: Грузчики | N83: =SUM(B83:M83) -> 0 | O83: =+SUM($B83:$M83)-N83 -> 0 | P83: 00-000033 | S83: =H83/1000 -> 0
A84: Дератизация, дезинсекция | G84: 3900 | N84: =SUM(B84:M84) -> 3900 | O84: =+SUM($B84:$M84)-N84 -> 0 | P84: 00-000072 | S84: =H84/1000 -> 0
A85: Доставка газет | N85: =SUM(B85:M85) -> 0 | O85: =+SUM($B85:$M85)-N85 -> 0 | P85: 00-000212 | S85: =H85/1000 -> 0
A86: Интернет, телефония | E86: 6924.74 | F86: 10099.12 | G86: 12164.34 | N86: =SUM(B86:M86) -> 29188.2 | O86: =+SUM($B86:$M86)-N86 -> 0 | P86: 00-000073 | S86: =H86/1000 -> 0
A87: Консьерж Сервис | D87: 15491.07 | E87: 26605.47 | F87: 21519.19 | G87: 11321.6 | N87: =SUM(B87:M87) -> 74937.33 | O87: =+SUM($B87:$M87)-N87 -> 0 | P87: 00-000331 | S87: =H87/1000 -> 0
A88: Лабораторные исследования | N88: =SUM(B88:M88) -> 0 | O88: =+SUM($B88:$M88)-N88 -> 0 | P88: 00-000164 | S88: =H88/1000 -> 0
A89: Летняя терраса | N89: =SUM(B89:M89) -> 0 | O89: =+SUM($B89:$M89)-N89 -> 0 | P89: 00-000296 | S89: =H89/1000 -> 0
A90: Максбонус | E90: 3000 | F90: 3000 | G90: 3000 | N90: =SUM(B90:M90) -> 9000 | O90: =+SUM($B90:$M90)-N90 -> 0 | P90: 00-000381 | S90: =H90/1000 -> 0
A91: Мастер-классы детские | N91: =SUM(B91:M91) -> 0 | O91: =+SUM($B91:$M91)-N91 -> 0 | P91: 00-000011 | S91: =H91/1000 -> 0
A92: Монтаж/демонтаж летней террасы | N92: =SUM(B92:M92) -> 0 | O92: =+SUM($B92:$M92)-N92 -> 0 | P92: 00-000186 | S92: =H92/1000 -> 0
A93: Монтажные/демонтажные работы | F93: 28620 | N93: =SUM(B93:M93) -> 28620 | O93: =+SUM($B93:$M93)-N93 -> 0 | P93: 00-000168 | S93: =H93/1000 -> 0
A94: Мытье окон | N94: =SUM(B94:M94) -> 0 | O94: =+SUM($B94:$M94)-N94 -> 0 | P94: 00-000158 | S94: =H94/1000 -> 0
A95: Обслуживание инвентаря/посуды | N95: =SUM(B95:M95) -> 0 | O95: =+SUM($B95:$M95)-N95 -> 0 | P95: 00-000314 | S95: =H95/1000 -> 0
A96: Обучение студентов | N96: =SUM(B96:M96) -> 0 | O96: =+SUM($B96:$M96)-N96 -> 0 | P96: 00-000269 | S96: =H96/1000 -> 0
A97: Охрана, сигнализация | F97: 8922 | G97: 9850 | N97: =SUM(B97:M97) -> 18772 | O97: =+SUM($B97:$M97)-N97 -> 0 | P97: 00-000077 | S97: =H97/1000 -> 0
A98: Правовые системы | N98: =SUM(B98:M98) -> 0 | O98: =+SUM($B98:$M98)-N98 -> 0 | P98: 00-000214 | S98: =H98/1000 -> 0
A99: Программное обеспечение | E99: 26889 | F99: 22100 | G99: 31389 | N99: =SUM(B99:M99) -> 80378 | O99: =+SUM($B99:$M99)-N99 -> 0 | P99: 00-000084 | S99: =H99/1000 -> 0
A100: Ремонт имущества | F100: 10643 | G100: 1843 | N100: =SUM(B100:M100) -> 12486 | O100: =+SUM($B100:$M100)-N100 -> 0 | P100: 00-000104 | S100: =H100/1000 -> 0
A101: Ремонт текущий | F101: 5500 | G101: 1000 | N101: =SUM(B101:M101) -> 6500 | O101: =+SUM($B101:$M101)-N101 -> 0 | P101: 00-000105 | S101: =H101/1000 -> 0
...

Sheet расходы Доп.подразделение
A1: Статьи расходов | B1: январь | C1: февраль | D1: март | E1: апрель | F1: май | G1: июнь | H1: июль | I1: август | J1: сентябрь | K1: октябрь | L1: ноябрь | M1: декабрь | N1: Итого | O1: Проверка | P1: Код
A2: Расходы на персонал | B2: =+B3+B14+B18 -> 0 | C2: =+C3+C14+C18 -> 0 | D2: =+D3+D14+D18 -> 0 | E2: =+E3+E14+E18 -> 0 | F2: =+F3+F14+F18 -> 0 | G2: =+G3+G14+G18 -> 0 | H2: =+H3+H14+H18 -> 0 | I2: =+I3+I14+I18 -> 0 | ... N2: =+N3+N14+N18 -> 0 | O2: =+SUM($B2:$M2)-N2 -> 0 | P2: 00-000406 | S2: =H2/1000 -> 0
A3: Фонд оплаты труда | B3: =SUM(B4:B13) -> 0 | C3: =SUM(C4:C13) -> 0 | D3: =SUM(D4:D13) -> 0 | E3: =SUM(E4:E13) -> 0 | F3: =SUM(F4:F13) -> 0 | G3: =SUM(G4:G13) -> 0 | H3: =SUM(H4:H13) -> 0 | I3: =SUM(I4:I13) -> 0 | ... N3: =SUM(N4:N13) -> 0 | O3: =+SUM($B3:$M3)-N3 -> 0 | P3: 00-000174 | S3: =H3/1000 -> 0
A4: 01 ЗП Кухня | N4: =SUM(B4:M4) -> 0 | O4: =+SUM($B4:$M4)-N4 -> 0 | P4: 00-000420 | S4: =H4/1000 -> 0
A5: 02 ЗП Зал | N5: =SUM(B5:M5) -> 0 | O5: =+SUM($B5:$M5)-N5 -> 0 | P5: 00-000421 | S5: =H5/1000 -> 0
A6: 03 ЗП Клининг | N6: =SUM(B6:M6) -> 0 | O6: =+SUM($B6:$M6)-N6 -> 0 | P6: 00-000422 | S6: =H6/1000 -> 0
A7: 04 ЗП Прочие | N7: =SUM(B7:M7) -> 0 | O7: =+SUM($B7:$M7)-N7 -> 0 | P7: 00-000423 | S7: =H7/1000 -> 0
A8: Больничный | N8: =SUM(B8:M8) -> 0 | O8: =+SUM($B8:$M8)-N8 -> 0 | P8: 00-000221 | S8: =H8/1000 -> 0
A9: Доплаты индивидуальные | N9: =SUM(B9:M9) -> 0 | O9: =+SUM($B9:$M9)-N9 -> 0 | P9: 00-000259 | S9: =H9/1000 -> 0
A10: Материальная помощь | N10: =SUM(B10:M10) -> 0 | O10: =+SUM($B10:$M10)-N10 -> 0 | P10: 00-000270 | S10: =H10/1000 -> 0
A11: Отпускные | N11: =SUM(B11:M11) -> 0 | O11: =+SUM($B11:$M11)-N11 -> 0 | P11: 00-000163 | S11: =H11/1000 -> 0
A12: Пособия | N12: =SUM(B12:M12) -> 0 | O12: =+SUM($B12:$M12)-N12 -> 0 | P12: 00-000250 | S12: =H12/1000 -> 0
A13: Премии | N13: =SUM(B13:M13) -> 0 | O13: =+SUM($B13:$M13)-N13 -> 0 | P13: 00-000172 | S13: =H13/1000 -> 0
A14: Налоги ФОТ | B14: =SUM(B15:B17) -> 0 | C14: =SUM(C15:C17) -> 0 | D14: =SUM(D15:D17) -> 0 | E14: =SUM(E15:E17) -> 0 | F14: =SUM(F15:F17) -> 0 | G14: =SUM(G15:G17) -> 0 | H14: =SUM(H15:H17) -> 0 | I14: =SUM(I15:I17) -> 0 | ... N14: =SUM(N15:N17) -> 0 | O14: =+SUM($B14:$M14)-N14 -> 0 | P14: 00-000424 | S14: =H14/1000 -> 0
A15: Взносы ФОТ | N15: =SUM(B15:M15) -> 0 | O15: =+SUM($B15:$M15)-N15 -> 0 | P15: 00-000425 | S15: =H15/1000 -> 0
A16: НДФЛ ФОТ | N16: =SUM(B16:M16) -> 0 | O16: =+SUM($B16:$M16)-N16 -> 0 | P16: 00-000069 | S16: =H16/1000 -> 0
A17: Самозанятые комиссия | N17: =SUM(B17:M17) -> 0 | O17: =+SUM($B17:$M17)-N17 -> 0 | P17: 00-000005 | S17: =H17/1000 -> 0
A18: Затраты на персонал | B18: =SUM(B19:B26) -> 0 | C18: =SUM(C19:C26) -> 0 | D18: =SUM(D19:D26) -> 0 | E18: =SUM(E19:E26) -> 0 | F18: =SUM(F19:F26) -> 0 | G18: =SUM(G19:G26) -> 0 | H18: =SUM(H19:H26) -> 0 | I18: =SUM(I19:I26) -> 0 | ... N18: =SUM(N19:N26) -> 0 | O18: =+SUM($B18:$M18)-N18 -> 0 | P18: 00-000272 | S18: =H18/1000 -> 0
A19: Компенсация проезда | N19: =SUM(B19:M19) -> 0 | O19: =+SUM($B19:$M19)-N19 -> 0 | P19: 00-000343 | S19: =H19/1000 -> 0
A20: Медосмотр сотрудников | N20: =SUM(B20:M20) -> 0 | O20: =+SUM($B20:$M20)-N20 -> 0 | P20: 00-000301 | S20: =H20/1000 -> 0
A21: Оплата проживания | N21: =SUM(B21:M21) -> 0 | O21: =+SUM($B21:$M21)-N21 -> 0 | P21: 00-000345 | S21: =H21/1000 -> 0
A22: Питание штата | N22: =SUM(B22:M22) -> 0 | O22: =+SUM($B22:$M22)-N22 -> 0 | P22: 00-000061 | S22: =H22/1000 -> 0
A23: Подарки сотрудникам | N23: =SUM(B23:M23) -> 0 | O23: =+SUM($B23:$M23)-N23 -> 0 | P23: 00-000025 | S23: =H23/1000 -> 0
A24: Содержание столовой | N24: =SUM(B24:M24) -> 0 | O24: =+SUM($B24:$M24)-N24 -> 0 | P24: 00-000303 | S24: =H24/1000 -> 0
A25: Сотовая связь | N25: =SUM(B25:M25) -> 0 | O25: =+SUM($B25:$M25)-N25 -> 0 | P25: 00-000095 | S25: =H25/1000 -> 0
A26: Спецодежда | N26: =SUM(B26:M26) -> 0 | O26: =+SUM($B26:$M26)-N26 -> 0 | P26: 00-000094 | S26: =H26/1000 -> 0
A28: Арендные платежи | B28: =SUM(B30:B40) -> 0 | C28: =SUM(C30:C40) -> 0 | D28: =SUM(D30:D40) -> 0 | E28: =SUM(E30:E40) -> 0 | F28: =SUM(F30:F40) -> 0 | G28: =SUM(G30:G40) -> 0 | H28: =SUM(H30:H40) -> 0 | I28: =SUM(I30:I40) -> 0 | ... N28: =SUM(N30:N40) -> 0 | O28: =+SUM($B28:$M28)-N28 -> 0 | P28: 00-000181 | S28: =H28/1000 -> 0
A29: Аренда алкогольного склада | N29: =SUM(B29:M29) -> 0 | O29: =+SUM($B29:$M29)-N29 -> 0 | P29: 00-000187 | S29: =H29/1000 -> 0
A30: Аренда гаража | N30: =SUM(B30:M30) -> 0 | O30: =+SUM($B30:$M30)-N30 -> 0 | P30: 00-000298 | S30: =H30/1000 -> 0
A31: Аренда заведения | N31: =SUM(B31:M31) -> 0 | O31: =+SUM($B31:$M31)-N31 -> 0 | P31: 00-000026 | S31: =H31/1000 -> 0
A32: Аренда земельного участка | N32: =SUM(B32:M32) -> 0 | O32: =+SUM($B32:$M32)-N32 -> 0 | P32: 00-000348 | S32: =H32/1000 -> 0
A33: Аренда имущества | N33: =SUM(B33:M33) -> 0 | O33: =+SUM($B33:$M33)-N33 -> 0 | P33: 00-000312 | S33: =H33/1000 -> 0
A34: Аренда офисов | N34: =SUM(B34:M34) -> 0 | O34: =+SUM($B34:$M34)-N34 -> 0 | P34: 00-000182 | S34: =H34/1000 -> 0
A35: Аренда парковочных мест | N35: =SUM(B35:M35) -> 0 | O35: =+SUM($B35:$M35)-N35 -> 0 | P35: 00-000332 | S35: =H35/1000 -> 0
A36: Аренда помещения мусорокамеры (Капитанская 12) | N36: =SUM(B36:M36) -> 0 | O36: =+SUM($B36:$M36)-N36 -> 0 | P36: 00-000193 | S36: =H36/1000 -> 0
A37: Аренда склада | N37: =SUM(B37:M37) -> 0 | O37: =+SUM($B37:$M37)-N37 -> 0 | P37: 00-000204 | S37: =H37/1000 -> 0
A38: Аренда склада Гладкова | N38: =SUM(B38:M38) -> 0 | O38: =+SUM($B38:$M38)-N38 -> 0 | P38: 00-000215 | S38: =H38/1000 -> 0
A39: Аренда цеха | N39: =SUM(B39:M39) -> 0 | O39: =+SUM($B39:$M39)-N39 -> 0 | P39: 00-000203 | S39: =H39/1000 -> 0
A40: Услуги автопарковки | N40: =SUM(B40:M40) -> 0 | O40: =+SUM($B40:$M40)-N40 -> 0 | P40: 00-000341 | S40: =H40/1000 -> 0
A41: Коммунальные расходы | B41: =SUM(B42:B50) -> 0 | C41: =SUM(C42:C50) -> 0 | D41: =SUM(D42:D50) -> 0 | E41: =SUM(E42:E50) -> 0 | F41: =SUM(F42:F50) -> 0 | G41: =SUM(G42:G50) -> 0 | H41: =SUM(H42:H50) -> 0 | I41: =SUM(I42:I50) -> 0 | ... N41: =SUM(N42:N50) -> 0 | O41: =+SUM($B41:$M41)-N41 -> 0 | P41: 00-000180 | S41: =H41/1000 -> 0
A42: Водоснабжение | N42: =SUM(B42:M42) -> 0 | O42: =+SUM($B42:$M42)-N42 -> 0 | P42: 00-000254 | S42: =H42/1000 -> 0
A43: Вывоз мусора | N43: =SUM(B43:M43) -> 0 | O43: =+SUM($B43:$M43)-N43 -> 0 | P43: 00-000060 | S43: =H43/1000 -> 0
A44: Коммунальные платежи | N44: =SUM(B44:M44) -> 0 | O44: =+SUM($B44:$M44)-N44 -> 0 | P44: 00-000027 | S44: =H44/1000 -> 0
A45: Коммунальные расходы офисы | N45: =SUM(B45:M45) -> 0 | O45: =+SUM($B45:$M45)-N45 -> 0 | P45: 00-000257 | S45: =H45/1000 -> 0
A46: Сброс отходов | N46: =SUM(B46:M46) -> 0 | O46: =+SUM($B46:$M46)-N46 -> 0 | P46: 00-000366 | S46: =H46/1000 -> 0
A47: Содержание мест общего пользования (эксплуатационные расходы) | N47: =SUM(B47:M47) -> 0 | O47: =+SUM($B47:$M47)-N47 -> 0 | P47: 00-000258 | S47: =H47/1000 -> 0
A48: Стоки. Водоотведение | N48: =SUM(B48:M48) -> 0 | O48: =+SUM($B48:$M48)-N48 -> 0 | P48: 00-000255 | S48: =H48/1000 -> 0
A49: Теплоснабжение | N49: =SUM(B49:M49) -> 0 | O49: =+SUM($B49:$M49)-N49 -> 0 | P49: 00-000256 | S49: =H49/1000 -> 0
A50: Электроэнергия | N50: =SUM(B50:M50) -> 0 | O50: =+SUM($B50:$M50)-N50 -> 0 | P50: 00-000253 | S50: =H50/1000 -> 0
A51: Прочие ОФР/Деко | B51: =B52+B59+B65+B72+B121+B147 -> 0 | C51: =C52+C59+C65+C72+C121+C147 -> 0 | D51: =D52+D59+D65+D72+D121+D147 -> 0 | E51: =E52+E59+E65+E72+E121+E147 -> 0 | F51: =F52+F59+F65+F72+F121+F147 -> 0 | G51: =G52+G59+G65+G72+G121+G147 -> 0 | H51: =H52+H59+H65+H72+H121+H147 -> 0 | I51: =I52+I59+I65+I72+I121+I147 -> 0 | ... N51: =N52+N59+N65+N72+N121+N147 -> 0 | O51: =+SUM($B51:$M51)-N51 -> 0 | P51: 00-000344 | S51: =H51/1000 -> 0
A52: HR Маркетинг | B52: =SUM(B53:B58) -> 0 | C52: =SUM(C53:C58) -> 0 | D52: =SUM(D53:D58) -> 0 | E52: =SUM(E53:E58) -> 0 | F52: =SUM(F53:F58) -> 0 | G52: =SUM(G53:G58) -> 0 | H52: =SUM(H53:H58) -> 0 | I52: =SUM(I53:I58) -> 0 | ... N52: =SUM(N53:N58) -> 0 | O52: =+SUM($B52:$M52)-N52 -> 0 | P52: 00-000339 | S52: =H52/1000 -> 0
A53: HR Маркетинг | N53: =SUM(B53:M53) -> 0 | O53: =+SUM($B53:$M53)-N53 -> 0 | P53: 00-000329 | S53: =H53/1000 -> 0
A54: Командировочные расходы | N54: =SUM(B54:M54) -> 0 | O54: =+SUM($B54:$M54)-N54 -> 0 | P54: 00-000074 | S54: =H54/1000 -> 0
A55: Корпоративные мероприятия | N55: =SUM(B55:M55) -> 0 | O55: =+SUM($B55:$M55)-N55 -> 0 | P55: 00-000293 | S55: =H55/1000 -> 0
A56: Обучение персонала | N56: =SUM(B56:M56) -> 0 | O56: =+SUM($B56:$M56)-N56 -> 0 | P56: 00-000142 | S56: =H56/1000 -> 0
A57: Подбор персонала | N57: =SUM(B57:M57) -> 0 | O57: =+SUM($B57:$M57)-N57 -> 0 | P57: 00-000347 | S57: =H57/1000 -> 0
A58: Развитие насмотренности | N58: =SUM(B58:M58) -> 0 | O58: =+SUM($B58:$M58)-N58 -> 0 | P58: 00-000340 | S58: =H58/1000 -> 0
A59: Праздники | B59: =SUM(B60:B64) -> 0 | C59: =SUM(C60:C64) -> 0 | D59: =SUM(D60:D64) -> 0 | E59: =SUM(E60:E64) -> 0 | F59: =SUM(F60:F64) -> 0 | G59: =SUM(G60:G64) -> 0 | H59: =SUM(H60:H64) -> 0 | I59: =SUM(I60:I64) -> 0 | ... N59: =SUM(N60:N64) -> 0 | O59: =+SUM($B59:$M59)-N59 -> 0 | P59: 00-000350 | S59: =SUM(S60:S64) -> 0
A60: 23 февраля | N60: =SUM(B60:M60) -> 0 | O60: =+SUM($B60:$M60)-N60 -> 0 | P60: 00-000355 | S60: =H60/1000 -> 0
A61: 8 марта | N61: =SUM(B61:M61) -> 0 | O61: =+SUM($B61:$M61)-N61 -> 0 | P61: 00-000354 | S61: =H61/1000 -> 0
A62: День рождения Беллини | N62: =SUM(B62:M62) -> 0 | O62: =+SUM($B62:$M62)-N62 -> 0 | P62: 00-000353 | S62: =H62/1000 -> 0
A63: Елка БГ | N63: =SUM(B63:M63) -> 0 | O63: =+SUM($B63:$M63)-N63 -> 0 | P63: 00-000358 | S63: =H63/1000 -> 0
A64: Новый Год | N64: =SUM(B64:M64) -> 0 | O64: =+SUM($B64:$M64)-N64 -> 0 | P64: 00-000356 | S64: =H64/1000 -> 0
A65: Транспортные расходы | B65: =SUM(B66:B71) -> 0 | C65: =SUM(C66:C71) -> 0 | D65: =SUM(D66:D71) -> 0 | E65: =SUM(E66:E71) -> 0 | F65: =SUM(F66:F71) -> 0 | G65: =SUM(G66:G71) -> 0 | H65: =SUM(H66:H71) -> 0 | I65: =SUM(I66:I71) -> 0 | ... N65: =SUM(N66:N71) -> 0 | O65: =+SUM($B65:$M65)-N65 -> 0 | P65: 00-000150 | S65: =H65/1000 -> 0
A66: Амортизация машины экспедитора | N66: =SUM(B66:M66) -> 0 | O66: =+SUM($B66:$M66)-N66 -> 0 | P66: 00-000216 | S66: =H66/1000 -> 0
A67: Бензин | N67: =SUM(B67:M67) -> 0 | O67: =+SUM($B67:$M67)-N67 -> 0 | P67: 00-000043 | S67: =H67/1000 -> 0
A68: Содержание а/м | N68: =SUM(B68:M68) -> 0 | O68: =+SUM($B68:$M68)-N68 -> 0 | P68: 00-000140 | S68: =H68/1000 -> 0
A69: Такси | N69: =SUM(B69:M69) -> 0 | O69: =+SUM($B69:$M69)-N69 -> 0 | P69: 00-000080 | S69: =H69/1000 -> 0
A70: Такси завтраки | N70: =SUM(B70:M70) -> 0 | O70: =+SUM($B70:$M70)-N70 -> 0 | P70: 00-000276 | S70: =H70/1000 -> 0
A71: Транспортные расходы текущие | N71: =SUM(B71:M71) -> 0 | O71: =+SUM($B71:$M71)-N71 -> 0 | P71: 00-000089 | S71: =H71/1000 -> 0
A72: Услуги, в т.ч. | B72: =SUM(B73:B120) -> 0 | C72: =SUM(C73:C120) -> 0 | D72: =SUM(D73:D120) -> 0 | E72: =SUM(E73:E120) -> 0 | F72: =SUM(F73:F120) -> 0 | G72: =SUM(G73:G120) -> 0 | H72: =SUM(H73:H120) -> 0 | I72: =SUM(I73:I120) -> 0 | ... N72: =SUM(N73:N120) -> 0 | O72: =+SUM($B72:$M72)-N72 -> 0 | S72: =H72/1000 -> 0
A73: Авторское вознаграждение | N73: =SUM(B73:M73) -> 0 | O73: =+SUM($B73:$M73)-N73 -> 0 | P73: 00-000156 | S73: =H73/1000 -> 0
A74: Агентское вознаграждение | N74: =SUM(B74:M74) -> 0 | O74: =+SUM($B74:$M74)-N74 -> 0 | P74: 00-000179 | S74: =H74/1000 -> 0
A75: Аренда оборудования | N75: =SUM(B75:M75) -> 0 | O75: =+SUM($B75:$M75)-N75 -> 0 | P75: 00-000317 | S75: =H75/1000 -> 0
A76: Банковские расходы текущие | N76: =SUM(B76:M76) -> 0 | O76: =+SUM($B76:$M76)-N76 -> 0 | P76: 00-000067 | S76: =H76/1000 -> 0
A77: Благоустройство | N77: =SUM(B77:M77) -> 0 | O77: =+SUM($B77:$M77)-N77 -> 0 | P77: 00-000313 | S77: =H77/1000 -> 0
A78: Вентиляция | N78: =SUM(B78:M78) -> 0 | O78: =+SUM($B78:$M78)-N78 -> 0 | P78: 00-000109 | S78: =H78/1000 -> 0
A79: Ветеринарные исследования | N79: =SUM(B79:M79) -> 0 | O79: =+SUM($B79:$M79)-N79 -> 0 | P79: 00-000300 | S79: =H79/1000 -> 0
A80: Вознаграждение | N80: =SUM(B80:M80) -> 0 | O80: =+SUM($B80:$M80)-N80 -> 0 | P80: 00-000175 | S80: =H80/1000 -> 0
A81: Вывоз масла | N81: =SUM(B81:M81) -> 0 | O81: =+SUM($B81:$M81)-N81 -> 0 | P81: 00-000268 | S81: =H81/1000 -> 0
A82: Госпошлины, разрешительная документация (в т.ч. лицензии), оформление деятельности | N82: =SUM(B82:M82) -> 0 | O82: =+SUM($B82:$M82)-N82 -> 0 | P82: 00-000032 | S82: =H82/1000 -> 0
A83: Грузчики | N83: =SUM(B83:M83) -> 0 | O83: =+SUM($B83:$M83)-N83 -> 0 | P83: 00-000033 | S83: =H83/1000 -> 0
A84: Дератизация, дезинсекция | N84: =SUM(B84:M84) -> 0 | O84: =+SUM($B84:$M84)-N84 -> 0 | P84: 00-000072 | S84: =H84/1000 -> 0
... A120: Электроработы | N120: =SUM(B120:M120) -> 0 | O120: =+SUM($B120:$M120)-N120 -> 0 | P120: 00-000188 | S120: =H120/1000 -> 0
A121: Хозрасходы | B121: =SUM(B122:B146) -> 0 | C121: =SUM(C122:C146) -> 0 | D121: =SUM(D122:D146) -> 0 | E121: =SUM(E122:E146) -> 0 | F121: =SUM(F122:F146) -> 0 | G121: =SUM(G122:G146) -> 0 | H121: =SUM(H122:H146) -> 0 | I121: =SUM(I122:I146) -> 0 | ... N121: =SUM(N122:N146) -> 0 | O121: =+SUM($B121:$M121)-N121 -> 0 | P121: 00-000134 | S121: =H121/1000 -> 0
A122: Антиковидные расходы (перчатки, маски, санитайзер) | N122: =SUM(B122:M122) -> 0 | O122: =+SUM($B122:$M122)-N122 -> 0 | P122: 00-000311 | S122: =H122/1000 -> 0
A123: Бейджи, номерки, таблички, монетницы | N123: =SUM(B123:M123) -> 0 | O123: =+SUM($B123:$M123)-N123 -> 0 | P123: 00-000135 | S123: =H123/1000 -> 0
A124: Бонусные карты | N124: =SUM(B124:M124) -> 0 | O124: =+SUM($B124:$M124)-N124 -> 0 | P124: 00-000249 | S124: =H124/1000 -> 0
A125: Бытовая химия | N125: =SUM(B125:M125) -> 0 | O125: =+SUM($B125:$M125)-N125 -> 0 | P125: 00-000071 | S125: =H125/1000 -> 0
A126: Вода питьевая | N126: =SUM(B126:M126) -> 0 | O126: =+SUM($B126:$M126)-N126 -> 0 | P126: 00-000149 | S126: =H126/1000 -> 0
A127: Декор | N127: =SUM(B127:M127) -> 0 | O127: =+SUM($B127:$M127)-N127 -> 0 | P127: 00-000137 | S127: =H127/1000 -> 0
A128: Детская комната (канцелярия, игрушки, браслеты) | N128: =SUM(B128:M128) -> 0 | O128: =+SUM($B128:$M128)-N128 -> 0 | P128: 00-000157 | S128: =H128/1000 -> 0
A129: Канцелярия | N129: =SUM(B129:M129) -> 0 | O129: =+SUM($B129:$M129)-N129 -> 0 | P129: 00-000063 | S129: =H129/1000 -> 0
A130: Комплектующие к товарным позициям | N130: =SUM(B130:M130) -> 0 | O130: =+SUM($B130:$M130)-N130 -> 0 | P130: 00-000243 | S130: =H130/1000 -> 0
A131: Малоценное имущество | N131: =SUM(B131:M131) -> 0 | O131: =+SUM($B131:$M131)-N131 -> 0 | P131: 00-000075 | S131: =H131/1000 -> 0
A132: Медикаменты | N132: =SUM(B132:M132) -> 0 | O132: =+SUM($B132:$M132)-N132 -> 0 | P132: 00-000076 | S132: =H132/1000 -> 0
A133: Одноразовые приборы | N133: =SUM(B133:M133) -> 0 | O133: =+SUM($B133:$M133)-N133 -> 0 | P133: 00-000398 | S133: =H133/1000 -> 0
... A146: Электроматериалы | N146: =SUM(B146:M146) -> 0 | O146: =+SUM($B146:$M146)-N146 -> 0 | P146: 00-000064 | S146: =H146/1000 -> 0
A147: Прочие расходы | B147: =SUM(B148:B153) -> 0 | C147: =SUM(C148:C153) -> 0 | D147: =SUM(D148:D153) -> 0 | E147: =SUM(E148:E153) -> 0 | F147: =SUM(F148:F153) -> 0 | G147: =SUM(G148:G153) -> 0 | H147: =SUM(H148:H153) -> 0 | I147: =SUM(I148:I153) -> 0 | ... N147: =SUM(N148:N153) -> 0 | O147: =+SUM($B147:$M147)-N147 -> 0 | P147: 00-000185 | S147: =H147/1000 -> 0
A148: Детский клуб | N148: =B148+C148+D148+E148+F148+G148+H148+I148+J148+K148+L148+M148 -> 0 | O148: =+SUM($B148:$M148)-N148 -> 0 | P148: 00-000170 | S148: =H148/1000 -> 0
...

Sheet баланс
B1: 46022 | C1: 46053 | D1: 46081 | E1: 46112 | F1: 46142 | G1: 46173 | H1: 46203 | I1: 46234 | J1: 46265 | K1: 46295 | L1: 46326 | M1: 46356 | N1: 46387 | Q1: =+G1 -> 46173
A2: Актив | Q2: =-(G9-G20)/1000 -> -828.67886
A3: Текущие активы
A4: руб. | E4: 50072.57 | F4: 166003.53 | G4: 174229.79 | H4: 643865.9
A5: Б/нал | D5: 11688.95 | E5: 2944817.9 | F5: 393968.96 | G5: 1539376.4 | H5: 579478.31
A6: Подотчеты | D6: 405812 | E6: 209552.61 | F6: 174126.4 | G6: 48924.81 | H6: 62537.58
A7: Покупатели | E7: -70000 | F7: -96620 | G7: -45638.4 | H7: -19100.08
A8: Бонусный счет | E8: -3000 | F8: =27333.99-17446.47 -> 9887.52 | G8: =29259.99 -> 29259.99 | H8: 922511.1
A9: Запасы (товары на складе) | D9: 474058.45 | E9: 2318952.8 | F9: 3001149 | G9: 2722690.5 | H9: 2687852.2
A10: Итого по разделу №1 | B10: =SUM(B4:B9) -> 0 | C10: =SUM(C4:C9) -> 0 | D10: =SUM(D4:D9) -> 891559.4 | E10: =SUM(E4:E9) -> 5450395.9 | F10: =SUM(F4:F9) -> 3648515.4 | G10: =SUM(G4:G9) -> 4468843.1 | H10: =SUM(H4:H9) -> 4877145 | I10: =SUM(I4:I9) -> 0 | ... N10: =SUM(N4:N9) -> 0
A11: Внеоборотные активы
A12: Инвестиционные расходы | D12: 45981733 | E12: 53336355 | F12: 55126452 | G12: 56899699 | H12: 57501542
A13: Имущество | D13: 22609582 | E13: 26301554 | F13: 26841221 | G13: 31848980 | H13: 32538728
A14: Итого по разделу №2 | B14: =SUM(B12:B13) -> 0 | C14: =SUM(C12:C13) -> 0 | D14: =SUM(D12:D13) -> 68591315 | E14: =SUM(E12:E13) -> 79637909 | F14: =SUM(F12:F13) -> 81967673 | G14: =SUM(G12:G13) -> 88748680 | H14: =SUM(H12:H13) -> 90040270 | I14: =SUM(I12:I13) -> 0 | ... N14: =SUM(N12:N13) -> 0
A15: Баланс | B15: =B14+B10 -> 0 | C15: =C14+C10 -> 0 | D15: =D14+D10 -> 69482874 | E15: =E14+E10 -> 85088305 | F15: =F14+F10 -> 85616189 | G15: =G14+G10 -> 93217523 | H15: =H14+H10 -> 94917415 | I15: =I14+I10 -> 0 | ... N15: =N14+N10 -> 0
A16: Пассив
A17: Привлеченный капитал
A18: Кредиторы БГ (67сч) | D18: 5017381.1 | E18: 6355983.9 | F18: 5216340.7 | G18: 6298090.8 | H18: 6436219.2
A19: Займы персоналу (73сч)
A20: Поставщик продуктов | E20: =-1757749*2+1948891.68 -> -1566606.3 | F20: 1855387 | G20: 1894011.7 | H20: 1806923.7
A21: Расчеты с поставщиками хозтоваров и услуг | D21: -6191978.3 | E21: -191142.68 | F21: -4269661 | G21: -51312.6 | H21: 84531.66
A22: Расчеты с бюджетом | D22: -49262.93 | E22: 6913.83 | F22: 77156.88 | G22: 219836.18 | H22: 360894.18
A23: Зарплата персонала | D23: 654421.79 | E23: 1830983 | F23: 2116146 | G23: 2163261.9 | H23: 1883777.5
A24: Прочие дебиторы, кредиторы | E24: -58618
A25: Займы внутренние
A26: Расчеты по кредитам и займам
A27: Расчеты с учред.(взносы в УК) | D27: 70052312 | E27: 77514493 | F27: 77629613 | G27: 77629613 | H27: 77629613
A28: Итого по разделу №1 | B28: =SUM(B18:B27) -> 0 | C28: =SUM(C18:C27) -> 0 | D28: =SUM(D18:D27) -> 69482874 | E28: =SUM(E18:E27) -> 83892007 | F28: =SUM(F18:F27) -> 82624983 | G28: =SUM(G18:G27) -> 88153501 | H28: =SUM(H18:H27) -> 88201960 | I28: =SUM(I18:I27) -> 0 | ... N28: =SUM(N18:N27) -> 0
A29: Собственный капитал
A30: Фонды собственных средств | B30: =B15-B28 -> 0 | C30: =C15-C28 -> 0 | D30: =D15-D28 -> 0 | E30: =E15-E28 -> 1196298.1 | F30: =F15-F28 -> 2991205.6 | G30: =G15-G28 -> 5064021.7 | H30: =H15-H28 -> 6715455.4 | I30: =I15-I28 -> 0 | ... N30: =N15-N28 -> 0
A31: Изменение собственных средств | C31: =B30 -> 0 | D31: =C30 -> 0 | E31: =D30 -> 0 | F31: =E30 -> 1196298.1 | G31: =F30 -> 2991205.6 | H31: =G30 -> 5064021.7 | I31: =H30 -> 6715455.4 | J31: =I30 -> 0 | ... N31: =M30 -> 0
A32: Итого по разделу №2 | B32: =SUM(B30) -> 0 | C32: =SUM(C30) -> 0 | D32: =SUM(D30) -> 0 | E32: =SUM(E30) -> 1196298.1 | F32: =SUM(F30) -> 2991205.6 | G32: =SUM(G30) -> 5064021.7 | H32: =SUM(H30) -> 6715455.4 | I32: =SUM(I30) -> 0 | ... N32: =SUM(N30) -> 0
A33: Баланс | B33: =B32+B28 -> 0 | C33: =C32+C28 -> 0 | D33: =D32+D28 -> 69482874 | E33: =E32+E28 -> 85088305 | F33: =F32+F28 -> 85616189 | G33: =G32+G28 -> 93217523 | H33: =H32+H28 -> 94917415 | I33: =I32+I28 -> 0 | ... N33: =N32+N28 -> 0
A35: Изменение активов: | B35: =[1]баланс!$P$38 -> 33798.32 | C35: =C30-C31 -> 0 | D35: =D30-D31 -> 0 | E35: =E30-E31 -> 1196298.1 | F35: =F30-F31 -> 1794907.5 | G35: =G30-G31 -> 2072816.1 | H35: =H30-H31 -> 1651433.6 | I35: =I30-I31 -> -6715455.4 | J35: =J30-J31 -> 0 | ... N35: =N30-N31 -> 0
A38: Справочно:Отчет о фин. рез. "Итоговое изменение активов" | C38: ='Отчет о фин.рез.'!B55 -> 0 | D38: ='Отчет о фин.рез.'!C55 -> 0 | E38: ='Отчет о фин.рез.'!D55 -> 1196.3515 | F38: ='Отчет о фин.рез.'!E55 -> 1794.5871 | G38: ='Отчет о фин.рез.'!F55 -> 2072.8161 | H38: ='Отчет о фин.рез.'!G55 -> 1651.4345 | I38: ='Отчет о фин.рез.'!H55 -> 0 | J38: ='Отчет о фин.рез.'!I55 -> 0 | ... N38: ='Отчет о фин.рез.'!M55 -> 0
A40: Проверка | C40: =+(C38*1000-C35) -> 0 | D40: =+(D38*1000-D35) -> 0 | E40: =+(E38*1000-E35) -> 53.39 | F40: =+(F38*1000-F35) -> -320.44 | G40: =+(G38*1000-G35) -> -0.039999994 | H40: =+(H38*1000-H35) -> 0.91000001 | I40: =+(I38*1000-I35) -> 6715455.4 | J40: =+(J38*1000-J35) -> 0 | ... N40: =+(N38*1000-N35) -> 0
C42: =C32+C27-C14 -> 0 | D42: =D32+D27-D14 -> 1460997.7 | E42: =E32+E27-E14 -> -927117.86 | F42: =F32+F24-F14 -> -78976467 | G42: =G32+G27-G14 -> -6055044.8 | H42: =H32+H27-H14 -> -5695201.2 | I42: =I32+I27-I14 -> 0 | J42: =J32+J27-J14 -> 0 | K42: =K32+K27-K14 -> 0 | L42: =L32+L27-L14 -> 0 | M42: =M32+M27-M14 -> 0 | N42: =N32+N27-N14 -> 0
A45: Имущество баланс | C45: =+SUM(C13:C13)-SUM(B13:B13) -> 0 | D45: =+SUM(D13:D13)-SUM(C13:C13) -> 22609582 | E45: =+SUM(E13:E13)-SUM(D13:D13) -> 3691972.4 | F45: =+SUM(F13:F13)-SUM(E13:E13) -> 539666.88 | G45: =+SUM(G13:G13)-SUM(F13:F13) -> 5007759.5 | H45: =+SUM(H13:H13)-SUM(G13:G13) -> 689747.06 | I45: =+SUM(I13:I13)-SUM(H13:H13) -> -32538728 | J45: =+SUM(J13:J13)-SUM(I13:I13) -> 0 | ... N45: =+SUM(N13:N13)-SUM(M13:M13) -> 0
A46: Имущество фин.рез | C46: ='Отчет о фин.рез.'!B57*1000 -> 0 | D46: ='Отчет о фин.рез.'!C57*1000 -> 22609582 | E46: ='Отчет о фин.рез.'!D57*1000 -> 3691972.4 | F46: ='Отчет о фин.рез.'!E57*1000 -> 539666.88 | G46: ='Отчет о фин.рез.'!F57*1000 -> 5007759.5 | H46: ='Отчет о фин.рез.'!G57*1000 -> 689747.06 | I46: ='Отчет о фин.рез.'!H57*1000 -> 0 | J46: ='Отчет о фин.рез.'!I57*1000 -> 0 | ... N46: ='Отчет о фин.рез.'!M57*1000 -> 0
A47: Проверка | C47: =+C45-C46 -> 0 | D47: =+D45-D46 -> 0 | E47: =+E45-E46 -> 0 | F47: =+F45-F46 -> -9.3132257e-10 | G47: =+G45-G46 -> 0 | H47: =+H45-H46 -> -1.2805685e-09 | I47: =+I45-I46 -> -32538728 | J47: =+J45-J46 -> 0 | ... N47: =+N45-N46 -> 0
A49: Инвестици баланс | C49: =+SUM(C12)-SUM(B12) -> 0 | D49: =+SUM(D12)-SUM(C12) -> 45981733 | E49: =+SUM(E12)-SUM(D12) -> 7354622.4 | F49: =+SUM(F12)-SUM(E12) -> 1790096.8 | G49: =+SUM(G12)-SUM(F12) -> 1773247.3 | H49: =+SUM(H12)-SUM(G12) -> 601842.96 | I49: =+SUM(I12)-SUM(H12) -> -57501542 | J49: =+SUM(J12)-SUM(I12) -> 0 | ... N49: =+SUM(N12)-SUM(M12) -> 0
A50: Инвестиции, финрез | C50: ='Отчет о фин.рез.'!B60*1000 -> 0 | D50: ='Отчет о фин.рез.'!C60*1000 -> 45981733 | E50: ='Отчет о фин.рез.'!D60*1000 -> 7354622.3 | F50: ='Отчет о фин.рез.'!E60*1000 -> 1790096.8 | G50: ='Отчет о фин.рез.'!F60*1000 -> 1773244.4 | H50: ='Отчет о фин.рез.'!G60*1000 -> 601842.96 | I50: ='Отчет о фин.рез.'!H60*1000 -> 0 | J50: ='Отчет о фин.рез.'!I60*1000 -> 0 | ... N50: ='Отчет о фин.рез.'!M60*1000 -> 0
A51: Проверка | C51: =+C49-C50 -> 0 | D51: =+D49-D50 -> 0 | E51: =+E49-E50 -> 0 | F51: =+F49-F50 -> 3.4924597e-09 | G51: =+G49-G50 -> 3 | H51: =+H49-H50 -> 9.3132257e-10 | I51: =+I49-I50 -> -57501542 | J51: =+J49-J50 -> 0 | ... N51: =+N49-N50 -> 0
A53: Возврат взносов УК, баланс | C53: =+SUM(C26:C27)-SUM(B26:B27) -> 0 | D53: =+SUM(D26:D27)-SUM(C26:C27) -> 70052312 | E53: =+SUM(E26:E27)-SUM(D26:D27) -> 7462181 | F53: =+SUM(F26:F27)-SUM(E26:E27) -> 115120 | G53: =+SUM(G26:G27)-SUM(F26:F27) -> 0 | H53: =+SUM(H26:H27)-SUM(G26:G27) -> 0 | I53: =+SUM(I26:I27)-SUM(H26:H27) -> -77629613 | J53: =+SUM(J26:J27)-SUM(I26:I27) -> 0 | ... N53: =+SUM(N26:N27)-SUM(M26:M27) -> 0
A54: Возврат взносов УК, финрез | C54: ='Отчет о фин.рез.'!B68*1000+'Отчет о фин.рез.'!B64*1000 -> 0 | D54: ='Отчет о фин.рез.'!C68*1000+'Отчет о фин.рез.'!C64*1000 -> -70052312 | E54: ='Отчет о фин.рез.'!D68*1000+'Отчет о фин.рез.'!D64*1000 -> -7462181 | F54: ='Отчет о фин.рез.'!E68*1000+'Отчет о фин.рез.'!E64*1000 -> -115120 | G54: ='Отчет о фин.рез.'!F68*1000+'Отчет о фин.рез.'!F64*1000 -> 0 | H54: ='Отчет о фин.рез.'!G68*1000+'Отчет о фин.рез.'!G64*1000 -> 0 | I54: ='Отчет о фин.рез.'!H68*1000+'Отчет о фин.рез.'!H64*1000 -> 0 | J54: ='Отчет о фин.рез.'!I68*1000+'Отчет о фин.рез.'!I64*1000 -> 0 | ... N54: ='Отчет о фин.рез.'!M68*1000+'Отчет о фин.рез.'!M64*1000 -> 0
A55: Проверка | C55: =+C53+C54 -> 0 | D55: =+D53+D54 -> 0 | E55: =+E53+E54 -> 0 | F55: =+F53+F54 -> 0 | G55: =+G53+G54 -> 0 | H55: =+H53+H54 -> 0 | I55: =+I53+I54 -> -77629613 | J55: =+J53+J54 -> 0 | ... N55: =+N53+N54 -> 0
A57: Средства, реально располагаемые в обороте | B57: =+SUM(B4:B9)-SUM(B19:B20,B21:B24) -> 0 | C57: =+SUM(C4:C9)-SUM(C19:C20,C21:C24) -> 0 | D57: =+SUM(D4:D9)-SUM(D19:D20,D21:D24) -> 6478378.8 | E57: =+SUM(E4:E9)-SUM(E19:E20,E21:E24) -> 5428866.1 | F57: =+SUM(F4:F9)-SUM(F19:F20,F21:F24) -> 3869486.6 | G57: =+SUM(G4:G9)-SUM(G19:G20,G21:G24) -> 243045.94 | H57: =+SUM(H4:H9)-SUM(H19:H20,H21:H24) -> 741017.99 | I57: =+SUM(I4:I9)-SUM(I19:I20,I21:I24) -> 0 | ... N57: =+SUM(N4:N9)-SUM(N19:N20,N21:N24) -> 0
A58: без учета бонусного и расчетов с учредителями | B58: =+SUM(B4:B6,B9)-SUM(B19:B23) -> 0 | C58: =+SUM(C4:C6,C9)-SUM(C19:C23) -> 0 | D58: =+SUM(D4:D6,D9)-SUM(D19:D23) -> 6478378.8 | E58: =+SUM(E4:E6,E9)-SUM(E19:E23) -> 5443248.1 | F58: =+SUM(F4:F6,F9)-SUM(F19:F23) -> 3956219.1 | G58: =+SUM(G4:G6,G9)-SUM(G19:G23) -> 259424.35 | H58: =+SUM(H4:H6,H9)-SUM(H19:H23) -> -162393.03 | I58: =+SUM(I4:I6,I9)-SUM(I19:I23) -> 0 | ... N58: =+SUM(N4:N6,N9)-SUM(N19:N23) -> 0
A59: Средства в обороте, баланс | B59: =+B10-SUM(B18:B25) -> 0 | C59: =+C10-SUM(C18:C25) -> 0 | D59: =+D10-SUM(D18:D25) -> 1460997.7 | E59: =+E10-SUM(E18:E25) -> -927117.86 | F59: =+F10-SUM(F18:F25) -> -1346854.1 | G59: =+G10-SUM(G18:G25) -> -6055044.8 | H59: =+H10-SUM(H18:H25) -> -5695201.2 | I59: =+I10-SUM(I18:I25) -> 0 | ... N59: =+N10-SUM(N18:N25) -> 0
A60: Средства в обороте, финрез | C60: ='Отчет о фин.рез.'!B74*1000 -> 0 | D60: ='Отчет о фин.рез.'!C74*1000 -> 1460997.7 | E60: ='Отчет о фин.рез.'!D74*1000 -> -927064.47 | F60: ='Отчет о фин.рез.'!E74*1000 -> -1347121.1 | G60: ='Отчет о фин.рез.'!F74*1000 -> -6055308.9 | H60: ='Отчет о фин.рез.'!G74*1000 -> -5695464.4 | I60: ='Отчет о фин.рез.'!H74*1000 -> -5695464.4 | J60: ='Отчет о фин.рез.'!I74*1000 -> -5695464.4 | ... N60: ='Отчет о фин.рез.'!M74*1000 -> -5695464.4
A61: Проверка | C61: =+C59-C60 -> 0 | D61: =+D59-D60 -> 7.4505806e-09 | E61: =+E59-E60 -> -53.39 | F61: =+F59-F60 -> 267.05 | G61: =+G59-G60 -> 264.09 | H61: =+H59-H60 -> 263.18 | I61: =+I59-I60 -> 5695464.4 | J61: =+J59-J60 -> 5695464.4 | ... N61: =+N59-N60 -> 5695464.4

Sheet Деление БарКухня
E1: 46023 | F1: 46054 | G1: 46082 | H1: 46113 | I1: 46143 | J1: 46174 | K1: 46204 | L1: 46235 | M1: 46266 | N1: 46296 | O1: 46327 | P1: 46357 | Q1: 46388
A2: Бенедикт | B2: Выручка | C2: Зал | D2: Кухня | G2: 3939956 | H2: 9041571.5 | I2: 10579404 | J2: 9819475.4 | Q2: =SUM(E2:P2) -> 33380407
A3: Бенедикт | B3: Выручка | C3: Зал | D3: Бар | G3: 1972289.5 | H3: 4568102.5 | I3: 5094849.5 | J3: 4417617.6 | Q3: =SUM(E3:P3) -> 16052859
A4: Бенедикт | B4: Выручка | C4: Доставка | D4: Кухня | Q4: =SUM(E4:P4) -> 0
A5: Бенедикт | B5: Выручка | C5: Доставка | D5: Бар | Q5: =SUM(E5:P5) -> 0
A6: Бенедикт | B6: Себестоимость | C6: Зал | D6: Кухня | G6: 1152549.8 | H6: 2621768.4 | I6: 3155337.6 | J6: 2945616.7
A7: Бенедикт | B7: Себестоимость | C7: Зал | D7: Бар | G7: 453796.89 | H7: 1056247.5 | I7: 1188078.9 | J7: 1015168
A8: Бенедикт | B8: Себестоимость | C8: Доставка | D8: Кухня
A9: Бенедикт | B9: Себестоимость | C9: Доставка | D9: Бар
A10: Бенедикт | B10: Товарный запас | D10: Кухня | G10: 1001413.6 | H10: 1470765.7 | I10: 1311378.7 | J10: 1180613.8
A11: Бенедикт | B11: Товарный запас | D11: Бар | G11: 1315057.5 | H11: 1497931.5 | I11: 1411650.7 | J11: 1495604.7
A12: Бенедикт | B12: Товарный запас | D12: Склад | G12: 2481.8 | H12: 32451.85 | I12: 0 | J12: 11972.8
A13: Бенедикт | B13: Излишки | D13: Кухня | G13: -27988.17 | H13: -95472.84 | I13: =-(47779.67+51299.47) -> -99079.14 | J13: -98996.95
A14: Бенедикт | B14: Излишки | D14: Бар | G14: -7596.09 | H14: -27430.01 | I14: =-(10368.88+11788.28) -> -22157.16 | J14: -25113.08
A15: Бенедикт | B15: Недостачи | D15: Кухня | G15: 133313.27 | H15: 170319.23 | I15: 157026.42 | J15: 95806.33
A16: Бенедикт | B16: Недостачи | D16: Бар | H16: 12823.04 | I16: 6414.77 | J16: 6283.39
A17: Бенедикт | B17: Излишки, % от себеса | D17: Кухня | E17: =IFERROR(E13/(E6+E8),"-") -> - | F17: =IFERROR(F13/(F6+F8),"-") -> - | G17: =IFERROR(G13/(G6+G8),"-") -> -0.024283696 | H17: =IFERROR(H13/(H6+H8),"-") -> -0.036415436 | I17: =IFERROR(I13/(I6+I8),"-") -> -0.031400488 | J17: =IFERROR(J13/(J6+J8),"-") -> -0.033608225 | K17: =IFERROR(K13/(K6+K8),"-") -> - | L17: =IFERROR(L13/(L6+L8),"-") -> - | ... P17: =IFERROR(P13/(P6+P8),"-") -> -
A18: Бенедикт | B18: Излишки, % от себеса | D18: Бар | E18: =IFERROR(E14/(E7+E9),"-") -> - | F18: =IFERROR(F14/(F7+F9),"-") -> - | G18: =IFERROR(G14/(G7+G9),"-") -> -0.016738964 | H18: =IFERROR(H14/(H7+H9),"-") -> -0.025969303 | I18: =IFERROR(I14/(I7+I9),"-") -> -0.018649569 | J18: =IFERROR(J14/(J7+J9),"-") -> -0.024737855 | K18: =IFERROR(K14/(K7+K9),"-") -> - | L18: =IFERROR(L14/(L7+L9),"-") -> - | ... P18: =IFERROR(P14/(P7+P9),"-") -> -
A19: Бенедикт | B19: Недостачи, % от себеса | D19: Кухня | E19: =IFERROR(E15/(E6+E8),"-") -> - | F19: =IFERROR(F15/(F6+F8),"-") -> - | G19: =IFERROR(G15/(G6+G8),"-") -> 0.11566812 | H19: =IFERROR(H15/(H6+H8),"-") -> 0.064963491 | I19: =IFERROR(I15/(I6+I8),"-") -> 0.049765331 | J19: =IFERROR(J15/(J6+J8),"-") -> 0.03252505 | K19: =IFERROR(K15/(K6+K8),"-") -> - | L19: =IFERROR(L15/(L6+L8),"-") -> - | ... P19: =IFERROR(P15/(P6+P8),"-") -> -
A20: Бенедикт | B20: Недостачи, % от себеса | D20: Бар | E20: =IFERROR(E16/(E7+E9),"-") -> - | F20: =IFERROR(F16/(F7+F9),"-") -> - | G20: =IFERROR(G16/(G7+G9),"-") -> 0 | H20: =IFERROR(H16/(H7+H9),"-") -> 0.012140185 | I20: =IFERROR(I16/(I7+I9),"-") -> 0.0053992793 | J20: =IFERROR(J16/(J7+J9),"-") -> 0.0061895073 | K20: =IFERROR(K16/(K7+K9),"-") -> - | L20: =IFERROR(L16/(L7+L9),"-") -> - | ... P20: =IFERROR(P16/(P7+P9),"-") -> -
A21: Бенедикт | B21: Фудкост | D21: Кухня | E21: =IFERROR((E8+E6)/(E4+E2),"-") -> - | F21: =IFERROR((F8+F6)/(F4+F2),"-") -> - | G21: =IFERROR((G8+G6)/(G4+G2),"-") -> 0.2925286 | H21: =IFERROR((H8+H6)/(H4+H2),"-") -> 0.28996823 | I21: =IFERROR((I8+I6)/(I4+I2),"-") -> 0.29825287 | J21: =IFERROR((J8+J6)/(J4+J2),"-") -> 0.29997699 | K21: =IFERROR((K8+K6)/(K4+K2),"-") -> - | L21: =IFERROR((L8+L6)/(L4+L2),"-") -> - | ... P21: =IFERROR((P8+P6)/(P4+P2),"-") -> -
A22: Бенедикт | B22: Фудкост | D22: Бар | E22: =IFERROR((E9+E7)/(E5+E3),"-") -> - | F22: =IFERROR((F9+F7)/(F5+F3),"-") -> - | G22: =IFERROR((G9+G7)/(G5+G3),"-") -> 0.23008635 | H22: =IFERROR((H9+H7)/(H5+H3),"-") -> 0.23122236 | I22: =IFERROR((I9+I7)/(I5+I3),"-") -> 0.23319216 | J22: =IFERROR((J9+J7)/(J5+J3),"-") -> 0.22979989 | K22: =IFERROR((K9+K7)/(K5+K3),"-") -> - | L22: =IFERROR((L9+L7)/(L5+L3),"-") -> - | ... P22: =IFERROR((P9+P7)/(P5+P3),"-") -> -
B24: проверка Выр | E24: =SUM(E2:E5)-'Отчет о фин.рез.'!B2*1000 -> 0 | F24: =SUM(F2:F5)-'Отчет о фин.рез.'!C2*1000 -> 0 | G24: =SUM(G2:G5)-'Отчет о фин.рез.'!D2*1000 -> -17654.5 | H24: =SUM(H2:H5)-'Отчет о фин.рез.'!E2*1000 -> -103526 | I24: =SUM(I2:I5)-'Отчет о фин.рез.'!F2*1000 -> -38336.5 | J24: =SUM(J2:J5)-'Отчет о фин.рез.'!G2*1000 -> -16258 | K24: =SUM(K2:K5)-'Отчет о фин.рез.'!H2*1000 -> 0 | L24: =SUM(L2:L5)-'Отчет о фин.рез.'!I2*1000 -> 0 | ... P24: =SUM(P2:P5)-'Отчет о фин.рез.'!M2*1000 -> 0
B25: Проверка себес | E25: =SUM(E6:E9)-'Отчет о фин.рез.'!B15*1000 -> 0 | F25: =SUM(F6:F9)-'Отчет о фин.рез.'!C15*1000 -> 0 | G25: =SUM(G6:G9)-'Отчет о фин.рез.'!D15*1000 -> 5785.71 | H25: =SUM(H6:H9)-'Отчет о фин.рез.'!E15*1000 -> -68301.1 | I25: =SUM(I6:I9)-'Отчет о фин.рез.'!F15*1000 -> 146.55 | J25: =SUM(J6:J9)-'Отчет о фин.рез.'!G15*1000 -> 0.75 | K25: =SUM(K6:K9)-'Отчет о фин.рез.'!H15*1000 -> 0 | L25: =SUM(L6:L9)-'Отчет о фин.рез.'!I15*1000 -> 0 | ... P25: =SUM(P6:P9)-'Отчет о фин.рез.'!M15*1000 -> 0
B26: Проверка ТЗ | E26: =SUM(E10:E12)-баланс!C9 -> 0 | F26: =SUM(F10:F12)-баланс!D9 -> -474058.45 | G26: =SUM(G10:G12)-баланс!E9 -> 0 | H26: =SUM(H10:H12)-баланс!F9 -> 0.0099999998 | I26: =SUM(I10:I12)-баланс!G9 -> 338.87 | J26: =SUM(J10:J12)-баланс!H9 -> 339.04 | K26: =SUM(K10:K12)-баланс!I9 -> 0 | L26: =SUM(L10:L12)-баланс!J9 -> 0 | ... P26: =SUM(P10:P12)-баланс!N9 -> 0
B27: Себес | D27: Кухня | E27: =E6+E8 -> 0 | F27: =F6+F8 -> 0 | G27: =G6+G8 -> 1152549.8 | H27: =H6+H8 -> 2621768.4 | I27: =I6+I8 -> 3155337.6 | J27: =J6+J8 -> 2945616.7 | K27: =K6+K8 -> 0 | L27: =L6+L8 -> 0 | ... P27: =P6+P8 -> 0
B28: Наценка | D28: Кухня | E28: =IFERROR((E2+E4)/(E6+E8)-1,"-") -> - | F28: =IFERROR((F2+F4)/(F6+F8)-1,"-") -> - | G28: =IFERROR((G2+G4)/(G6+G8)-1,"-") -> 2.4184691 | H28: =IFERROR((H2+H4)/(H6+H8)-1,"-") -> 2.4486537 | I28: =IFERROR((I2+I4)/(I6+I8)-1,"-") -> 2.3528596 | J28: =IFERROR((J2+J4)/(J6+J8)-1,"-") -> 2.333589 | K28: =IFERROR((K2+K4)/(K6+K8)-1,"-") -> - | L28: =IFERROR((L2+L4)/(L6+L8)-1,"-") -> - | ... P28: =IFERROR((P2+P4)/(P6+P8)-1,"-") -> -
B29: ТЗ | D29: Кухня | E29: =E10 -> 0 | F29: =F10 -> 0 | G29: =G10 -> 1001413.6 | H29: =H10 -> 1470765.7 | I29: =I10 -> 1311378.7 | J29: =J10 -> 1180613.8 | K29: =K10 -> 0 | L29: =L10 -> 0 | ... P29: =P10 -> 0
B30: Оборачиваемость ТЗ | D30: Кухня | E30: =IFERROR(E29/(E27/(F1-E1)),"-") -> - | F30: =IFERROR(F29/(F27/(G1-F1)),"-") -> - | G30: =IFERROR(G29/(G27/(H1-G1)),"-") -> 26.934905 | H30: =IFERROR(H29/(H27/(I1-H1)),"-") -> 16.829469 | I30: =IFERROR(I29/(I27/(J1-I1)),"-") -> 12.8838 | J30: =IFERROR(J29/(J27/(K1-J1)),"-") -> 12.024108 | K30: =IFERROR(K29/(K27/(L1-K1)),"-") -> - | L30: =IFERROR(L29/(L27/(M1-L1)),"-") -> - | ... P30: =IFERROR(P29/(P27/(Q1-P1)),"-") -> -
G31: =IFERROR(SUM(E29:G29)/SUM(E27:G27)*(H1-E1)/3,"-") -> 26.066037 | J31: =IFERROR(SUM(H29:J29)/SUM(H27:J27)*(K1-H1)/3,"-") -> 13.780521 | M31: =IFERROR(SUM(K29:M29)/SUM(K27:M27)*(N1-K1)/3,"-") -> - | P31: =IFERROR(SUM(N29:P29)/SUM(N27:P27)*(Q1-N1)/3,"-") -> -
B33: Себес | D33: Бар | E33: =E9+E7 -> 0 | F33: =F9+F7 -> 0 | G33: =G9+G7 -> 453796.89 | H33: =H9+H7 -> 1056247.5 | I33: =I9+I7 -> 1188078.9 | J33: =J9+J7 -> 1015168 | K33: =K9+K7 -> 0 | L33: =L9+L7 -> 0 | ... P33: =P9+P7 -> 0
B34: Наценка | D34: Бар | E34: =IFERROR((E3+E5)/(E7+E9)-1,"-") -> - | F34: =IFERROR((F3+F5)/(F7+F9)-1,"-") -> - | G34: =IFERROR((G3+G5)/(G7+G9)-1,"-") -> 3.3461944 | H34: =IFERROR((H3+H5)/(H7+H9)-1,"-") -> 3.3248412 | I34: =IFERROR((I3+I5)/(I7+I9)-1,"-") -> 3.2883089 | J34: =IFERROR((J3+J5)/(J7+J9)-1,"-") -> 3.3516122 | K34: =IFERROR((K3+K5)/(K7+K9)-1,"-") -> - | L34: =IFERROR((L3+L5)/(L7+L9)-1,"-") -> - | ... P34: =IFERROR((P3+P5)/(P7+P9)-1,"-") -> -
B35: ТЗ | D35: Бар | E35: =E11 -> 0 | F35: =F11 -> 0 | G35: =G11 -> 1315057.5 | H35: =H11 -> 1497931.5 | I35: =I11 -> 1411650.7 | J35: =J11 -> 1495604.7 | K35: =K11 -> 0 | L35: =L11 -> 0 | ... P35: =P11 -> 0
B36: Оборачиваемость ТЗ | D36: Бар | E36: =IFERROR(E35/(E33/(F1-E1)),"-") -> - | F36: =IFERROR(F35/(F33/(G1-F1)),"-") -> - | G36: =IFERROR(G35/(G33/(H1-G1)),"-") -> 89.834865 | H36: =IFERROR(H35/(H33/(I1-H1)),"-") -> 42.544901 | I36: =IFERROR(I35/(I33/(J1-I1)),"-") -> 36.833556 | J36: =IFERROR(J35/(J33/(K1-J1)),"-") -> 44.197747 | K36: =IFERROR(K35/(K33/(L1-K1)),"-") -> - | L36: =IFERROR(L35/(L33/(M1-L1)),"-") -> - | ... P36: =IFERROR(P35/(P33/(Q1-P1)),"-") -> -
G37: =IFERROR(SUM(E35:G35)/SUM(E33:G33)*(H1-E1)/3,"-") -> 86.936966 | J37: =IFERROR(SUM(H35:J35)/SUM(H33:J33)*(K1-H1)/3,"-") -> 40.995315 | M37: =IFERROR(SUM(K35:M35)/SUM(K33:M33)*(N1-K1)/3,"-") -> - | P37: =IFERROR(SUM(N35:P35)/SUM(N33:P33)*(Q1-N1)/3,"-") -> -
E39: =E1 -> 46023 | F39: =F1 -> 46054 | G39: =G1 -> 46082 | H39: =H1 -> 46113 | I39: =I1 -> 46143 | J39: =J1 -> 46174 | K39: =K1 -> 46204 | L39: =L1 -> 46235 | ... P39: =P1 -> 46357 | Q39: год
B40: Доля в выручке | D40: Бар | E40: =IFERROR(E3/SUM(E2:E3),"-") -> - | F40: =IFERROR(F3/SUM(F2:F3),"-") -> - | G40: =IFERROR(G3/SUM(G2:G3),"-") -> 0.33359398 | H40: =IFERROR(H3/SUM(H2:H3),"-") -> 0.33565113 | I40: =IFERROR(I3/SUM(I2:I3),"-") -> 0.32504575 | J40: =IFERROR(J3/SUM(J2:J3),"-") -> 0.3102893 | K40: =IFERROR(K3/SUM(K2:K3),"-") -> - | L40: =IFERROR(L3/SUM(L2:L3),"-") -> - | ... Q40: =IFERROR(Q3/SUM(Q2:Q3),"-") -> 0.32473798
N46: DjTe3{Q}

Sheet Аналитическая форма
B1: Наименование статей | C1: январь | K1: февраль | S1: март | AA1: апрель | AI1: май | AQ1: июнь | AY1: июль | BG1: август | BO1: сентябрь | BW1: октябрь | CE1: ноябрь | CM1: декабрь | CU1: ГОД
C2: 2025 | E2: 2026 | G2: 2026 | K2: 2025 | M2: 2026 | O2: 2026 | S2: 2025 | U2: 2026 | W2: 2026 | AA2: 2025 | AC2: 2026 | AE2: 2026 | AI2: 2025 | AK2: 2026 | AM2: 2026 | AQ2: 2025 | AS2: 2026 | AU2: 2026 | AY2: 2025 | BA2: 2026 | BC2: 2026 | BG2: 2025 | BI2: 2026 | BK2: 2026 | BO2: 2025 | BQ2: 2026 | BS2: 2026 | BW2: 2025 | BY2: 2026 | CA2: 2026 | CE2: 2025 | CG2: 2026 | CI2: 2026 | CM2: 2025 | CO2: 2026 | CQ2: 2026 | CU2: 2025 | CW2: 2026 | CY2: 2026
C3: факт | D3: доля к Выр, % | E3: план | F3: доля к Выр, % | G3: факт | H3: Доля к Выр, % | I3: Факт/План, % | J3: 26/25, % | K3: факт | L3: доля к Выр, % | M3: план | N3: доля к Выр, % | O3: факт | P3: Доля к Выр, % | Q3: Факт/План, % | R3: 26/25, % | S3: факт | T3: доля к Выр, % | U3: план | V3: доля к Выр, % | W3: факт | X3: Доля к Выр, % | Y3: Факт/План, % | Z3: 26/25, % | AA3: факт | AB3: доля к Выр, % | AC3: план | AD3: доля к Выр, % | AE3: факт | AF3: Доля к Выр, % | AG3: Факт/План, % | AH3: 26/25, % | AI3: факт | AJ3: доля к Выр, % | AK3: план | AL3: доля к Выр, % | AM3: факт | AN3: Доля к Выр, % | AO3: Факт/План, % | AP3: 26/25, % | AQ3: факт | AR3: доля к Выр, % | AS3: план | AT3: доля к Выр, % | AU3: факт | AV3: Доля к Выр, % | AW3: Факт/План, % | AX3: 26/25, % | AY3: факт | AZ3: доля к Выр, % | BA3: план | BB3: доля к Выр, % | BC3: факт | BD3: Доля к Выр, % | BE3: Факт/План, % | BF3: 26/25, % | BG3: факт | BH3: доля к Выр, % | BI3: план | BJ3: доля к Выр, % | BK3: факт | BL3: Доля к Выр, % | BM3: Факт/План, % | BN3: 26/25, % | BO3: факт | BP3: доля к Выр, % | BQ3: план | BR3: доля к Выр, % | BS3: факт | BT3: Доля к Выр, % | BU3: Факт/План, % | BV3: 26/25, % | BW3: факт | BX3: доля к Выр, % | BY3: план | BZ3: доля к Выр, % | CA3: факт | CB3: Доля к Выр, % | CC3: Факт/План, % | CD3: 26/25, % | CE3: факт | CF3: доля к Выр, % | CG3: план | CH3: доля к Выр, % | CI3: факт | CJ3: Доля к Выр, % | CK3: Факт/План, % | CL3: 26/25, % | CM3: факт | CN3: доля к Выр, % | CO3: план | CP3: доля к Выр, % | CQ3: факт | CR3: Доля к Выр, % | CS3: Факт/План, % | CT3: 26/25, % | CU3: факт | CV3: доля к Выр, % | CW3: план | CX3: доля к Выр, % | CY3: факт | CZ3: Доля к Выр, % | DA3: Факт/План, % | DB3: 26/25, %
B4: Выручка, всего, в т.ч. | C4: =SUM(C5:C7) -> 0 | E4: =SUM(E5:E7) -> 0 | G4: =SUM(G5:G7) -> 0 | I4: =IF(IFERROR(G4/E4-1,"")=0,"",IFERROR(+G4/E4-1,"")) | J4: =IF(IFERROR(G4/C4-1,"")=0,"",IFERROR(+G4/C4-1,"")) | K4: =SUM(K5:K7) -> 0 | M4: =SUM(M5:M7) -> 0 | O4: =SUM(O5:O7) -> 0 | Q4: =IF(IFERROR(O4/M4-1,"")=0,"",IFERROR(+O4/M4-1,"")) | R4: =IF(IFERROR(O4/K4-1,"")=0,"",IFERROR(+O4/K4-1,"")) | S4: =SUM(S5:S7) -> 0 | U4: =SUM(U5:U7) -> 0 | W4: =SUM(W5:W7) -> 5929.9 | Y4: =IF(IFERROR(W4/U4-1,"")=0,"",IFERROR(+W4/U4-1,"")) | Z4: =IF(IFERROR(W4/S4-1,"")=0,"",IFERROR(+W4/S4-1,"")) | AA4: =SUM(AA5:AA7) -> 0 | AC4: =SUM(AC5:AC7) -> 13671.84 | AE4: =SUM(AE5:AE7) -> 13713.2 | AG4: =IF(IFERROR(AE4/AC4-1,"")=0,"",IFERROR(+AE4/AC4-1,"")) -> 0.0030251963 | AH4: =IF(IFERROR(AE4/AA4-1,"")=0,"",IFERROR(+AE4/AA4-1,"")) | AI4: =SUM(AI5:AI7) -> 0 | AK4: =SUM(AK5:AK7) -> 13972 | AM4: =SUM(AM5:AM7) -> 15712.59 | AO4: =IF(IFERROR(AM4/AK4-1,"")=0,"",IFERROR(+AM4/AK4-1,"")) -> 0.12457701 | AP4: =IF(IFERROR(AM4/AI4-1,"")=0,"",IFERROR(+AM4/AI4-1,"")) | AQ4: =SUM(AQ5:AQ7) -> 0 | AS4: =SUM(AS5:AS7) -> 15080 | AU4: =SUM(AU5:AU7) -> 14253.351 | AW4: =IF(IFERROR(AU4/AS4-1,"")=0,"",IFERROR(+AU4/AS4-1,"")) -> -0.054817573 | AX4: =IF(IFERROR(AU4/AQ4-1,"")=0,"",IFERROR(+AU4/AQ4-1,"")) | AY4: =SUM(AY5:AY7) -> 0 | BA4: =SUM(BA5:BA7) -> 15667.5 | BC4: =SUM(BC5:BC7) -> 0 | BE4: =IF(IFERROR(BC4/BA4-1,"")=0,"",IFERROR(+BC4/BA4-1,"")) -> -1 | BF4: =IF(IFERROR(BC4/AY4-1,"")=0,"",IFERROR(+BC4/AY4-1,"")) | BG4: =SUM(BG5:BG7) -> 0 | BI4: =SUM(BI5:BI7) -> 15667.5 | BK4: =SUM(BK5:BK7) -> 0 | BM4: =IF(IFERROR(BK4/BI4-1,"")=0,"",IFERROR(+BK4/BI4-1,"")) -> -1 | BN4: =IF(IFERROR(BK4/BG4-1,"")=0,"",IFERROR(+BK4/BG4-1,"")) | BO4: =SUM(BO5:BO7) -> 0 | BQ4: =SUM(BQ5:BQ7) -> 14480 | BS4: =SUM(BS5:BS7) -> 0 | BU4: =IF(IFERROR(BS4/BQ4-1,"")=0,"",IFERROR(+BS4/BQ4-1,"")) -> -1 | BV4: =IF(IFERROR(BS4/BO4-1,"")=0,"",IFERROR(+BS4/BO4-1,"")) | BW4: =SUM(BW5:BW7) -> 0 | BY4: =SUM(BY5:BY7) -> 14084.031 | CA4: =SUM(CA5:CA7) -> 0 | CC4: =IF(IFERROR(CA4/BY4-1,"")=0,"",IFERROR(+CA4/BY4-1,"")) -> -1 | CD4: =IF(IFERROR(CA4/BW4-1,"")=0,"",IFERROR(+CA4/BW4-1,"")) | CE4: =SUM(CE5:CE7) -> 0 | CG4: =SUM(CG5:CG7) -> 14541.024 | CI4: =SUM(CI5:CI7) -> 0 | CK4: =IF(IFERROR(CI4/CG4-1,"")=0,"",IFERROR(+CI4/CG4-1,"")) -> -1 | CL4: =IF(IFERROR(CI4/CE4-1,"")=0,"",IFERROR(+CI4/CE4-1,"")) | CM4: =SUM(CM5:CM7) -> 0 | CO4: =SUM(CO5:CO7) -> 15446.08 | CQ4: =SUM(CQ5:CQ7) -> 0 | CS4: =IF(IFERROR(CQ4/CO4-1,"")=0,"",IFERROR(+CQ4/CO4-1,"")) -> -1 | CT4: =IF(IFERROR(CQ4/CM4-1,"")=0,"",IFERROR(+CQ4/CM4-1,"")) | CU4: =SUM(C4,K4,S4,AA4,AI4,AQ4,AY4,BG4,BO4,BW4,CE4,CM4) -> 0 | CV4: =IFERROR(CU4/CU$4,"") | CW4: =SUM(E4,M4,U4,AC4,AK4,AS4,BA4,BI4,BQ4,BY4,CG4,CO4) -> 132609.98 | CX4: =IFERROR(CW4/CW$4,"") -> 1 | CY4: =SUM(G4,O4,W4,AE4,AM4,AU4,BC4,BK4,BS4,CA4,CI4,CQ4) -> 49609.041 | CZ4: =IFERROR(CY4/CY$4,"") -> 1 | DA4: =IF(IFERROR(CY4/CW4-1,"")=0,"",IFERROR(+CY4/CW4-1,"")) -> -0.62590265 | DB4: =IF(IFERROR(CY4/CU4-1,"")=0,"",IFERROR(+CY4/CU4-1,""))
B5: зал | D5: =IFERROR(C5/C$4,".") -> . | F5: =IFERROR(E5/E$4,"") | G5: =+'Отчет о фин.рез.'!B3 -> 0 | H5: =IFERROR(G5/G$4,"") | I5: =IF(IFERROR(G5/E5-1,"")=0,"",IFERROR(+G5/E5-1,"")) | J5: =IF(IFERROR(G5/C5-1,"")=0,"",IFERROR(+G5/C5-1,"")) | L5: =IFERROR(K5/K$4,".") -> . | N5: =IFERROR(M5/M$4,"") | O5: =+'Отчет о фин.рез.'!C3 -> 0 | P5: =IFERROR(O5/O$4,"") | Q5: =IF(IFERROR(O5/M5-1,"")=0,"",IFERROR(+O5/M5-1,"")) | R5: =IF(IFERROR(O5/K5-1,"")=0,"",IFERROR(+O5/K5-1,"")) | T5: =IFERROR(S5/S$4,".") -> . | U5: 0 | V5: =IFERROR(U5/U$4,"") | W5: =+'Отчет о фин.рез.'!D3 -> 5929.9 | X5: =IFERROR(W5/W$4,"") -> 1 | Y5: =IF(IFERROR(W5/U5-1,"")=0,"",IFERROR(+W5/U5-1,"")) | Z5: =IF(IFERROR(W5/S5-1,"")=0,"",IFERROR(+W5/S5-1,"")) | AB5: =IFERROR(AA5/AA$4,".") -> . | AC5: 13671.84 | AD5: =IFERROR(AC5/AC$4,"") -> 1 | AE5: =+'Отчет о фин.рез.'!E3 -> 13713.2 | AF5: =IFERROR(AE5/AE$4,"") -> 1 | AG5: =IF(IFERROR(AE5/AC5-1,"")=0,"",IFERROR(+AE5/AC5-1,"")) -> 0.0030251963 | AH5: =IF(IFERROR(AE5/AA5-1,"")=0,"",IFERROR(+AE5/AA5-1,"")) | AJ5: =IFERROR(AI5/AI$4,".") -> . | AK5: 13672 | AL5: =IFERROR(AK5/AK$4,"") -> 0.97852849 | AM5: =+'Отчет о фин.рез.'!F3 -> 15712.59 | AN5: =IFERROR(AM5/AM$4,"") -> 1 | AO5: =IF(IFERROR(AM5/AK5-1,"")=0,"",IFERROR(+AM5/AK5-1,"")) -> 0.14925322 | AP5: =IF(IFERROR(AM5/AI5-1,"")=0,"",IFERROR(+AM5/AI5-1,"")) | AR5: =IFERROR(AQ5/AQ$4,".") -> . | AS5: 14960 | AT5: =IFERROR(AS5/AS$4,"") -> 0.99204244 | AU5: =+'Отчет о фин.рез.'!G3 -> 14253.351 | AV5: =IFERROR(AU5/AU$4,"") -> 1 | AW5: =IF(IFERROR(AU5/AS5-1,"")=0,"",IFERROR(+AU5/AS5-1,"")) -> -0.047235896 | AX5: =IF(IFERROR(AU5/AQ5-1,"")=0,"",IFERROR(+AU5/AQ5-1,"")) | AZ5: =IFERROR(AY5/AY$4,".") -> . | BA5: 15487.5 | BB5: =IFERROR(BA5/BA$4,"") -> 0.98851125 | BC5: =+'Отчет о фин.рез.'!H3 -> 0 | BD5: =IFERROR(BC5/BC$4,"") | BE5: =IF(IFERROR(BC5/BA5-1,"")=0,"",IFERROR(+BC5/BA5-1,"")) -> -1 | BF5: =IF(IFERROR(BC5/AY5-1,"")=0,"",IFERROR(+BC5/AY5-1,"")) | BH5: =IFERROR(BG5/BG$4,".") -> . | BI5: 15487.5 | BJ5: =IFERROR(BI5/BI$4,"") -> 0.98851125 | BK5: =+'Отчет о фин.рез.'!I3 -> 0 | BL5: =IFERROR(BK5/BK$4,"") | BM5: =IF(IFERROR(BK5/BI5-1,"")=0,"",IFERROR(+BK5/BI5-1,"")) -> -1 | BN5: =IF(IFERROR(BK5/BG5-1,"")=0,"",IFERROR(+BK5/BG5-1,"")) | BP5: =IFERROR(BO5/BO$4,".") -> . | BQ5: 14280 | BR5: =IFERROR(BQ5/BQ$4,"") -> 0.98618785 | BS5: =+'Отчет о фин.рез.'!J3 -> 0 | BT5: =IFERROR(BS5/BS$4,"") | BU5: =IF(IFERROR(BS5/BQ5-1,"")=0,"",IFERROR(+BS5/BQ5-1,"")) -> -1 | BV5: =IF(IFERROR(BS5/BO5-1,"")=0,"",IFERROR(+BS5/BO5-1,"")) | BX5: =IFERROR(BW5/BW$4,".") -> . | BY5: 10385.957 | BZ5: =IFERROR(BY5/BY$4,"") -> 0.73742788 | CA5: =+'Отчет о фин.рез.'!K3 -> 0 | CB5: =IFERROR(CA5/CA$4,"") | CC5: =IF(IFERROR(CA5/BY5-1,"")=0,"",IFERROR(+CA5/BY5-1,"")) -> -1 | CD5: =IF(IFERROR(CA5/BW5-1,"")=0,"",IFERROR(+CA5/BW5-1,"")) | CF5: =IFERROR(CE5/CE$4,".") -> . | CG5: 11111.833 | CH5: =IFERROR(CG5/CG$4,"") -> 0.76417124 | CI5: =+'Отчет о фин.рез.'!L3 -> 0 | CJ5: =IFERROR(CI5/CI$4,"") | CK5: =IF(IFERROR(CI5/CG5-1,"")=0,"",IFERROR(+CI5/CG5-1,"")) -> -1 | CL5: =IF(IFERROR(CI5/CE5-1,"")=0,"",IFERROR(+CI5/CE5-1,"")) | CN5: =IFERROR(CM5/CM$4,".") -> . | CO5: 11288.099 | CP5: =IFERROR(CO5/CO$4,"") -> 0.73080672 | CQ5: =+'Отчет о фин.рез.'!M3 -> 0 | CR5: =IFERROR(CQ5/CQ$4,"") | CS5: =IF(IFERROR(CQ5/CO5-1,"")=0,"",IFERROR(+CQ5/CO5-1,"")) -> -1 | CT5: =IF(IFERROR(CQ5/CM5-1,"")=0,"",IFERROR(+CQ5/CM5-1,"")) | CU5: =SUM(C5,K5,S5,AA5,AI5,AQ5,AY5,BG5,BO5,BW5,CE5,CM5) -> 0 | CV5: =IFERROR(CU5/CU$4,"") | CW5: =SUM(E5,M5,U5,AC5,AK5,AS5,BA5,BI5,BQ5,BY5,CG5,CO5) -> 120344.73 | CX5: =IFERROR(CW5/CW$4,"") -> 0.90750887 | CY5: =SUM(G5,O5,W5,AE5,AM5,AU5,BC5,BK5,BS5,CA5,CI5,CQ5) -> 49609.041 | CZ5: =IFERROR(CY5/CY$4,"") -> 1 | DA5: =IF(IFERROR(CY5/CW5-1,"")=0,"",IFERROR(+CY5/CW5-1,"")) -> -0.58777554 | DB5: =IF(IFERROR(CY5/CU5-1,"")=0,"",IFERROR(+CY5/CU5-1,""))
B6: доставка | D6: =IFERROR(C6/C$4,"") | F6: =IFERROR(E6/E$4,"") | G6: =+'Отчет о фин.рез.'!B4 -> 0 | H6: =IFERROR(G6/G$4,"") | I6: =IF(IFERROR(G6/E6-1,"")=0,"",IFERROR(+G6/E6-1,"")) | J6: =IF(IFERROR(G6/C6-1,"")=0,"",IFERROR(+G6/C6-1,"")) | L6: =IFERROR(K6/K$4,"") | N6: =IFERROR(M6/M$4,"") | O6: =+'Отчет о фин.рез.'!C4 -> 0 | P6: =IFERROR(O6/O$4,"") | Q6: =IF(IFERROR(O6/M6-1,"")=0,"",IFERROR(+O6/M6-1,"")) | R6: =IF(IFERROR(O6/K6-1,"")=0,"",IFERROR(+O6/K6-1,"")) | T6: =IFERROR(S6/S$4,"") | U6: 0 | V6: =IFERROR(U6/U$4,"") | W6: =+'Отчет о фин.рез.'!D4 -> 0 | X6: =IFERROR(W6/W$4,"") -> 0 | Y6: =IF(IFERROR(W6/U6-1,"")=0,"",IFERROR(+W6/U6-1,"")) | Z6: =IF(IFERROR(W6/S6-1,"")=0,"",IFERROR(+W6/S6-1,"")) | AB6: =IFERROR(AA6/AA$4,"") | AC6: 0 | AD6: =IFERROR(AC6/AC$4,"") -> 0 | AE6: =+'Отчет о фин.рез.'!E4 -> 0 | AF6: =IFERROR(AE6/AE$4,"") -> 0 | AG6: =IF(IFERROR(AE6/AC6-1,"")=0,"",IFERROR(+AE6/AC6-1,"")) | AH6: =IF(IFERROR(AE6/AA6-1,"")=0,"",IFERROR(+AE6/AA6-1,"")) | AJ6: =IFERROR(AI6/AI$4,"") | AK6: 300 | AL6: =IFERROR(AK6/AK$4,"") -> 0.021471514 | AM6: =+'Отчет о фин.рез.'!F4 -> 0 | AN6: =IFERROR(AM6/AM$4,"") -> 0 | AO6: =IF(IFERROR(AM6/AK6-1,"")=0,"",IFERROR(+AM6/AK6-1,"")) -> -1 | AP6: =IF(IFERROR(AM6/AI6-1,"")=0,"",IFERROR(+AM6/AI6-1,"")) | AR6: =IFERROR(AQ6/AQ$4,"") | AS6: 120 | AT6: =IFERROR(AS6/AS$4,"") -> 0.0079575597 | AU6: =+'Отчет о фин.рез.'!G4 -> 0 | AV6: =IFERROR(AU6/AU$4,"") -> 0 | AW6: =IF(IFERROR(AU6/AS6-1,"")=0,"",IFERROR(+AU6/AS6-1,"")) -> -1 | AX6: =IF(IFERROR(AU6/AQ6-1,"")=0,"",IFERROR(+AU6/AQ6-1,"")) | AZ6: =IFERROR(AY6/AY$4,"") | BA6: 180 | BB6: =IFERROR(BA6/BA$4,"") -> 0.011488751 | BC6: =+'Отчет о фин.рез.'!H4 -> 0 | BD6: =IFERROR(BC6/BC$4,"") | BE6: =IF(IFERROR(BC6/BA6-1,"")=0,"",IFERROR(+BC6/BA6-1,"")) -> -1 | BF6: =IF(IFERROR(BC6/AY6-1,"")=0,"",IFERROR(+BC6/AY6-1,"")) | BH6: =IFERROR(BG6/BG$4,"") | BI6: 180 | BJ6: =IFERROR(BI6/BI$4,"") -> 0.011488751 | BK6: =+'Отчет о фин.рез.'!I4 -> 0 | BL6: =IFERROR(BK6/BK$4,"") | BM6: =IF(IFERROR(BK6/BI6-1,"")=0,"",IFERROR(+BK6/BI6-1,"")) -> -1 | BN6: =IF(IFERROR(BK6/BG6-1,"")=0,"",IFERROR(+BK6/BG6-1,"")) | BP6: =IFERROR(BO6/BO$4,"") | BQ6: 200 | BR6: =IFERROR(BQ6/BQ$4,"") -> 0.013812155 | BS6: =+'Отчет о фин.рез.'!J4 -> 0 | BT6: =IFERROR(BS6/BS$4,"") | BU6: =IF(IFERROR(BS6/BQ6-1,"")=0,"",IFERROR(+BS6/BQ6-1,"")) -> -1 | BV6: =IF(IFERROR(BS6/BO6-1,"")=0,"",IFERROR(+BS6/BO6-1,"")) | BX6: =IFERROR(BW6/BW$4,"") | BY6: 3698.0738 | BZ6: =IFERROR(BY6/BY$4,"") -> 0.26257212 | CA6: =+'Отчет о фин.рез.'!K4 -> 0 | CB6: =IFERROR(CA6/CA$4,"") | CC6: =IF(IFERROR(CA6/BY6-1,"")=0,"",IFERROR(+CA6/BY6-1,"")) -> -1 | CD6: =IF(IFERROR(CA6/BW6-1,"")=0,"",IFERROR(+CA6/BW6-1,"")) | CF6: =IFERROR(CE6/CE$4,"") | CG6: 3429.1918 | CH6: =IFERROR(CG6/CG$4,"") -> 0.23582876 | CI6: =+'Отчет о фин.рез.'!L4 -> 0 | CJ6: =IFERROR(CI6/CI$4,"") | CK6: =IF(IFERROR(CI6/CG6-1,"")=0,"",IFERROR(+CI6/CG6-1,"")) -> -1 | CL6: =IF(IFERROR(CI6/CE6-1,"")=0,"",IFERROR(+CI6/CE6-1,"")) | CN6: =IFERROR(CM6/CM$4,"") | CO6: 4157.9811 | CP6: =IFERROR(CO6/CO$4,"") -> 0.26919328 | CQ6: =+'Отчет о фин.рез.'!M4 -> 0 | CR6: =IFERROR(CQ6/CQ$4,"") | CS6: =IF(IFERROR(CQ6/CO6-1,"")=0,"",IFERROR(+CQ6/CO6-1,"")) -> -1 | CT6: =IF(IFERROR(CQ6/CM6-1,"")=0,"",IFERROR(+CQ6/CM6-1,"")) | CU6: =SUM(C6,K6,S6,AA6,AI6,AQ6,AY6,BG6,BO6,BW6,CE6,CM6) -> 0 | CV6: =IFERROR(CU6/CU$4,"") | CW6: =SUM(E6,M6,U6,AC6,AK6,AS6,BA6,BI6,BQ6,BY6,CG6,CO6) -> 12265.247 | CX6: =IFERROR(CW6/CW$4,"") -> 0.092491132 | CY6: =SUM(G6,O6,W6,AE6,AM6,AU6,BC6,BK6,BS6,CA6,CI6,CQ6) -> 0 | CZ6: =IFERROR(CY6/CY$4,"") -> 0 | DA6: =IF(IFERROR(CY6/CW6-1,"")=0,"",IFERROR(+CY6/CW6-1,"")) -> -1 | DB6: =IF(IFERROR(CY6/CU6-1,"")=0,"",IFERROR(+CY6/CU6-1,""))
B7: Доп подразделение (назвать по-своему или пустое) | D7: =IFERROR(C7/C$4,"") | F7: =IFERROR(E7/E$4,"") | G7: =+'Отчет о фин.рез.'!B5 -> 0 | H7: =IFERROR(G7/G$4,"") | I7: =IF(IFERROR(G7/E7-1,"")=0,"",IFERROR(+G7/E7-1,"")) | J7: =IF(IFERROR(G7/C7-1,"")=0,"",IFERROR(+G7/C7-1,"")) | L7: =IFERROR(K7/K$4,"") | N7: =IFERROR(M7/M$4,"") | O7: =+'Отчет о фин.рез.'!C5 -> 0 | P7: =IFERROR(O7/O$4,"") | Q7: =IF(IFERROR(O7/M7-1,"")=0,"",IFERROR(+O7/M7-1,"")) | R7: =IF(IFERROR(O7/K7-1,"")=0,"",IFERROR(+O7/K7-1,"")) | T7: =IFERROR(S7/S$4,"") | U7: 0 | V7: =IFERROR(U7/U$4,"") | W7: =+'Отчет о фин.рез.'!D5 -> 0 | X7: =IFERROR(W7/W$4,"") -> 0 | Y7: =IF(IFERROR(W7/U7-1,"")=0,"",IFERROR(+W7/U7-1,"")) | Z7: =IF(IFERROR(W7/S7-1,"")=0,"",IFERROR(+W7/S7-1,"")) | AB7: =IFERROR(AA7/AA$4,"") | AC7: 0 | AD7: =IFERROR(AC7/AC$4,"") -> 0 | AE7: =+'Отчет о фин.рез.'!E5 -> 0 | AF7: =IFERROR(AE7/AE$4,"") -> 0 | AG7: =IF(IFERROR(AE7/AC7-1,"")=0,"",IFERROR(+AE7/AC7-1,"")) | AH7: =IF(IFERROR(AE7/AA7-1,"")=0,"",IFERROR(+AE7/AA7-1,"")) | AJ7: =IFERROR(AI7/AI$4,"") | AK7: 0 | AL7: =IFERROR(AK7/AK$4,"") -> 0 | AM7: =+'Отчет о фин.рез.'!F5 -> 0 | AN7: =IFERROR(AM7/AM$4,"") -> 0 | AO7: =IF(IFERROR(AM7/AK7-1,"")=0,"",IFERROR(+AM7/AK7-1,"")) | AP7: =IF(IFERROR(AM7/AI7-1,"")=0,"",IFERROR(+AM7/AI7-1,"")) | AR7: =IFERROR(AQ7/AQ$4,"") | AS7: 0 | AT7: =IFERROR(AS7/AS$4,"") -> 0 | AU7: =+'Отчет о фин.рез.'!G5 -> 0 | AV7: =IFERROR(AU7/AU$4,"") -> 0 | AW7: =IF(IFERROR(AU7/AS7-1,"")=0,"",IFERROR(+AU7/AS7-1,"")) | AX7: =IF(IFERROR(AU7/AQ7-1,"")=0,"",IFERROR(+AU7/AQ7-1,"")) | AZ7: =IFERROR(AY7/AY$4,"") | BA7: 0 | BB7: =IFERROR(BA7/BA$4,"") -> 0 | BC7: =+'Отчет о фин.рез.'!H5 -> 0 | BD7: =IFERROR(BC7/BC$4,"") | BE7: =IF(IFERROR(BC7/BA7-1,"")=0,"",IFERROR(+BC7/BA7-1,"")) | BF7: =IF(IFERROR(BC7/AY7-1,"")=0,"",IFERROR(+BC7/AY7-1,"")) | BH7: =IFERROR(BG7/BG$4,"") | BI7: 0 | BJ7: =IFERROR(BI7/BI$4,"") -> 0 | BK7: =+'Отчет о фин.рез.'!I5 -> 0 | BL7: =IFERROR(BK7/BK$4,"") | BM7: =IF(IFERROR(BK7/BI7-1,"")=0,"",IFERROR(+BK7/BI7-1,"")) | BN7: =IF(IFERROR(BK7/BG7-1,"")=0,"",IFERROR(+BK7/BG7-1,"")) | BP7: =IFERROR(BO7/BO$4,"") | BQ7: 0 | BR7: =IFERROR(BQ7/BQ$4,"") -> 0 | BS7: =+'Отчет о фин.рез.'!J5 -> 0 | BT7: =IFERROR(BS7/BS$4,"") | BU7: =IF(IFERROR(BS7/BQ7-1,"")=0,"",IFERROR(+BS7/BQ7-1,"")) | BV7: =IF(IFERROR(BS7/BO7-1,"")=0,"",IFERROR(+BS7/BO7-1,"")) | BX7: =IFERROR(BW7/BW$4,"") | BY7: 0 | BZ7: =IFERROR(BY7/BY$4,"") -> 0 | CA7: =+'Отчет о фин.рез.'!K5 -> 0 | CB7: =IFERROR(CA7/CA$4,"") | CC7: =IF(IFERROR(CA7/BY7-1,"")=0,"",IFERROR(+CA7/BY7-1,"")) | CD7: =IF(IFERROR(CA7/BW7-1,"")=0,"",IFERROR(+CA7/BW7-1,"")) | CF7: =IFERROR(CE7/CE$4,"") | CG7: 0 | CH7: =IFERROR(CG7/CG$4,"") -> 0 | CI7: =+'Отчет о фин.рез.'!L5 -> 0 | CJ7: =IFERROR(CI7/CI$4,"") | CK7: =IF(IFERROR(CI7/CG7-1,"")=0,"",IFERROR(+CI7/CG7-1,"")) | CL7: =IF(IFERROR(CI7/CE7-1,"")=0,"",IFERROR(+CI7/CE7-1,"")) | CN7: =IFERROR(CM7/CM$4,"") | CO7: 0 | CP7: =IFERROR(CO7/CO$4,"") -> 0 | CQ7: =+'Отчет о фин.рез.'!M5 -> 0 | CR7: =IFERROR(CQ7/CQ$4,"") | CS7: =IF(IFERROR(CQ7/CO7-1,"")=0,"",IFERROR(+CQ7/CO7-1,"")) | CT7: =IF(IFERROR(CQ7/CM7-1,"")=0,"",IFERROR(+CQ7/CM7-1,"")) | CU7: =SUM(C7,K7,S7,AA7,AI7,AQ7,AY7,BG7,BO7,BW7,CE7,CM7) -> 0 | CV7: =IFERROR(CU7/CU$4,"") | CW7: =SUM(E7,M7,U7,AC7,AK7,AS7,BA7,BI7,BQ7,BY7,CG7,CO7) -> 0 | CX7: =IFERROR(CW7/CW$4,"") -> 0 | CY7: =SUM(G7,O7,W7,AE7,AM7,AU7,BC7,BK7,BS7,CA7,CI7,CQ7) -> 0 | CZ7: =IFERROR(CY7/CY$4,"") -> 0 | DA7: =IF(IFERROR(CY7/CW7-1,"")=0,"",IFERROR(+CY7/CW7-1,"")) | DB7: =IF(IFERROR(CY7/CU7-1,"")=0,"",IFERROR(+CY7/CU7-1,""))
B8: Количество гостей/заказов: | C8: =+SUM(C9:C11) -> 0 | G8: =+SUM(G9:G11) -> 0 | I8: =IF(IFERROR(G8/E8-1,"")=0,"",IFERROR(+G8/E8-1,"")) | J8: =IF(IFERROR(G8/C8-1,"")=0,"",IFERROR(+G8/C8-1,"")) | K8: =+SUM(K9:K11) -> 0 | O8: =+SUM(O9:O11) -> 0 | Q8: =IF(IFERROR(O8/M8-1,"")=0,"",IFERROR(+O8/M8-1,"")) | R8: =IF(IFERROR(O8/K8-1,"")=0,"",IFERROR(+O8/K8-1,"")) | S8: =+SUM(S9:S11) -> 0 | U8: =SUM(U9:U11) -> 0 | W8: =+SUM(W9:W11) -> 3807 | Y8: =IF(IFERROR(W8/U8-1,"")=0,"",IFERROR(+W8/U8-1,"")) | Z8: =IF(IFERROR(W8/S8-1,"")=0,"",IFERROR(+W8/S8-1,"")) | AA8: =+SUM(AA9:AA11) -> 0 | AC8: =SUM(AC9:AC11) -> 8138 | AE8: =+SUM(AE9:AE11) -> 8253 | AG8: =IF(IFERROR(AE8/AC8-1,"")=0,"",IFERROR(+AE8/AC8-1,"")) -> 0.014131236 | AH8: =IF(IFERROR(AE8/AA8-1,"")=0,"",IFERROR(+AE8/AA8-1,"")) | AI8: =+SUM(AI9:AI11) -> 0 | AK8: =SUM(AK9:AK11) -> 8695 | AM8: =+SUM(AM9:AM11) -> 9177 | AO8: =IF(IFERROR(AM8/AK8-1,"")=0,"",IFERROR(+AM8/AK8-1,"")) -> 0.055434158 | AP8: =IF(IFERROR(AM8/AI8-1,"")=0,"",IFERROR(+AM8/AI8-1,"")) | AQ8: =+SUM(AQ9:AQ11) -> 0 | AS8: =SUM(AS9:AS11) -> 8860 | AU8: =+SUM(AU9:AU11) -> 9166 | AW8: =IF(IFERROR(AU8/AS8-1,"")=0,"",IFERROR(+AU8/AS8-1,"")) -> 0.034537246 | AX8: =IF(IFERROR(AU8/AQ8-1,"")=0,"",IFERROR(+AU8/AQ8-1,"")) | AY8: =+SUM(AY9:AY11) -> 0 | BA8: =SUM(BA9:BA11) -> 8940 | BC8: =+SUM(BC9:BC11) -> 0 | BE8: =IF(IFERROR(BC8/BA8-1,"")=0,"",IFERROR(+BC8/BA8-1,"")) -> -1 | BF8: =IF(IFERROR(BC8/AY8-1,"")=0,"",IFERROR(+BC8/AY8-1,"")) | BG8: =+SUM(BG9:BG11) -> 0 | BI8: =SUM(BI9:BI11) -> 8940 | BK8: =+SUM(BK9:BK11) -> 0 | BM8: =IF(IFERROR(BK8/BI8-1,"")=0,"",IFERROR(+BK8/BI8-1,"")) -> -1 | BN8: =IF(IFERROR(BK8/BG8-1,"")=0,"",IFERROR(+BK8/BG8-1,"")) | BO8: =+SUM(BO9:BO11) -> 0 | BQ8: =SUM(BQ9:BQ11) -> 8500 | BS8: =+SUM(BS9:BS11) -> 0 | BU8: =IF(IFERROR(BS8/BQ8-1,"")=0,"",IFERROR(+BS8/BQ8-1,"")) -> -1 | BV8: =IF(IFERROR(BS8/BO8-1,"")=0,"",IFERROR(+BS8/BO8-1,"")) | BW8: =+SUM(BW9:BW11) -> 0 | BY8: =SUM(BY9:BY11) -> 10351.425 | CA8: =+SUM(CA9:CA11) -> 0 | CC8: =IF(IFERROR(CA8/BY8-1,"")=0,"",IFERROR(+CA8/BY8-1,"")) -> -1 | CD8: =IF(IFERROR(CA8/BW8-1,"")=0,"",IFERROR(+CA8/BW8-1,"")) | CE8: =+SUM(CE9:CE11) -> 0 | CG8: =SUM(CG9:CG11) -> 10219.125 | CI8: =+SUM(CI9:CI11) -> 0 | CK8: =IF(IFERROR(CI8/CG8-1,"")=0,"",IFERROR(+CI8/CG8-1,"")) -> -1 | CL8: =IF(IFERROR(CI8/CE8-1,"")=0,"",IFERROR(+CI8/CE8-1,"")) | CM8: =+SUM(CM9:CM11) -> 0 | CO8: =SUM(CO9:CO11) -> 10117.275 | CQ8: =+SUM(CQ9:CQ11) -> 0 | CS8: =IF(IFERROR(CQ8/CO8-1,"")=0,"",IFERROR(+CQ8/CO8-1,"")) -> -1 | CT8: =IF(IFERROR(CQ8/CM8-1,"")=0,"",IFERROR(+CQ8/CM8-1,"")) | CU8: =SUM(C8,K8,S8,AA8,AI8,AQ8,AY8,BG8,BO8,BW8,CE8,CM8) -> 0 | CV8: =IFERROR(CU8/CU$4,"") | CW8: =SUM(E8,M8,U8,AC8,AK8,AS8,BA8,BI8,BQ8,BY8,CG8,CO8) -> 82760.825 | CX8: =IFERROR(CW8/CW$4,"") -> 0.624092 | CY8: =SUM(G8,O8,W8,AE8,AM8,AU8,BC8,BK8,BS8,CA8,CI8,CQ8) -> 30403 | CZ8: =IFERROR(CY8/CY$4,"") -> 0.612852 | DA8: =IF(IFERROR(CY8/CW8-1,"")=0,"",IFERROR(+CY8/CW8-1,"")) -> -0.6326402 | DB8: =IF(IFERROR(CY8/CU8-1,"")=0,"",IFERROR(+CY8/CU8-1,""))
B9: зал | G9: =+'Отчет о фин.рез.'!B7 -> 0 | I9: =IF(IFERROR(G9/E9-1,"")=0,"",IFERROR(+G9/E9-1,"")) | J9: =IF(IFERROR(G9/C9-1,"")=0,"",IFERROR(+G9/C9-1,"")) | O9: =+'Отчет о фин.рез.'!C7 -> 0 | Q9: =IF(IFERROR(O9/M9-1,"")=0,"",IFERROR(+O9/M9-1,"")) | R9: =IF(IFERROR(O9/K9-1,"")=0,"",IFERROR(+O9/K9-1,"")) | U9: 0 | W9: =+'Отчет о фин.рез.'!D7 -> 3807 | Y9: =IF(IFERROR(W9/U9-1,"")=0,"",IFERROR(+W9/U9-1,"")) | Z9: =IF(IFERROR(W9/S9-1,"")=0,"",IFERROR(+W9/S9-1,"")) | AC9: 8138 | AE9: =+'Отчет о фин.рез.'!E7 -> 8253 | AG9: =IF(IFERROR(AE9/AC9-1,"")=0,"",IFERROR(+AE9/AC9-1,"")) -> 0.014131236 | AH9: =IF(IFERROR(AE9/AA9-1,"")=0,"",IFERROR(+AE9/AA9-1,"")) | AK9: 8545 | AM9: =+'Отчет о фин.рез.'!F7 -> 9177 | AO9: =IF(IFERROR(AM9/AK9-1,"")=0,"",IFERROR(+AM9/AK9-1,"")) -> 0.073961381 | AP9: =IF(IFERROR(AM9/AI9-1,"")=0,"",IFERROR(+AM9/AI9-1,"")) | AS9: 8800 | AU9: =+'Отчет о фин.рез.'!G7 -> 9085 | AW9: =IF(IFERROR(AU9/AS9-1,"")=0,"",IFERROR(+AU9/AS9-1,"")) -> 0.032386364 | AX9: =IF(IFERROR(AU9/AQ9-1,"")=0,"",IFERROR(+AU9/AQ9-1,"")) | BA9: 8850 | BC9: =+'Отчет о фин.рез.'!H7 -> 0 | BE9: =IF(IFERROR(BC9/BA9-1,"")=0,"",IFERROR(+BC9/BA9-1,"")) -> -1 | BF9: =IF(IFERROR(BC9/AY9-1,"")=0,"",IFERROR(+BC9/AY9-1,"")) | BI9: 8850 | BK9: =+'Отчет о фин.рез.'!I7 -> 0 | BM9: =IF(IFERROR(BK9/BI9-1,"")=0,"",IFERROR(+BK9/BI9-1,"")) -> -1 | BN9: =IF(IFERROR(BK9/BG9-1,"")=0,"",IFERROR(+BK9/BG9-1,"")) | BQ9: 8400 | BS9: =+'Отчет о фин.рез.'!J7 -> 0 | BU9: =IF(IFERROR(BS9/BQ9-1,"")=0,"",IFERROR(+BS9/BQ9-1,"")) -> -1 | BV9: =IF(IFERROR(BS9/BO9-1,"")=0,"",IFERROR(+BS9/BO9-1,"")) | BY9: 8760.675 | CA9: =+'Отчет о фин.рез.'!K7 -> 0 | CC9: =IF(IFERROR(CA9/BY9-1,"")=0,"",IFERROR(+CA9/BY9-1,"")) -> -1 | CD9: =IF(IFERROR(CA9/BW9-1,"")=0,"",IFERROR(+CA9/BW9-1,"")) | CG9: 8695.575 | CI9: =+'Отчет о фин.рез.'!L7 -> 0 | CK9: =IF(IFERROR(CI9/CG9-1,"")=0,"",IFERROR(+CI9/CG9-1,"")) -> -1 | CL9: =IF(IFERROR(CI9/CE9-1,"")=0,"",IFERROR(+CI9/CE9-1,"")) | CO9: 8387.4 | CQ9: =+'Отчет о фин.рез.'!M7 -> 0 | CS9: =IF(IFERROR(CQ9/CO9-1,"")=0,"",IFERROR(+CQ9/CO9-1,"")) -> -1 | CT9: =IF(IFERROR(CQ9/CM9-1,"")=0,"",IFERROR(+CQ9/CM9-1,"")) | CU9: =SUM(C9,K9,S9,AA9,AI9,AQ9,AY9,BG9,BO9,BW9,CE9,CM9) -> 0 | CV9: =IFERROR(CU9/CU$4,"") | CW9: =SUM(E9,M9,U9,AC9,AK9,AS9,BA9,BI9,BQ9,BY9,CG9,CO9) -> 77426.65 | CX9: =IFERROR(CW9/CW$4,"") -> 0.58386746 | CY9: =SUM(G9,O9,W9,AE9,AM9,AU9,BC9,BK9,BS9,CA9,CI9,CQ9) -> 30322 | CZ9: =IFERROR(CY9/CY$4,"") -> 0.61121923 | DA9: =IF(IFERROR(CY9/CW9-1,"")=0,"",IFERROR(+CY9/CW9-1,"")) -> -0.60837774 | DB9: =IF(IFERROR(CY9/CU9-1,"")=0,"",IFERROR(+CY9/CU9-1,""))
B10: доставка | G10: =+'Отчет о фин.рез.'!B8 -> 0 | I10: =IF(IFERROR(G10/E10-1,"")=0,"",IFERROR(+G10/E10-1,"")) | J10: =IF(IFERROR(G10/C10-1,"")=0,"",IFERROR(+G10/C10-1,"")) | O10: =+'Отчет о фин.рез.'!C8 -> 0 | Q10: =IF(IFERROR(O10/M10-1,"")=0,"",IFERROR(+O10/M10-1,"")) | R10: =IF(IFERROR(O10/K10-1,"")=0,"",IFERROR(+O10/K10-1,"")) | U10: 0 | W10: =+'Отчет о фин.рез.'!D8 -> 0 | Y10: =IF(IFERROR(W10/U10-1,"")=0,"",IFERROR(+W10/U10-1,"")) | Z10: =IF(IFERROR(W10/S10-1,"")=0,"",IFERROR(+W10/S10-1,"")) | AC10: 0 | AE10: =+'Отчет о фин.рез.'!E8 -> 0 | AG10: =IF(IFERROR(AE10/AC10-1,"")=0,"",IFERROR(+AE10/AC10-1,"")) | AH10: =IF(IFERROR(AE10/AA10-1,"")=0,"",IFERROR(+AE10/AA10-1,"")) | AK10: 150 | AM10: =+'Отчет о фин.рез.'!F8 -> 0 | AO10: =IF(IFERROR(AM10/AK10-1,"")=0,"",IFERROR(+AM10/AK10-1,"")) -> -1 | AP10: =IF(IFERROR(AM10/AI10-1,"")=0,"",IFERROR(+AM10/AI10-1,"")) | AS10: 60 | AU10: =+'Отчет о фин.рез.'!G8 -> 81 | AW10: =IF(IFERROR(AU10/AS10-1,"")=0,"",IFERROR(+AU10/AS10-1,"")) -> 0.35 | AX10: =IF(IFERROR(AU10/AQ10-1,"")=0,"",IFERROR(+AU10/AQ10-1,"")) | BA10: 90 | BC10: =+'Отчет о фин.рез.'!H8 -> 0 | BE10: =IF(IFERROR(BC10/BA10-1,"")=0,"",IFERROR(+BC10/BA10-1,"")) -> -1 | BF10: =IF(IFERROR(BC10/AY10-1,"")=0,"",IFERROR(+BC10/AY10-1,"")) | BI10: 90 | BK10: =+'Отчет о фин.рез.'!I8 -> 0 | BM10: =IF(IFERROR(BK10/BI10-1,"")=0,"",IFERROR(+BK10/BI10-1,"")) -> -1 | BN10: =IF(IFERROR(BK10/BG10-1,"")=0,"",IFERROR(+BK10/BG10-1,"")) | BQ10: 100 | BS10: =+'Отчет о фин.рез.'!J8 -> 0 | BU10: =IF(IFERROR(BS10/BQ10-1,"")=0,"",IFERROR(+BS10/BQ10-1,"")) -> -1 | BV10: =IF(IFERROR(BS10/BO10-1,"")=0,"",IFERROR(+BS10/BO10-1,"")) | BY10: 1590.75 | CA10: =+'Отчет о фин.рез.'!K8 -> 0 | CC10: =IF(IFERROR(CA10/BY10-1,"")=0,"",IFERROR(+CA10/BY10-1,"")) -> -1 | CD10: =IF(IFERROR(CA10/BW10-1,"")=0,"",IFERROR(+CA10/BW10-1,"")) | CG10: 1523.55 | CI10: =+'Отчет о фин.рез.'!L8 -> 0 | CK10: =IF(IFERROR(CI10/CG10-1,"")=0,"",IFERROR(+CI10/CG10-1,"")) -> -1 | CL10: =IF(IFERROR(CI10/CE10-1,"")=0,"",IFERROR(+CI10/CE10-1,"")) | CO10: 1729.875 | CQ10: =+'Отчет о фин.рез.'!M8 -> 0 | CS10: =IF(IFERROR(CQ10/CO10-1,"")=0,"",IFERROR(+CQ10/CO10-1,"")) -> -1 | CT10: =IF(IFERROR(CQ10/CM10-1,"")=0,"",IFERROR(+CQ10/CM10-1,"")) | CU10: =SUM(C10,K10,S10,AA10,AI10,AQ10,AY10,BG10,BO10,BW10,CE10,CM10) -> 0 | CV10: =IFERROR(CU10/CU$4,"") | CW10: =SUM(E10,M10,U10,AC10,AK10,AS10,BA10,BI10,BQ10,BY10,CG10,CO10) -> 5334.175 | CX10: =IFERROR(CW10/CW$4,"") -> 0.040224538 | CY10: =SUM(G10,O10,W10,AE10,AM10,AU10,BC10,BK10,BS10,CA10,CI10,CQ10) -> 81 | CZ10: =IFERROR(CY10/CY$4,"") -> 0.0016327669 | DA10: =IF(IFERROR(CY10/CW10-1,"")=0,"",IFERROR(+CY10/CW10-1,"")) -> -0.9848149 | DB10: =IF(IFERROR(CY10/CU10-1,"")=0,"",IFERROR(+CY10/CU10-1,""))
B11: Доп подразделение (назвать по-своему или пустое) | G11: =+'Отчет о фин.рез.'!B9 -> 0 | I11: =IF(IFERROR(G11/E11-1,"")=0,"",IFERROR(+G11/E11-1,"")) | J11: =IF(IFERROR(G11/C11-1,"")=0,"",IFERROR(+G11/C11-1,"")) | O11: =+'Отчет о фин.рез.'!C9 -> 0 | Q11: =IF(IFERROR(O11/M11-1,"")=0,"",IFERROR(+O11/M11-1,"")) | R11: =IF(IFERROR(O11/K11-1,"")=0,"",IFERROR(+O11/K11-1,"")) | U11: 0 | W11: =+'Отчет о фин.рез.'!D9 -> 0 | Y11: =IF(IFERROR(W11/U11-1,"")=0,"",IFERROR(+W11/U11-1,"")) | Z11: =IF(IFERROR(W11/S11-1,"")=0,"",IFERROR(+W11/S11-1,"")) | AC11: 0 | AE11: =+'Отчет о фин.рез.'!E9 -> 0 | AG11: =IF(IFERROR(AE11/AC11-1,"")=0,"",IFERROR(+AE11/AC11-1,"")) | AH11: =IF(IFERROR(AE11/AA11-1,"")=0,"",IFERROR(+AE11/AA11-1,"")) | AK11: 0 | AM11: =+'Отчет о фин.рез.'!F9 -> 0 | AO11: =IF(IFERROR(AM11/AK11-1,"")=0,"",IFERROR(+AM11/AK11-1,"")) | AP11: =IF(IFERROR(AM11/AI11-1,"")=0,"",IFERROR(+AM11/AI11-1,"")) | AS11: 0 | AU11: =+'Отчет о фин.рез.'!G9 -> 0 | AW11: =IF(IFERROR(AU11/AS11-1,"")=0,"",IFERROR(+AU11/AS11-1,"")) | AX11: =IF(IFERROR(AU11/AQ11-1,"")=0,"",IFERROR(+AU11/AQ11-1,"")) | BA11: 0 | BC11: =+'Отчет о фин.рез.'!H9 -> 0 | BE11: =IF(IFERROR(BC11/BA11-1,"")=0,"",IFERROR(+BC11/BA11-1,"")) | BF11: =IF(IFERROR(BC11/AY11-1,"")=0,"",IFERROR(+BC11/AY11-1,"")) | BI11: 0 | BK11: =+'Отчет о фин.рез.'!I9 -> 0 | BM11: =IF(IFERROR(BK11/BI11-1,"")=0,"",IFERROR(+BK11/BI11-1,"")) | BN11: =IF(IFERROR(BK11/BG11-1,"")=0,"",IFERROR(+BK11/BG11-1,"")) | BQ11: 0 | BS11: =+'Отчет о фин.рез.'!J9 -> 0 | BU11: =IF(IFERROR(BS11/BQ11-1,"")=0,"",IFERROR(+BS11/BQ11-1,"")) | BV11: =IF(IFERROR(BS11/BO11-1,"")=0,"",IFERROR(+BS11/BO11-1,"")) | BY11: 0 | CA11: =+'Отчет о фин.рез.'!K9 -> 0 | CC11: =IF(IFERROR(CA11/BY11-1,"")=0,"",IFERROR(+CA11/BY11-1,"")) | CD11: =IF(IFERROR(CA11/BW11-1,"")=0,"",IFERROR(+CA11/BW11-1,"")) | CG11: 0 | CI11: =+'Отчет о фин.рез.'!L9 -> 0 | CK11: =IF(IFERROR(CI11/CG11-1,"")=0,"",IFERROR(+CI11/CG11-1,"")) | CL11: =IF(IFERROR(CI11/CE11-1,"")=0,"",IFERROR(+CI11/CE11-1,"")) | CO11: 0 | CQ11: =+'Отчет о фин.рез.'!M9 -> 0 | CS11: =IF(IFERROR(CQ11/CO11-1,"")=0,"",IFERROR(+CQ11/CO11-1,"")) | CT11: =IF(IFERROR(CQ11/CM11-1,"")=0,"",IFERROR(+CQ11/CM11-1,"")) | CU11: =SUM(C11,K11,S11,AA11,AI11,AQ11,AY11,BG11,BO11,BW11,CE11,CM11) -> 0 | CV11: =IFERROR(CU11/CU$4,"") | CW11: =SUM(E11,M11,U11,AC11,AK11,AS11,BA11,BI11,BQ11,BY11,CG11,CO11) -> 0 | CX11: =IFERROR(CW11/CW$4,"") -> 0 | CY11: =SUM(G11,O11,W11,AE11,AM11,AU11,BC11,BK11,BS11,CA11,CI11,CQ11) -> 0 | CZ11: =IFERROR(CY11/CY$4,"") -> 0 | DA11: =IF(IFERROR(CY11/CW11-1,"")=0,"",IFERROR(+CY11/CW11-1,"")) | DB11: =IF(IFERROR(CY11/CU11-1,"")=0,"",IFERROR(+CY11/CU11-1,""))
B12: Средний чек | C12: =IFERROR(C4*1000/C8,"") | E12: =IFERROR(E4*1000/E8,"") | G12: =IFERROR(G4*1000/G8,"") | I12: =IF(IFERROR(G12/E12-1,"")=0,"",IFERROR(+G12/E12-1,"")) | J12: =IF(IFERROR(G12/C12-1,"")=0,"",IFERROR(+G12/C12-1,"")) | K12: =IFERROR(K4*1000/K8,"") | M12: =IFERROR(M4*1000/M8,"") | O12: =IFERROR(O4*1000/O8,"") | Q12: =IF(IFERROR(O12/M12-1,"")=0,"",IFERROR(+O12/M12-1,"")) | R12: =IF(IFERROR(O12/K12-1,"")=0,"",IFERROR(+O12/K12-1,"")) | S12: =IFERROR(S4*1000/S8,"") | U12: =IFERROR(U4*1000/U8,"") | W12: =IFERROR(W4*1000/W8,"") -> 1557.6307 | Y12: =IF(IFERROR(W12/U12-1,"")=0,"",IFERROR(+W12/U12-1,"")) | Z12: =IF(IFERROR(W12/S12-1,"")=0,"",IFERROR(+W12/S12-1,"")) | AA12: =IFERROR(AA4*1000/AA8,"") | AC12: =IFERROR(AC4*1000/AC8,"") -> 1680 | AE12: =IFERROR(AE4*1000/AE8,"") -> 1661.6018 | AG12: =IF(IFERROR(AE12/AC12-1,"")=0,"",IFERROR(+AE12/AC12-1,"")) -> -0.010951285 | AH12: =IF(IFERROR(AE12/AA12-1,"")=0,"",IFERROR(+AE12/AA12-1,"")) | AI12: =IFERROR(AI4*1000/AI8,"") | AK12: =IFERROR(AK4*1000/AK8,"") -> 1606.9005 | AM12: =IFERROR(AM4*1000/AM8,"") -> 1712.1706 | AO12: =IF(IFERROR(AM12/AK12-1,"")=0,"",IFERROR(+AM12/AK12-1,"")) -> 0.06551129 | AP12: =IF(IFERROR(AM12/AI12-1,"")=0,"",IFERROR(+AM12/AI12-1,"")) | AQ12: =IFERROR(AQ4*1000/AQ8,"") | AS12: =IFERROR(AS4*1000/AS8,"") -> 1702.0316 | AU12: =IFERROR(AU4*1000/AU8,"") -> 1555.0241 | AW12: =IF(IFERROR(AU12/AS12-1,"")=0,"",IFERROR(+AU12/AS12-1,"")) -> -0.086371776 | AX12: =IF(IFERROR(AU12/AQ12-1,"")=0,"",IFERROR(+AU12/AQ12-1,"")) | AY12: =IFERROR(AY4*1000/AY8,"") | BA12: =IFERROR(BA4*1000/BA8,"") -> 1752.5168 | BC12: =IFERROR(BC4*1000/BC8,"") | BE12: =IF(IFERROR(BC12/BA12-1,"")=0,"",IFERROR(+BC12/BA12-1,"")) | BF12: =IF(IFERROR(BC12/AY12-1,"")=0,"",IFERROR(+BC12/AY12-1,"")) | BG12: =IFERROR(BG4*1000/BG8,"") | BI12: =IFERROR(BI4*1000/BI8,"") -> 1752.5168 | BK12: =IFERROR(BK4*1000/BK8,"") | BM12: =IF(IFERROR(BK12/BI12-1,"")=0,"",IFERROR(+BK12/BI12-1,"")) | BN12: =IF(IFERROR(BK12/BG12-1,"")=0,"",IFERROR(+BK12/BG12-1,"")) | BO12: =IFERROR(BO4*1000/BO8,"") | BQ12: =IFERROR(BQ4*1000/BQ8,"") -> 1703.5294 | BS12: =IFERROR(BS4*1000/BS8,"") | BU12: =IF(IFERROR(BS12/BQ12-1,"")=0,"",IFERROR(+BS12/BQ12-1,"")) | BV12: =IF(IFERROR(BS12/BO12-1,"")=0,"",IFERROR(+BS12/BO12-1,"")) | BW12: =IFERROR(BW4*1000/BW8,"") | BY12: =IFERROR(BY4*1000/BY8,"") -> 1360.5886 | CA12: =IFERROR(CA4*1000/CA8,"") | CC12: =IF(IFERROR(CA12/BY12-1,"")=0,"",IFERROR(+CA12/BY12-1,"")) | CD12: =IF(IFERROR(CA12/BW12-1,"")=0,"",IFERROR(+CA12/BW12-1,"")) | CE12: =IFERROR(CE4*1000/CE8,"") | CG12: =IFERROR(CG4*1000/CG8,"") -> 1422.9227 | CI12: =IFERROR(CI4*1000/CI8,"") | CK12: =IF(IFERROR(CI12/CG12-1,"")=0,"",IFERROR(+CI12/CG12-1,"")) | CL12: =IF(IFERROR(CI12/CE12-1,"")=0,"",IFERROR(+CI12/CE12-1,"")) | CM12: =IFERROR(CM4*1000/CM8,"") | CO12: =IFERROR(CO4*1000/CO8,"") -> 1526.7036 | CQ12: =IFERROR(CQ4*1000/CQ8,"") | CS12: =IF(IFERROR(CQ12/CO12-1,"")=0,"",IFERROR(+CQ12/CO12-1,"")) | CT12: =IF(IFERROR(CQ12/CM12-1,"")=0,"",IFERROR(+CQ12/CM12-1,"")) | CU12: =SUM(C12,K12,S12,AA12,AI12,AQ12,AY12,BG12,BO12,BW12,CE12,CM12) -> 0 | CV12: =IFERROR(CU12/CU$4,"") | CW12: =SUM(E12,M12,U12,AC12,AK12,AS12,BA12,BI12,BQ12,BY12,CG12,CO12) -> 14507.71 | CX12: =IFERROR(CW12/CW$4,"") -> 0.10940135 | CY12: =SUM(G12,O12,W12,AE12,AM12,AU12,BC12,BK12,BS12,CA12,CI12,CQ12) -> 6486.4273 | CZ12: =IFERROR(CY12/CY$4,"") -> 0.13075091 | DA12: =IF(IFERROR(CY12/CW12-1,"")=0,"",IFERROR(+CY12/CW12-1,"")) -> -0.55289792 | DB12: =IF(IFERROR(CY12/CU12-1,"")=0,"",IFERROR(+CY12/CU12-1,""))
B13: зал | C13: =IFERROR(C5*1000/C9,"-") -> - | E13: =IFERROR(E5*1000/E9,"-") -> - | G13: =IFERROR(G5*1000/G9,"") | I13: =IF(IFERROR(G13/E13-1,"")=0,"",IFERROR(+G13/E13-1,"")) | J13: =IF(IFERROR(G13/C13-1,"")=0,"",IFERROR(+G13/C13-1,"")) | K13: =IFERROR(K5*1000/K9,"-") -> - | M13: =IFERROR(M5*1000/M9,"-") -> - | O13: =IFERROR(O5*1000/O9,"") | Q13: =IF(IFERROR(O13/M13-1,"")=0,"",IFERROR(+O13/M13-1,"")) | R13: =IF(IFERROR(O13/K13-1,"")=0,"",IFERROR(+O13/K13-1,"")) | S13: =IFERROR(S5*1000/S9,"-") -> - | U13: =IFERROR(U5*1000/U9,"-") -> - | W13: =IFERROR(W5*1000/W9,"") -> 1557.6307 | Y13: =IF(IFERROR(W13/U13-1,"")=0,"",IFERROR(+W13/U13-1,"")) | Z13: =IF(IFERROR(W13/S13-1,"")=0,"",IFERROR(+W13/S13-1,"")) | AA13: =IFERROR(AA5*1000/AA9,"-") -> - | AC13: =IFERROR(AC5*1000/AC9,"-") -> 1680 | AE13: =IFERROR(AE5*1000/AE9,"") -> 1661.6018 | AG13: =IF(IFERROR(AE13/AC13-1,"")=0,"",IFERROR(+AE13/AC13-1,"")) -> -0.010951285 | AH13: =IF(IFERROR(AE13/AA13-1,"")=0,"",IFERROR(+AE13/AA13-1,"")) | AI13: =IFERROR(AI5*1000/AI9,"-") -> - | AK13: =IFERROR(AK5*1000/AK9,"-") -> 1600 | AM13: =IFERROR(AM5*1000/AM9,"") -> 1712.1706 | AO13: =IF(IFERROR(AM13/AK13-1,"")=0,"",IFERROR(+AM13/AK13-1,"")) -> 0.070106653 | AP13: =IF(IFERROR(AM13/AI13-1,"")=0,"",IFERROR(+AM13/AI13-1,"")) | AQ13: =IFERROR(AQ5*1000/AQ9,"-") -> - | AS13: =IFERROR(AS5*1000/AS9,"-") -> 1700 | AU13: =IFERROR(AU5*1000/AU9,"") -> 1568.8884 | AW13: =IF(IFERROR(AU13/AS13-1,"")=0,"",IFERROR(+AU13/AS13-1,"")) -> -0.077124478 | AX13: =IF(IFERROR(AU13/AQ13-1,"")=0,"",IFERROR(+AU13/AQ13-1,"")) | AY13: =IFERROR(AY5*1000/AY9,"-") -> - | BA13: =IFERROR(BA5*1000/BA9,"-") -> 1750 | BC13: =IFERROR(BC5*1000/BC9,"") | BE13: =IF(IFERROR(BC13/BA13-1,"")=0,"",IFERROR(+BC13/BA13-1,"")) | BF13: =IF(IFERROR(BC13/AY13-1,"")=0,"",IFERROR(+BC13/AY13-1,"")) | BG13: =IFERROR(BG5*1000/BG9,"-") -> - | BI13: =IFERROR(BI5*1000/BI9,"-") -> 1750 | BK13: =IFERROR(BK5*1000/BK9,"") | BM13: =IF(IFERROR(BK13/BI13-1,"")=0,"",IFERROR(+BK13/BI13-1,"")) | BN13: =IF(IFERROR(BK13/BG13-1,"")=0,"",IFERROR(+BK13/BG13-1,"")) | BO13: =IFERROR(BO5*1000/BO9,"-") -> - | BQ13: =IFERROR(BQ5*1000/BQ9,"-") -> 1700 | BS13: =IFERROR(BS5*1000/BS9,"") | BU13: =IF(IFERROR(BS13/BQ13-1,"")=0,"",IFERROR(+BS13/BQ13-1,"")) | BV13: =IF(IFERROR(BS13/BO13-1,"")=0,"",IFERROR(+BS13/BO13-1,"")) | BW13: =IFERROR(BW5*1000/BW9,"-") -> - | BY13: =IFERROR(BY5*1000/BY9,"-") -> 1185.5202 | CA13: =IFERROR(CA5*1000/CA9,"") | CC13: =IF(IFERROR(CA13/BY13-1,"")=0,"",IFERROR(+CA13/BY13-1,"")) | CD13: =IF(IFERROR(CA13/BW13-1,"")=0,"",IFERROR(+CA13/BW13-1,"")) | CE13: =IFERROR(CE5*1000/CE9,"-") -> - | CG13: =IFERROR(CG5*1000/CG9,"-") -> 1277.8721 | CI13: =IFERROR(CI5*1000/CI9,"") | CK13: =IF(IFERROR(CI13/CG13-1,"")=0,"",IFERROR(+CI13/CG13-1,"")) | CL13: =IF(IFERROR(CI13/CE13-1,"")=0,"",IFERROR(+CI13/CE13-1,"")) | CM13: =IFERROR(CM5*1000/CM9,"-") -> - | CO13: =IFERROR(CO5*1000/CO9,"-") -> 1345.8401 | CQ13: =IFERROR(CQ5*1000/CQ9,"") | CS13: =IF(IFERROR(CQ13/CO13-1,"")=0,"",IFERROR(+CQ13/CO13-1,"")) | CT13: =IF(IFERROR(CQ13/CM13-1,"")=0,"",IFERROR(+CQ13/CM13-1,"")) | CU13: =SUM(C13,K13,S13,AA13,AI13,AQ13,AY13,BG13,BO13,BW13,CE13,CM13) -> 0 | CV13: =IFERROR(CU13/CU$4,"") | CW13: =SUM(E13,M13,U13,AC13,AK13,AS13,BA13,BI13,BQ13,BY13,CG13,CO13) -> 13989.232 | CX13: =IFERROR(CW13/CW$4,"") -> 0.10549155 | CY13: =SUM(G13,O13,W13,AE13,AM13,AU13,BC13,BK13,BS13,CA13,CI13,CQ13) -> 6500.2916 | CZ13: =IFERROR(CY13/CY$4,"") -> 0.13103038 | DA13: =IF(IFERROR(CY13/CW13-1,"")=0,"",IFERROR(+CY13/CW13-1,"")) -> -0.53533608 | DB13: =IF(IFERROR(CY13/CU13-1,"")=0,"",IFERROR(+CY13/CU13-1,""))
B14: доставка | C14: =IFERROR(C6*1000/C10,"-") -> - | E14: =IFERROR(E6*1000/E10,"-") -> - | G14: =IFERROR(G6*1000/G10,"") | I14: =IF(IFERROR(G14/E14-1,"")=0,"",IFERROR(+G14/E14-1,"")) | J14: =IF(IFERROR(G14/C14-1,"")=0,"",IFERROR(+G14/C14-1,"")) | K14: =IFERROR(K6*1000/K10,"-") -> - | M14: =IFERROR(M6*1000/M10,"-") -> - | O14: =IFERROR(O6*1000/O10,"") | Q14: =IF(IFERROR(O14/M14-1,"")=0,"",IFERROR(+O14/M14-1,"")) | R14: =IF(IFERROR(O14/K14-1,"")=0,"",IFERROR(+O14/K14-1,"")) | S14: =IFERROR(S6*1000/S10,"-") -> - | U14: =IFERROR(U6*1000/U10,"-") -> - | W14: =IFERROR(W6*1000/W10,"") | Y14: =IF(IFERROR(W14/U14-1,"")=0,"",IFERROR(+W14/U14-1,"")) | Z14: =IF(IFERROR(W14/S14-1,"")=0,"",IFERROR(+W14/S14-1,"")) | AA14: =IFERROR(AA6*1000/AA10,"-") -> - | AC14: =IFERROR(AC6*1000/AC10,"-") -> - | AE14: =IFERROR(AE6*1000/AE10,"") | AG14: =IF(IFERROR(AE14/AC14-1,"")=0,"",IFERROR(+AE14/AC14-1,"")) | AH14: =IF(IFERROR(AE14/AA14-1,"")=0,"",IFERROR(+AE14/AA14-1,"")) | AI14: =IFERROR(AI6*1000/AI10,"-") -> - | AK14: =IFERROR(AK6*1000/AK10,"-") -> 2000 | AM14: =IFERROR(AM6*1000/AM10,"") | AO14: =IF(IFERROR(AM14/AK14-1,"")=0,"",IFERROR(+AM14/AK14-1,"")) | AP14: =IF(IFERROR(AM14/AI14-1,"")=0,"",IFERROR(+AM14/AI14-1,"")) | AQ14: =IFERROR(AQ6*1000/AQ10,"-") -> - | AS14: =IFERROR(AS6*1000/AS10,"-") -> 2000 | AU14: =IFERROR(AU6*1000/AU10,"") -> 0 | AW14: =IF(IFERROR(AU14/AS14-1,"")=0,"",IFERROR(+AU14/AS14-1,"")) -> -1 | AX14: =IF(IFERROR(AU14/AQ14-1,"")=0,"",IFERROR(+AU14/AQ14-1,"")) | AY14: =IFERROR(AY6*1000/AY10,"-") -> - | BA14: =IFERROR(BA6*1000/BA10,"-") -> 2000 | BC14: =IFERROR(BC6*1000/BC10,"") | BE14: =IF(IFERROR(BC14/BA14-1,"")=0,"",IFERROR(+BC14/BA14-1,"")) | BF14: =IF(IFERROR(BC14/AY14-1,"")=0,"",IFERROR(+BC14/AY14-1,"")) | BG14: =IFERROR(BG6*1000/BG10,"-") -> - | BI14: =IFERROR(BI6*1000/BI10,"-") -> 2000 | BK14: =IFERROR(BK6*1000/BK10,"") | BM14: =IF(IFERROR(BK14/BI14-1,"")=0,"",IFERROR(+BK14/BI14-1,"")) | BN14: =IF(IFERROR(BK14/BG14-1,"")=0,"",IFERROR(+BK14/BG14-1,"")) | BO14: =IFERROR(BO6*1000/BO10,"-") -> - | BQ14: =IFERROR(BQ6*1000/BQ10,"-") -> 2000 | BS14: =IFERROR(BS6*1000/BS10,"") | BU14: =IF(IFERROR(BS14/BQ14-1,"")=0,"",IFERROR(+BS14/BQ14-1,"")) | BV14: =IF(IFERROR(BS14/BO14-1,"")=0,"",IFERROR(+BS14/BO14-1,"")) | BW14: =IFERROR(BW6*1000/BW10,"-") -> - | BY14: =IFERROR(BY6*1000/BY10,"-") -> 2324.736 | CA14: =IFERROR(CA6*1000/CA10,"") | CC14: =IF(IFERROR(CA14/BY14-1,"")=0,"",IFERROR(+CA14/BY14-1,"")) | CD14: =IF(IFERROR(CA14/BW14-1,"")=0,"",IFERROR(+CA14/BW14-1,"")) | CE14: =IFERROR(CE6*1000/CE10,"-") -> - | CG14: =IFERROR(CG6*1000/CG10,"-") -> 2250.7905 | CI14: =IFERROR(CI6*1000/CI10,"") | CK14: =IF(IFERROR(CI14/CG14-1,"")=0,"",IFERROR(+CI14/CG14-1,"")) | CL14: =IF(IFERROR(CI14/CE14-1,"")=0,"",IFERROR(+CI14/CE14-1,"")) | CM14: =IFERROR(CM6*1000/CM10,"-") -> - | CO14: =IFERROR(CO6*1000/CO10,"-") -> 2403.631 | CQ14: =IFERROR(CQ6*1000/CQ10,"") | CS14: =IF(IFERROR(CQ14/CO14-1,"")=0,"",IFERROR(+CQ14/CO14-1,"")) | CT14: =IF(IFERROR(CQ14/CM14-1,"")=0,"",IFERROR(+CQ14/CM14-1,"")) | CU14: =SUM(C14,K14,S14,AA14,AI14,AQ14,AY14,BG14,BO14,BW14,CE14,CM14) -> 0 | CV14: =IFERROR(CU14/CU$4,"") | CW14: =SUM(E14,M14,U14,AC14,AK14,AS14,BA14,BI14,BQ14,BY14,CG14,CO14) -> 16979.157 | CX14: =IFERROR(CW14/CW$4,"") -> 0.12803831 | CY14: =SUM(G14,O14,W14,AE14,AM14,AU14,BC14,BK14,BS14,CA14,CI14,CQ14) -> 0 | CZ14: =IFERROR(CY14/CY$4,"") -> 0 | DA14: =IF(IFERROR(CY14/CW14-1,"")=0,"",IFERROR(+CY14/CW14-1,"")) -> -1 | DB14: =IF(IFERROR(CY14/CU14-1,"")=0,"",IFERROR(+CY14/CU14-1,""))
B15: Доп подразделение (назвать по-своему или пустое) | C15: =IFERROR(C7*1000/C11,"-") -> - | E15: =IFERROR(E7*1000/E11,"-") -> - | G15: =IFERROR(G7*1000/G11,"") | I15: =IF(IFERROR(G15/E15-1,"")=0,"",IFERROR(+G15/E15-1,"")) | J15: =IF(IFERROR(G15/C15-1,"")=0,"",IFERROR(+G15/C15-1,"")) | K15: =IFERROR(K7*1000/K11,"-") -> - | M15: =IFERROR(M7*1000/M11,"-") -> - | O15: =IFERROR(O7*1000/O11,"") | Q15: =IF(IFERROR(O15/M15-1,"")=0,"",IFERROR(+O15/M15-1,"")) | R15: =IF(IFERROR(O15/K15-1,"")=0,"",IFERROR(+O15/K15-1,"")) | S15: =IFERROR(S7*1000/S11,"-") -> - | U15: =IFERROR(U7*1000/U11,"-") -> - | W15: =IFERROR(W7*1000/W11,"") | Y15: =IF(IFERROR(W15/U15-1,"")=0,"",IFERROR(+W15/U15-1,"")) | Z15: =IF(IFERROR(W15/S15-1,"")=0,"",IFERROR(+W15/S15-1,"")) | AA15: =IFERROR(AA7*1000/AA11,"-") -> - | AC15: =IFERROR(AC7*1000/AC11,"-") -> - | AE15: =IFERROR(AE7*1000/AE11,"") | AG15: =IF(IFERROR(AE15/AC15-1,"")=0,"",IFERROR(+AE15/AC15-1,"")) | AH15: =IF(IFERROR(AE15/AA15-1,"")=0,"",IFERROR(+AE15/AA15-1,"")) | AI15: =IFERROR(AI7*1000/AI11,"-") -> - | AK15: =IFERROR(AK7*1000/AK11,"-") -> - | AM15: =IFERROR(AM7*1000/AM11,"") | AO15: =IF(IFERROR(AM15/AK15-1,"")=0,"",IFERROR(+AM15/AK15-1,"")) | AP15: =IF(IFERROR(AM15/AI15-1,"")=0,"",IFERROR(+AM15/AI15-1,"")) | AQ15: =IFERROR(AQ7*1000/AQ11,"-") -> - | AS15: =IFERROR(AS7*1000/AS11,"-") -> - | AU15: =IFERROR(AU7*1000/AU11,"") | AW15: =IF(IFERROR(AU15/AS15-1,"")=0,"",IFERROR(+AU15/AS15-1,"")) | AX15: =IF(IFERROR(AU15/AQ15-1,"")=0,"",IFERROR(+AU15/AQ15-1,"")) | AY15: =IFERROR(AY7*1000/AY11,"-") -> - | BA15: =IFERROR(BA7*1000/BA11,"-") -> - | BC15: =IFERROR(BC7*1000/BC11,"") | BE15: =IF(IFERROR(BC15/BA15-1,"")=0,"",IFERROR(+BC15/BA15-1,"")) | BF15: =IF(IFERROR(BC15/AY15-1,"")=0,"",IFERROR(+BC15/AY15-1,"")) | BG15: =IFERROR(BG7*1000/BG11,"-") -> - | BI15: =IFERROR(BI7*1000/BI11,"-") -> - | BK15: =IFERROR(BK7*1000/BK11,"") | BM15: =IF(IFERROR(BK15/BI15-1,"")=0,"",IFERROR(+BK15/BI15-1,"")) | BN15: =IF(IFERROR(BK15/BG15-1,"")=0,"",IFERROR(+BK15/BG15-1,"")) | BO15: =IFERROR(BO7*1000/BO11,"-") -> - | BQ15: =IFERROR(BQ7*1000/BQ11,"-") -> - | BS15: =IFERROR(BS7*1000/BS11,"") | BU15: =IF(IFERROR(BS15/BQ15-1,"")=0,"",IFERROR(+BS15/BQ15-1,"")) | BV15: =IF(IFERROR(BS15/BO15-1,"")=0,"",IFERROR(+BS15/BO15-1,"")) | BW15: =IFERROR(BW7*1000/BW11,"-") -> - | BY15: =IFERROR(BY7*1000/BY11,"-") -> - | CA15: =IFERROR(CA7*1000/CA11,"") | CC15: =IF(IFERROR(CA15/BY15-1,"")=0,"",IFERROR(+CA15/BY15-1,"")) | CD15: =IF(IFERROR(CA15/BW15-1,"")=0,"",IFERROR(+CA15/BW15-1,"")) | CE15: =IFERROR(CE7*1000/CE11,"-") -> - | CG15: =IFERROR(CG7*1000/CG11,"-") -> - | CI15: =IFERROR(CI7*1000/CI11,"") | CK15: =IF(IFERROR(CI15/CG15-1,"")=0,"",IFERROR(+CI15/CG15-1,"")) | CL15: =IF(IFERROR(CI15/CE15-1,"")=0,"",IFERROR(+CI15/CE15-1,"")) | CM15: =IFERROR(CM7*1000/CM11,"-") -> - | CO15: =IFERROR(CO7*1000/CO11,"-") -> - | CQ15: =IFERROR(CQ7*1000/CQ11,"") | CS15: =IF(IFERROR(CQ15/CO15-1,"")=0,"",IFERROR(+CQ15/CO15-1,"")) | CT15: =IF(IFERROR(CQ15/CM15-1,"")=0,"",IFERROR(+CQ15/CM15-1,"")) | CU15: =SUM(C15,K15,S15,AA15,AI15,AQ15,AY15,BG15,BO15,BW15,CE15,CM15) -> 0 | CV15: =IFERROR(CU15/CU$4,"") | CW15: =SUM(E15,M15,U15,AC15,AK15,AS15,BA15,BI15,BQ15,BY15,CG15,CO15) -> 0 | CX15: =IFERROR(CW15/CW$4,"") -> 0 | CY15: =SUM(G15,O15,W15,AE15,AM15,AU15,BC15,BK15,BS15,CA15,CI15,CQ15) -> 0 | CZ15: =IFERROR(CY15/CY$4,"") -> 0 | DA15: =IF(IFERROR(CY15/CW15-1,"")=0,"",IFERROR(+CY15/CW15-1,"")) | DB15: =IF(IFERROR(CY15/CU15-1,"")=0,"",IFERROR(+CY15/CU15-1,""))
B16: Себестоимость ИТОГО | C16: =+C17+C21 -> 0 | D16: =IFERROR(C16/C$4,"") | E16: =+E17+E21 -> 0 | F16: =IFERROR(E16/E$4,"") | G16: =+G17+G21 -> 0 | H16: =IFERROR(G16/G$4,"") | I16: =+IFERROR(H16-F16,"") | J16: =+IFERROR(H16-D16,"") | K16: =+K17+K21 -> 0 | L16: =IFERROR(K16/K$4,"") | M16: =+M17+M21 -> 0 | N16: =IFERROR(M16/M$4,"") | O16: =+O17+O21 -> 0 | P16: =IFERROR(O16/O$4,"") | Q16: =+IFERROR(P16-N16,"") | R16: =+IFERROR(P16-L16,"") | S16: =+S17+S21 -> 0 | T16: =IFERROR(S16/S$4,"") | U16: =+U17+U21 -> 0 | V16: =IFERROR(U16/U$4,"") | W16: =+W17+W21 -> 2056.6998 | X16: =IFERROR(W16/W$4,"") -> 0.3468355 | Y16: =+IFERROR(X16-V16,"") | Z16: =+IFERROR(X16-T16,"") | AA16: =+AA17+AA21 -> 0 | AB16: =IFERROR(AA16/AA$4,"") | AC16: =+AC17+AC21 -> 3417.96 | AD16: =IFERROR(AC16/AC$4,"") -> 0.25 | AE16: =+AE17+AE21 -> 3982.4001 | AF16: =IFERROR(AE16/AE$4,"") -> 0.29040633 | AG16: =+IFERROR(AF16-AD16,"") -> 0.040406335 | AH16: =+IFERROR(AF16-AB16,"") | AI16: =+AI17+AI21 -> 0 | AJ16: =IFERROR(AI16/AI$4,"") | AK16: =+AK17+AK21 -> 3493 | AL16: =IFERROR(AK16/AK$4,"") -> 0.25 | AM16: =+AM17+AM21 -> 4620.2513 | AN16: =IFERROR(AM16/AM$4,"") -> 0.29404772 | AO16: =+IFERROR(AN16-AL16,"") -> 0.044047721 | AP16: =+IFERROR(AN16-AJ16,"") | AQ16: =+AQ17+AQ21 -> 0 | AR16: =IFERROR(AQ16/AQ$4,"") | AS16: =+AS17+AS21 -> 4221.2 | AT16: =IFERROR(AS16/AS$4,"") -> 0.27992042 | AU16: =+AU17+AU21 -> 4111.6563 | AV16: =IFERROR(AU16/AU$4,"") -> 0.28846945 | AW16: =+IFERROR(AV16-AT16,"") -> 0.008549026 | AX16: =+IFERROR(AV16-AR16,"") | AY16: =+AY17+AY21 -> 0 | AZ16: =IFERROR(AY16/AY$4,"") | BA16: =+BA17+BA21 -> 4385.1 | BB16: =IFERROR(BA16/BA$4,"") -> 0.27988511 | BC16: =+BC17+BC21 -> 0 | BD16: =IFERROR(BC16/BC$4,"") | BE16: =+IFERROR(BD16-BB16,"") | BF16: =+IFERROR(BD16-AZ16,"") | BG16: =+BG17+BG21 -> 0 | BH16: =IFERROR(BG16/BG$4,"") | BI16: =+BI17+BI21 -> 4385.1 | BJ16: =IFERROR(BI16/BI$4,"") -> 0.27988511 | BK16: =+BK17+BK21 -> 0 | BL16: =IFERROR(BK16/BK$4,"") | BM16: =+IFERROR(BL16-BJ16,"") | BN16: =+IFERROR(BL16-BH16,"") | BO16: =+BO17+BO21 -> 0 | BP16: =IFERROR(BO16/BO$4,"") | BQ16: =+BQ17+BQ21 -> 4052.4 | BR16: =IFERROR(BQ16/BQ$4,"") -> 0.27986188 | BS16: =+BS17+BS21 -> 0 | BT16: =IFERROR(BS16/BS$4,"") | BU16: =+IFERROR(BT16-BR16,"") | BV16: =+IFERROR(BT16-BP16,"") | BW16: =+BW17+BW21 -> 0 | BX16: =IFERROR(BW16/BW$4,"") | BY16: =+BY17+BY21 -> 3182.6349 | BZ16: =IFERROR(BY16/BY$4,"") -> 0.22597472 | CA16: =+CA17+CA21 -> 0 | CB16: =IFERROR(CA16/CA$4,"") | CC16: =+IFERROR(CB16-BZ16,"") | CD16: =+IFERROR(CB16-BX16,"") | CE16: =+CE17+CE21 -> 0 | CF16: =IFERROR(CE16/CE$4,"") | CG16: =+CG17+CG21 -> 3338.1546 | CH16: =IFERROR(CG16/CG$4,"") -> 0.22956805 | CI16: =+CI17+CI21 -> 0 | CJ16: =IFERROR(CI16/CI$4,"") | CK16: =+IFERROR(CJ16-CH16,"") | CL16: =+IFERROR(CJ16-CF16,"") | CM16: =+CM17+CM21 -> 0 | CN16: =IFERROR(CM16/CM$4,"") | CO16: =+CO17+CO21 -> 3555.5831 | CP16: =IFERROR(CO16/CO$4,"") -> 0.23019323 | CQ16: =+CQ17+CQ21 -> 0 | CR16: =IFERROR(CQ16/CQ$4,"") | CS16: =+IFERROR(CR16-CP16,"") | CT16: =+IFERROR(CR16-CN16,"") | CU16: =SUM(C16,K16,S16,AA16,AI16,AQ16,AY16,BG16,BO16,BW16,CE16,CM16) -> 0 | CV16: =IFERROR(CU16/CU$4,"") | CW16: =SUM(E16,M16,U16,AC16,AK16,AS16,BA16,BI16,BQ16,BY16,CG16,CO16) -> 34031.133 | CX16: =IFERROR(CW16/CW$4,"") -> 0.25662574 | CY16: =SUM(G16,O16,W16,AE16,AM16,AU16,BC16,BK16,BS16,CA16,CI16,CQ16) -> 14771.008 | CZ16: =IFERROR(CY16/CY$4,"") -> 0.2977483 | DA16: =IF(IFERROR(CY16/CW16-1,"")=0,"",IFERROR(+CY16/CW16-1,"")) -> -0.56595604 | DB16: =IF(IFERROR(CY16/CU16-1,"")=0,"",IFERROR(+CY16/CU16-1,""))
B17: Себестоимость реализации, всего, в т.ч. | C17: =SUM(C18:C20) -> 0 | D17: =IFERROR(C17/C$4,"") | E17: =SUM(E18:E20) -> 0 | F17: =IFERROR(E17/E$4,"") | G17: =SUM(G18:G20) -> 0 | H17: =IFERROR(G17/G$4,"") | I17: =+IFERROR(H17-F17,"") | J17: =+IFERROR(H17-D17,"") | K17: =SUM(K18:K20) -> 0 | L17: =IFERROR(K17/K$4,"") | M17: =SUM(M18:M20) -> 0 | N17: =IFERROR(M17/M$4,"") | O17: =SUM(O18:O20) -> 0 | P17: =IFERROR(O17/O$4,"") | Q17: =+IFERROR(P17-N17,"") | R17: =+IFERROR(P17-L17,"") | S17: =SUM(S18:S20) -> 0 | T17: =IFERROR(S17/S$4,"") | U17: =SUM(U18:U20) -> 0 | V17: =IFERROR(U17/U$4,"") | W17: =SUM(W18:W20) -> 1600.561 | X17: =IFERROR(W17/W$4,"") -> 0.26991366 | Y17: =+IFERROR(X17-V17,"") | Z17: =+IFERROR(X17-T17,"") | AA17: =SUM(AA18:AA20) -> 0 | AB17: =IFERROR(AA17/AA$4,"") | AC17: =SUM(AC18:AC20) -> 3417.96 | AD17: =IFERROR(AC17/AC$4,"") -> 0.25 | AE17: =SUM(AE18:AE20) -> 3746.317 | AF17: =IFERROR(AE17/AE$4,"") -> 0.27319058 | AG17: =+IFERROR(AF17-AD17,"") -> 0.023190576 | AH17: =+IFERROR(AF17-AB17,"") | AI17: =SUM(AI18:AI20) -> 0 | AJ17: =IFERROR(AI17/AI$4,"") | AK17: =SUM(AK18:AK20) -> 3493 | AL17: =IFERROR(AK17/AK$4,"") -> 0.25 | AM17: =SUM(AM18:AM20) -> 4343.27 | AN17: =IFERROR(AM17/AM$4,"") -> 0.27641974 | AO17: =+IFERROR(AN17-AL17,"") -> 0.026419737 | AP17: =+IFERROR(AN17-AJ17,"") | AQ17: =SUM(AQ18:AQ20) -> 0 | AR17: =IFERROR(AQ17/AQ$4,"") | AS17: =SUM(AS18:AS20) -> 4221.2 | AT17: =IFERROR(AS17/AS$4,"") -> 0.27992042 | AU17: =SUM(AU18:AU20) -> 3960.784 | AV17: =IFERROR(AU17/AU$4,"") -> 0.27788441 | AW17: =+IFERROR(AV17-AT17,"") -> -0.0020360167 | AX17: =+IFERROR(AV17-AR17,"") | AY17: =SUM(AY18:AY20) -> 0 | AZ17: =IFERROR(AY17/AY$4,"") | BA17: =SUM(BA18:BA20) -> 4385.1 | BB17: =IFERROR(BA17/BA$4,"") -> 0.27988511 | BC17: =SUM(BC18:BC20) -> 0 | BD17: =IFERROR(BC17/BC$4,"") | BE17: =+IFERROR(BD17-BB17,"") | BF17: =+IFERROR(BD17-AZ17,"") | BG17: =SUM(BG18:BG20) -> 0 | BH17: =IFERROR(BG17/BG$4,"") | BI17: =SUM(BI18:BI20) -> 4385.1 | BJ17: =IFERROR(BI17/BI$4,"") -> 0.27988511 | BK17: =SUM(BK18:BK20) -> 0 | BL17: =IFERROR(BK17/BK$4,"") | BM17: =+IFERROR(BL17-BJ17,"") | BN17: =+IFERROR(BL17-BH17,"") | BO17: =SUM(BO18:BO20) -> 0 | BP17: =IFERROR(BO17/BO$4,"") | BQ17: =SUM(BQ18:BQ20) -> 4052.4 | BR17: =IFERROR(BQ17/BQ$4,"") -> 0.27986188 | BS17: =SUM(BS18:BS20) -> 0 | BT17: =IFERROR(BS17/BS$4,"") | BU17: =+IFERROR(BT17-BR17,"") | BV17: =+IFERROR(BT17-BP17,"") | BW17: =SUM(BW18:BW20) -> 0 | BX17: =IFERROR(BW17/BW$4,"") | BY17: =SUM(BY18:BY20) -> 3182.6349 | BZ17: =IFERROR(BY17/BY$4,"") -> 0.22597472 | CA17: =SUM(CA18:CA20) -> 0 | CB17: =IFERROR(CA17/CA$4,"") | CC17: =+IFERROR(CB17-BZ17,"") | CD17: =+IFERROR(CB17-BX17,"") | CE17: =SUM(CE18:CE20) -> 0 | CF17: =IFERROR(CE17/CE$4,"") | CG17: =SUM(CG18:CG20) -> 3338.1546 | CH17: =IFERROR(CG17/CG$4,"") -> 0.22956805 | CI17: =SUM(CI18:CI20) -> 0 | CJ17: =IFERROR(CI17/CI$4,"") | CK17: =+IFERROR(CJ17-CH17,"") | CL17: =+IFERROR(CJ17-CF17,"") | CM17: =SUM(CM18:CM20) -> 0 | CN17: =IFERROR(CM17/CM$4,"") | CO17: =SUM(CO18:CO20) -> 3555.5831 | CP17: =IFERROR(CO17/CO$4,"") -> 0.23019323 | CQ17: =SUM(CQ18:CQ20) -> 0 | CR17: =IFERROR(CQ17/CQ$4,"") | CS17: =+IFERROR(CR17-CP17,"") | CT17: =+IFERROR(CR17-CN17,"") | CU17: =SUM(C17,K17,S17,AA17,AI17,AQ17,AY17,BG17,BO17,BW17,CE17,CM17) -> 0 | CV17: =IFERROR(CU17/CU$4,"") | CW17: =SUM(E17,M17,U17,AC17,AK17,AS17,BA17,BI17,BQ17,BY17,CG17,CO17) -> 34031.133 | CX17: =IFERROR(CW17/CW$4,"") -> 0.25662574 | CY17: =SUM(G17,O17,W17,AE17,AM17,AU17,BC17,BK17,BS17,CA17,CI17,CQ17) -> 13650.932 | CZ17: =IFERROR(CY17/CY$4,"") -> 0.27517025 | DA17: =IF(IFERROR(CY17/CW17-1,"")=0,"",IFERROR(+CY17/CW17-1,"")) -> -0.5988693 | DB17: =IF(IFERROR(CY17/CU17-1,"")=0,"",IFERROR(+CY17/CU17-1,""))
B18: зал | D18: =IFERROR(C18/C$5,"") | F18: =IFERROR(E18/E$5,"") | G18: =+'Отчет о фин.рез.'!B16 -> 0 | H18: =IFERROR(G18/G$5,"") | I18: =+IFERROR(H18-F18,"") | J18: =+IFERROR(H18-D18,"") | L18: =IFERROR(K18/K$5,"") | N18: =IFERROR(M18/M$5,"") | O18: =+'Отчет о фин.рез.'!C16 -> 0 | P18: =IFERROR(O18/O$5,"") | Q18: =+IFERROR(P18-N18,"") | R18: =+IFERROR(P18-L18,"") | T18: =IFERROR(S18/S$5,"") | U18: 0 | V18: =IFERROR(U18/U$5,"") | W18: =+'Отчет о фин.рез.'!D16 -> 1600.561 | X18: =IFERROR(W18/W$5,"") -> 0.26991366 | Y18: =+IFERROR(X18-V18,"") | Z18: =+IFERROR(X18-T18,"") | AB18: =IFERROR(AA18/AA$5,"") | AC18: 3417.96 | AD18: =IFERROR(AC18/AC$5,"") -> 0.25 | AE18: =+'Отчет о фин.рез.'!E16 -> 3746.317 | AF18: =IFERROR(AE18/AE$5,"") -> 0.27319058 | AG18: =+IFERROR(AF18-AD18,"") -> 0.023190576 | AH18: =+IFERROR(AF18-AB18,"") | AJ18: =IFERROR(AI18/AI$5,"") | AK18: 3418 | AL18: =IFERROR(AK18/AK$5,"") -> 0.25 | AM18: =+'Отчет о фин.рез.'!F16 -> 4343.27 | AN18: =IFERROR(AM18/AM$5,"") -> 0.27641974 | AO18: =+IFERROR(AN18-AL18,"") -> 0.026419737 | AP18: =+IFERROR(AN18-AJ18,"") | AR18: =IFERROR(AQ18/AQ$5,"") | AS18: 4188.8 | AT18: =IFERROR(AS18/AS$5,"") -> 0.28 | AU18: =+'Отчет о фин.рез.'!G16 -> 3960.784 | AV18: =IFERROR(AU18/AU$5,"") -> 0.27788441 | AW18: =+IFERROR(AV18-AT18,"") -> -0.0021155923 | AX18: =+IFERROR(AV18-AR18,"") | AZ18: =IFERROR(AY18/AY$5,"") | BA18: 4336.5 | BB18: =IFERROR(BA18/BA$5,"") -> 0.28 | BC18: =+'Отчет о фин.рез.'!H16 -> 0 | BD18: =IFERROR(BC18/BC$5,"") | BE18: =+IFERROR(BD18-BB18,"") | BF18: =+IFERROR(BD18-AZ18,"") | BH18: =IFERROR(BG18/BG$5,"") | BI18: 4336.5 | BJ18: =IFERROR(BI18/BI$5,"") -> 0.28 | BK18: =+'Отчет о фин.рез.'!I16 -> 0 | BL18: =IFERROR(BK18/BK$5,"") | BM18: =+IFERROR(BL18-BJ18,"") | BN18: =+IFERROR(BL18-BH18,"") | BP18: =IFERROR(BO18/BO$5,"") | BQ18: 3998.4 | BR18: =IFERROR(BQ18/BQ$5,"") -> 0.28 | BS18: =+'Отчет о фин.рез.'!J16 -> 0 | BT18: =IFERROR(BS18/BS$5,"") | BU18: =+IFERROR(BT18-BR18,"") | BV18: =+IFERROR(BT18-BP18,"") | BX18: =IFERROR(BW18/BW$5,"") | BY18: 2344.4898 | BZ18: =IFERROR(BY18/BY$5,"") -> 0.22573652 | CA18: =+'Отчет о фин.рез.'!K16 -> 0 | CB18: =IFERROR(CA18/CA$5,"") | CC18: =+IFERROR(CB18-BZ18,"") | CD18: =+IFERROR(CB18-BX18,"") | CF18: =IFERROR(CE18/CE$5,"") | CG18: 2551.3453 | CH18: =IFERROR(CG18/CG$5,"") -> 0.22960617 | CI18: =+'Отчет о фин.рез.'!L16 -> 0 | CJ18: =IFERROR(CI18/CI$5,"") | CK18: =+IFERROR(CJ18-CH18,"") | CL18: =+IFERROR(CJ18-CF18,"") | CN18: =IFERROR(CM18/CM$5,"") | CO18: 2593.7642 | CP18: =IFERROR(CO18/CO$5,"") -> 0.22977865 | CQ18: =+'Отчет о фин.рез.'!M16 -> 0 | CR18: =IFERROR(CQ18/CQ$5,"") | CS18: =+IFERROR(CR18-CP18,"") | CT18: =+IFERROR(CR18-CN18,"") | CU18: =SUM(C18,K18,S18,AA18,AI18,AQ18,AY18,BG18,BO18,BW18,CE18,CM18) -> 0 | CV18: =IFERROR(CU18/CU$4,"") | CW18: =SUM(E18,M18,U18,AC18,AK18,AS18,BA18,BI18,BQ18,BY18,CG18,CO18) -> 31185.759 | CX18: =IFERROR(CW18/CW$4,"") -> 0.23516903 | CY18: =SUM(G18,O18,W18,AE18,AM18,AU18,BC18,BK18,BS18,CA18,CI18,CQ18) -> 13650.932 | CZ18: =IFERROR(CY18/CY$4,"") -> 0.27517025 | DA18: =IF(IFERROR(CY18/CW18-1,"")=0,"",IFERROR(+CY18/CW18-1,"")) -> -0.56227033 | DB18: =IF(IFERROR(CY18/CU18-1,"")=0,"",IFERROR(+CY18/CU18-1,""))
B19: доставка | D19: =IFERROR(C19/C$6,"") | F19: =IFERROR(E19/E$6,"") | G19: =+'Отчет о фин.рез.'!B17 -> 0 | H19: =IFERROR(G19/G$6,"") | I19: =+IFERROR(H19-F19,"") | J19: =+IFERROR(H19-D19,"") | L19: =IFERROR(K19/K$6,"") | N19: =IFERROR(M19/M$6,"") | O19: =+'Отчет о фин.рез.'!C17 -> 0 | P19: =IFERROR(O19/O$6,"") | Q19: =+IFERROR(P19-N19,"") | R19: =+IFERROR(P19-L19,"") | T19: =IFERROR(S19/S$6,"") | U19: 0 | V19: =IFERROR(U19/U$6,"") | W19: =+'Отчет о фин.рез.'!D17 -> 0 | X19: =IFERROR(W19/W$6,"") | Y19: =+IFERROR(X19-V19,"") | Z19: =+IFERROR(X19-T19,"") | AB19: =IFERROR(AA19/AA$6,"") | AC19: 0 | AD19: =IFERROR(AC19/AC$6,"") | AE19: =+'Отчет о фин.рез.'!E17 -> 0 | AF19: =IFERROR(AE19/AE$6,"") | AG19: =+IFERROR(AF19-AD19,"") | AH19: =+IFERROR(AF19-AB19,"") | AJ19: =IFERROR(AI19/AI$6,"") | AK19: 75 | AL19: =IFERROR(AK19/AK$6,"") -> 0.25 | AM19: =+'Отчет о фин.рез.'!F17 -> 0 | AN19: =IFERROR(AM19/AM$6,"") | AO19: =+IFERROR(AN19-AL19,"") | AP19: =+IFERROR(AN19-AJ19,"") | AR19: =IFERROR(AQ19/AQ$6,"") | AS19: 32.4 | AT19: =IFERROR(AS19/AS$6,"") -> 0.27 | AU19: =+'Отчет о фин.рез.'!G17 -> 0 | AV19: =IFERROR(AU19/AU$6,"") | AW19: =+IFERROR(AV19-AT19,"") | AX19: =+IFERROR(AV19-AR19,"") | AZ19: =IFERROR(AY19/AY$6,"") | BA19: 48.6 | BB19: =IFERROR(BA19/BA$6,"") -> 0.27 | BC19: =+'Отчет о фин.рез.'!H17 -> 0 | BD19: =IFERROR(BC19/BC$6,"") | BE19: =+IFERROR(BD19-BB19,"") | BF19: =+IFERROR(BD19-AZ19,"") | BH19: =IFERROR(BG19/BG$6,"") | BI19: 48.6 | BJ19: =IFERROR(BI19/BI$6,"") -> 0.27 | BK19: =+'Отчет о фин.рез.'!I17 -> 0 | BL19: =IFERROR(BK19/BK$6,"") | BM19: =+IFERROR(BL19-BJ19,"") | BN19: =+IFERROR(BL19-BH19,"") | BP19: =IFERROR(BO19/BO$6,"") | BQ19: 54 | BR19: =IFERROR(BQ19/BQ$6,"") -> 0.27 | BS19: =+'Отчет о фин.рез.'!J17 -> 0 | BT19: =IFERROR(BS19/BS$6,"") | BU19: =+IFERROR(BT19-BR19,"") | BV19: =+IFERROR(BT19-BP19,"") | BX19: =IFERROR(BW19/BW$6,"") | BY19: 838.14516 | BZ19: =IFERROR(BY19/BY$6,"") -> 0.22664371 | CA19: =+'Отчет о фин.рез.'!K17 -> 0 | CB19: =IFERROR(CA19/CA$6,"") | CC19: =+IFERROR(CB19-BZ19,"") | CD19: =+IFERROR(CB19-BX19,"") | CF19: =IFERROR(CE19/CE$6,"") | CG19: 786.80927 | CH19: =IFERROR(CG19/CG$6,"") -> 0.22944452 | CI19: =+'Отчет о фин.рез.'!L17 -> 0 | CJ19: =IFERROR(CI19/CI$6,"") | CK19: =+IFERROR(CJ19-CH19,"") | CL19: =+IFERROR(CJ19-CF19,"") | CN19: =IFERROR(CM19/CM$6,"") | CO19: 961.8189 | CP19: =IFERROR(CO19/CO$6,"") -> 0.23131873 | CQ19: =+'Отчет о фин.рез.'!M17 -> 0 | CR19: =IFERROR(CQ19/CQ$6,"") | CS19: =+IFERROR(CR19-CP19,"") | CT19: =+IFERROR(CR19-CN19,"") | CU19: =SUM(C19,K19,S19,AA19,AI19,AQ19,AY19,BG19,BO19,BW19,CE19,CM19) -> 0 | CV19: =IFERROR(CU19/CU$4,"") | CW19: =SUM(E19,M19,U19,AC19,AK19,AS19,BA19,BI19,BQ19,BY19,CG19,CO19) -> 2845.3733 | CX19: =IFERROR(CW19/CW$4,"") -> 0.021456707 | CY19: =SUM(G19,O19,W19,AE19,AM19,AU19,BC19,BK19,BS19,CA19,CI19,CQ19) -> 0 | CZ19: =IFERROR(CY19/CY$4,"") -> 0 | DA19: =IF(IFERROR(CY19/CW19-1,"")=0,"",IFERROR(+CY19/CW19-1,"")) -> -1 | DB19: =IF(IFERROR(CY19/CU19-1,"")=0,"",IFERROR(+CY19/CU19-1,""))
B20: Доп подразделение (назвать по-своему или пустое) | D20: =IFERROR(C20/C$7,"") | F20: =IFERROR(E20/E$7,"") | G20: =+'Отчет о фин.рез.'!B18 -> 0 | H20: =IFERROR(G20/G$7,"") | I20: =+IFERROR(H20-F20,"") | J20: =+IFERROR(H20-D20,"") | L20: =IFERROR(K20/K$7,"") | N20: =IFERROR(M20/M$7,"") | O20: =+'Отчет о фин.рез.'!C18 -> 0 | P20: =IFERROR(O20/O$7,"") | Q20: =+IFERROR(P20-N20,"") | R20: =+IFERROR(P20-L20,"") | T20: =IFERROR(S20/S$7,"") | U20: 0 | V20: =IFERROR(U20/U$7,"") | W20: =+'Отчет о фин.рез.'!D18 -> 0 | X20: =IFERROR(W20/W$7,"") | Y20: =+IFERROR(X20-V20,"") | Z20: =+IFERROR(X20-T20,"") | AB20: =IFERROR(AA20/AA$7,"") | AC20: 0 | AD20: =IFERROR(AC20/AC$7,"") | AE20: =+'Отчет о фин.рез.'!E18 -> 0 | AF20: =IFERROR(AE20/AE$7,"") | AG20: =+IFERROR(AF20-AD20,"") | AH20: =+IFERROR(AF20-AB20,"") | AJ20: =IFERROR(AI20/AI$7,"") | AK20: 0 | AL20: =IFERROR(AK20/AK$7,"") | AM20: =+'Отчет о фин.рез.'!F18 -> 0 | AN20: =IFERROR(AM20/AM$7,"") | AO20: =+IFERROR(AN20-AL20,"") | AP20: =+IFERROR(AN20-AJ20,"") | AR20: =IFERROR(AQ20/AQ$7,"") | AS20: 0 | AT20: =IFERROR(AS20/AS$7,"") | AU20: =+'Отчет о фин.рез.'!G18 -> 0 | AV20: =IFERROR(AU20/AU$7,"") | AW20: =+IFERROR(AV20-AT20,"") | AX20: =+IFERROR(AV20-AR20,"") | AZ20: =IFERROR(AY20/AY$7,"") | BA20: 0 | BB20: =IFERROR(BA20/BA$7,"") | BC20: =+'Отчет о фин.рез.'!H18 -> 0 | BD20: =IFERROR(BC20/BC$7,"") | BE20: =+IFERROR(BD20-BB20,"") | BF20: =+IFERROR(BD20-AZ20,"") | BH20: =IFERROR(BG20/BG$7,"") | BI20: 0 | BJ20: =IFERROR(BI20/BI$7,"") | BK20: =+'Отчет о фин.рез.'!I18 -> 0 | BL20: =IFERROR(BK20/BK$7,"") | BM20: =+IFERROR(BL20-BJ20,"") | BN20: =+IFERROR(BL20-BH20,"") | BP20: =IFERROR(BO20/BO$7,"") | BQ20: 0 | BR20: =IFERROR(BQ20/BQ$7,"") | BS20: =+'Отчет о фин.рез.'!J18 -> 0 | BT20: =IFERROR(BS20/BS$7,"") | BU20: =+IFERROR(BT20-BR20,"") | BV20: =+IFERROR(BT20-BP20,"") | BX20: =IFERROR(BW20/BW$7,"") | BY20: 0 | BZ20: =IFERROR(BY20/BY$7,"") | CA20: =+'Отчет о фин.рез.'!K18 -> 0 | CB20: =IFERROR(CA20/CA$7,"") | CC20: =+IFERROR(CB20-BZ20,"") | CD20: =+IFERROR(CB20-BX20,"") | CF20: =IFERROR(CE20/CE$7,"") | CG20: 0 | CH20: =IFERROR(CG20/CG$7,"") | CI20: =+'Отчет о фин.рез.'!L18 -> 0 | CJ20: =IFERROR(CI20/CI$7,"") | CK20: =+IFERROR(CJ20-CH20,"") | CL20: =+IFERROR(CJ20-CF20,"") | CN20: =IFERROR(CM20/CM$7,"") | CO20: 0 | CP20: =IFERROR(CO20/CO$7,"") | CQ20: =+'Отчет о фин.рез.'!M18 -> 0 | CR20: =IFERROR(CQ20/CQ$7,"") | CS20: =+IFERROR(CR20-CP20,"") | CT20: =+IFERROR(CR20-CN20,"") | CU20: =SUM(C20,K20,S20,AA20,AI20,AQ20,AY20,BG20,BO20,BW20,CE20,CM20) -> 0 | CV20: =IFERROR(CU20/CU$4,"") | CW20: =SUM(E20,M20,U20,AC20,AK20,AS20,BA20,BI20,BQ20,BY20,CG20,CO20) -> 0 | CX20: =IFERROR(CW20/CW$4,"") -> 0 | CY20: =SUM(G20,O20,W20,AE20,AM20,AU20,BC20,BK20,BS20,CA20,CI20,CQ20) -> 0 | CZ20: =IFERROR(CY20/CY$4,"") -> 0 | DA20: =IF(IFERROR(CY20/CW20-1,"")=0,"",IFERROR(+CY20/CW20-1,"")) | DB20: =IF(IFERROR(CY20/CU20-1,"")=0,"",IFERROR(+CY20/CU20-1,""))
B21: Произв.показатели | C21: =+C22+C29+C37 -> 0 | D21: =IF(IFERROR(C21/C$4,"")=0,"",IFERROR(C21/C$4,"")) | E21: =+E22+E29+E37 -> 0 | F21: =IF(IFERROR(E21/E$4,"")=0,"",IFERROR(E21/E$4,"")) | G21: =+G22+G29+G37 -> 0 | H21: =IF(IFERROR(G21/G$4,"")=0,"",IFERROR(G21/G$4,"")) | I21: =IF(IFERROR(G21/E21-1,"")=0,"",IFERROR(+G21/E21-1,"")) | J21: =IF(IFERROR(G21/C21-1,"")=0,"",IFERROR(+G21/C21-1,"")) | K21: =+K22+K29+K37 -> 0 | L21: =IF(IFERROR(K21/K$4,"")=0,"",IFERROR(K21/K$4,"")) | M21: =+M22+M29+M37 -> 0 | N21: =IF(IFERROR(M21/M$4,"")=0,"",IFERROR(M21/M$4,"")) | O21: =+O22+O29+O37 -> 0 | P21: =IF(IFERROR(O21/O$4,"")=0,"",IFERROR(O21/O$4,"")) | Q21: =IF(IFERROR(O21/M21-1,"")=0,"",IFERROR(+O21/M21-1,"")) | R21: =IF(IFERROR(O21/K21-1,"")=0,"",IFERROR(+O21/K21-1,"")) | S21: =+S22+S29+S37 -> 0 | T21: =IF(IFERROR(S21/S$4,"")=0,"",IFERROR(S21/S$4,"")) | U21: =+U22+U29+U37 -> 0 | V21: =IF(IFERROR(U21/U$4,"")=0,"",IFERROR(U21/U$4,"")) | W21: =+W22+W29+W37 -> 456.13882 | X21: =IF(IFERROR(W21/W$4,"")=0,"",IFERROR(W21/W$4,"")) -> 0.07692184 | Y21: =IF(IFERROR(W21/U21-1,"")=0,"",IFERROR(+W21/U21-1,"")) | Z21: =IF(IFERROR(W21/S21-1,"")=0,"",IFERROR(+W21/S21-1,"")) | AA21: =+AA22+AA29+AA37 -> 0 | AB21: =IF(IFERROR(AA21/AA$4,"")=0,"",IFERROR(AA21/AA$4,"")) | AC21: =+AC22+AC29+AC37 -> 0 | AD21: =IF(IFERROR(AC21/AC$4,"")=0,"",IFERROR(AC21/AC$4,"")) | AE21: =+AE22+AE29+AE37 -> 236.08315 | AF21: =IF(IFERROR(AE21/AE$4,"")=0,"",IFERROR(AE21/AE$4,"")) -> 0.017215759 | AG21: =IF(IFERROR(AE21/AC21-1,"")=0,"",IFERROR(+AE21/AC21-1,"")) | AH21: =IF(IFERROR(AE21/AA21-1,"")=0,"",IFERROR(+AE21/AA21-1,"")) | AI21: =+AI22+AI29+AI37 -> 0 | AJ21: =IF(IFERROR(AI21/AI$4,"")=0,"",IFERROR(AI21/AI$4,"")) | AK21: =+AK22+AK29+AK37 -> 0 | AL21: =IF(IFERROR(AK21/AK$4,"")=0,"",IFERROR(AK21/AK$4,"")) | AM21: =+AM22+AM29+AM37 -> 276.98128 | AN21: =IF(IFERROR(AM21/AM$4,"")=0,"",IFERROR(AM21/AM$4,"")) -> 0.017627984 | AO21: =IF(IFERROR(AM21/AK21-1,"")=0,"",IFERROR(+AM21/AK21-1,"")) | AP21: =IF(IFERROR(AM21/AI21-1,"")=0,"",IFERROR(+AM21/AI21-1,"")) | AQ21: =+AQ22+AQ29+AQ37 -> 0 | AR21: =IF(IFERROR(AQ21/AQ$4,"")=0,"",IFERROR(AQ21/AQ$4,"")) | AS21: =+AS22+AS29+AS37 -> 0 | AT21: =IF(IFERROR(AS21/AS$4,"")=0,"",IFERROR(AS21/AS$4,"")) | AU21: =+AU22+AU29+AU37 -> 150.87233 | AV21: =IF(IFERROR(AU21/AU$4,"")=0,"",IFERROR(AU21/AU$4,"")) -> 0.010585043 | AW21: =IF(IFERROR(AU21/AS21-1,"")=0,"",IFERROR(+AU21/AS21-1,"")) | AX21: =IF(IFERROR(AU21/AQ21-1,"")=0,"",IFERROR(+AU21/AQ21-1,"")) | AY21: =+AY22+AY29+AY37 -> 0 | AZ21: =IF(IFERROR(AY21/AY$4,"")=0,"",IFERROR(AY21/AY$4,"")) | BA21: =+BA22+BA29+BA37 -> 0 | BB21: =IF(IFERROR(BA21/BA$4,"")=0,"",IFERROR(BA21/BA$4,"")) | BC21: =+BC22+BC29+BC37 -> 0 | BD21: =IF(IFERROR(BC21/BC$4,"")=0,"",IFERROR(BC21/BC$4,"")) | BE21: =IF(IFERROR(BC21/BA21-1,"")=0,"",IFERROR(+BC21/BA21-1,"")) | BF21: =IF(IFERROR(BC21/AY21-1,"")=0,"",IFERROR(+BC21/AY21-1,"")) | BG21: =+BG22+BG29+BG37 -> 0 | BH21: =IF(IFERROR(BG21/BG$4,"")=0,"",IFERROR(BG21/BG$4,"")) | BI21: =+BI22+BI29+BI37 -> 0 | BJ21: =IF(IFERROR(BI21/BI$4,"")=0,"",IFERROR(BI21/BI$4,"")) | BK21: =+BK22+BK29+BK37 -> 0 | BL21: =IF(IFERROR(BK21/BK$4,"")=0,"",IFERROR(BK21/BK$4,"")) | BM21: =IF(IFERROR(BK21/BI21-1,"")=0,"",IFERROR(+BK21/BI21-1,"")) | BN21: =IF(IFERROR(BK21/BG21-1,"")=0,"",IFERROR(+BK21/BG21-1,"")) | BO21: =+BO22+BO29+BO37 -> 0 | BP21: =IF(IFERROR(BO21/BO$4,"")=0,"",IFERROR(BO21/BO$4,"")) | BQ21: =+BQ22+BQ29+BQ37 -> 0 | BR21: =IF(IFERROR(BQ21/BQ$4,"")=0,"",IFERROR(BQ21/BQ$4,"")) | BS21: =+BS22+BS29+BS37 -> 0 | BT21: =IF(IFERROR(BS21/BS$4,"")=0,"",IFERROR(BS21/BS$4,"")) | BU21: =IF(IFERROR(BS21/BQ21-1,"")=0,"",IFERROR(+BS21/BQ21-1,"")) | BV21: =IF(IFERROR(BS21/BO21-1,"")=0,"",IFERROR(+BS21/BO21-1,"")) | BW21: =+BW22+BW29+BW37 -> 0 | BX21: =IF(IFERROR(BW21/BW$4,"")=0,"",IFERROR(BW21/BW$4,"")) | BY21: =+BY22+BY29+BY37 -> 0 | BZ21: =IF(IFERROR(BY21/BY$4,"")=0,"",IFERROR(BY21/BY$4,"")) | CA21: =+CA22+CA29+CA37 -> 0 | CB21: =IF(IFERROR(CA21/CA$4,"")=0,"",IFERROR(CA21/CA$4,"")) | CC21: =IF(IFERROR(CA21/BY21-1,"")=0,"",IFERROR(+CA21/BY21-1,"")) | CD21: =IF(IFERROR(CA21/BW21-1,"")=0,"",IFERROR(+CA21/BW21-1,"")) | CE21: =+CE22+CE29+CE37 -> 0 | CF21: =IF(IFERROR(CE21/CE$4,"")=0,"",IFERROR(CE21/CE$4,"")) | CG21: =+CG22+CG29+CG37 -> 0 | CH21: =IF(IFERROR(CG21/CG$4,"")=0,"",IFERROR(CG21/CG$4,"")) | CI21: =+CI22+CI29+CI37 -> 0 | CJ21: =IF(IFERROR(CI21/CI$4,"")=0,"",IFERROR(CI21/CI$4,"")) | CK21: =IF(IFERROR(CI21/CG21-1,"")=0,"",IFERROR(+CI21/CG21-1,"")) | CL21: =IF(IFERROR(CI21/CE21-1,"")=0,"",IFERROR(+CI21/CE21-1,"")) | CM21: =+CM22+CM29+CM37 -> 0 | CN21: =IF(IFERROR(CM21/CM$4,"")=0,"",IFERROR(CM21/CM$4,"")) | CO21: =+CO22+CO29+CO37 -> 0 | CP21: =IF(IFERROR(CO21/CO$4,"")=0,"",IFERROR(CO21/CO$4,"")) | CQ21: =+CQ22+CQ29+CQ37 -> 0 | CR21: =IF(IFERROR(CQ21/CQ$4,"")=0,"",IFERROR(CQ21/CQ$4,"")) | CS21: =IF(IFERROR(CQ21/CO21-1,"")=0,"",IFERROR(+CQ21/CO21-1,"")) | CT21: =IF(IFERROR(CQ21/CM21-1,"")=0,"",IFERROR(+CQ21/CM21-1,"")) | CU21: =SUM(C21,K21,S21,AA21,AI21,AQ21,AY21,BG21,BO21,BW21,CE21,CM21) -> 0 | CV21: =IFERROR(CU21/CU$4,"") | CW21: =SUM(E21,M21,U21,AC21,AK21,AS21,BA21,BI21,BQ21,BY21,CG21,CO21) -> 0 | CX21: =IFERROR(CW21/CW$4,"") -> 0 | CY21: =SUM(G21,O21,W21,AE21,AM21,AU21,BC21,BK21,BS21,CA21,CI21,CQ21) -> 1120.0756 | CZ21: =IFERROR(CY21/CY$4,"") -> 0.022578053 | DA21: =IF(IFERROR(CY21/CW21-1,"")=0,"",IFERROR(+CY21/CW21-1,"")) | DB21: =IF(IFERROR(CY21/CU21-1,"")=0,"",IFERROR(+CY21/CU21-1,""))
B22: =+Расходы!A248 -> Производственные издержки Бар | C22: =SUM(C23:C28) -> 0 | D22: =IF(IFERROR(C22/C$4,"")=0,"",IFERROR(C22/C$4,"")) | E22: =SUM(E23:E28) -> 0 | F22: =IF(IFERROR(E22/E$4,"")=0,"",IFERROR(E22/E$4,"")) | G22: =+Расходы!B248/1000 -> 0 | H22: =IF(IFERROR(G22/G$4,"")=0,"",IFERROR(G22/G$4,"")) | I22: =IF(IFERROR(G22/E22-1,"")=0,"",IFERROR(+G22/E22-1,"")) | J22: =IF(IFERROR(G22/C22-1,"")=0,"",IFERROR(+G22/C22-1,"")) | K22: =SUM(K23:K28) -> 0 | L22: =IF(IFERROR(K22/K$4,"")=0,"",IFERROR(K22/K$4,"")) | M22: =SUM(M23:M28) -> 0 | N22: =IF(IFERROR(M22/M$4,"")=0,"",IFERROR(M22/M$4,"")) | O22: =+Расходы!C248/1000 -> 0 | P22: =IF(IFERROR(O22/O$4,"")=0,"",IFERROR(O22/O$4,"")) | Q22: =IF(IFERROR(O22/M22-1,"")=0,"",IFERROR(+O22/M22-1,"")) | R22: =IF(IFERROR(O22/K22-1,"")=0,"",IFERROR(+O22/K22-1,"")) | S22: =SUM(S23:S28) -> 0 | T22: =IF(IFERROR(S22/S$4,"")=0,"",IFERROR(S22/S$4,"")) | U22: =SUM(U23:U28) -> 0 | V22: =IF(IFERROR(U22/U$4,"")=0,"",IFERROR(U22/U$4,"")) | W22: =+Расходы!D248/1000 -> 10.66721 | X22: =IF(IFERROR(W22/W$4,"")=0,"",IFERROR(W22/W$4,"")) -> 0.0017988853 | Y22: =IF(IFERROR(W22/U22-1,"")=0,"",IFERROR(+W22/U22-1,"")) | Z22: =IF(IFERROR(W22/S22-1,"")=0,"",IFERROR(+W22/S22-1,"")) | AA22: =SUM(AA23:AA28) -> 0 | AB22: =IF(IFERROR(AA22/AA$4,"")=0,"",IFERROR(AA22/AA$4,"")) | AC22: =SUM(AC23:AC28) -> 0 | AD22: =IF(IFERROR(AC22/AC$4,"")=0,"",IFERROR(AC22/AC$4,"")) | AE22: =+Расходы!E248/1000 -> -0.91894 | AF22: =IF(IFERROR(AE22/AE$4,"")=0,"",IFERROR(AE22/AE$4,"")) -> -6.7011347e-05 | AG22: =IF(IFERROR(AE22/AC22-1,"")=0,"",IFERROR(+AE22/AC22-1,"")) | AH22: =IF(IFERROR(AE22/AA22-1,"")=0,"",IFERROR(+AE22/AA22-1,"")) | AI22: =SUM(AI23:AI28) -> 0 | AJ22: =IF(IFERROR(AI22/AI$4,"")=0,"",IFERROR(AI22/AI$4,"")) | AK22: =SUM(AK23:AK28) -> 0 | AL22: =IF(IFERROR(AK22/AK$4,"")=0,"",IFERROR(AK22/AK$4,"")) | AM22: =+Расходы!F248/1000 -> 8.71188 | AN22: =IF(IFERROR(AM22/AM$4,"")=0,"",IFERROR(AM22/AM$4,"")) -> 0.00055445219 | AO22: =IF(IFERROR(AM22/AK22-1,"")=0,"",IFERROR(+AM22/AK22-1,"")) | AP22: =IF(IFERROR(AM22/AI22-1,"")=0,"",IFERROR(+AM22/AI22-1,"")) | AQ22: =SUM(AQ23:AQ28) -> 0 | AR22: =IF(IFERROR(AQ22/AQ$4,"")=0,"",IFERROR(AQ22/AQ$4,"")) | AS22: =SUM(AS23:AS28) -> 0 | AT22: =IF(IFERROR(AS22/AS$4,"")=0,"",IFERROR(AS22/AS$4,"")) | AU22: =+Расходы!G248/1000 -> -0.2251 | AV22: =IF(IFERROR(AU22/AU$4,"")=0,"",IFERROR(AU22/AU$4,"")) -> -1.5792777e-05 | AW22: =IF(IFERROR(AU22/AS22-1,"")=0,"",IFERROR(+AU22/AS22-1,"")) | AX22: =IF(IFERROR(AU22/AQ22-1,"")=0,"",IFERROR(+AU22/AQ22-1,"")) | AY22: =SUM(AY23:AY28) -> 0 | AZ22: =IF(IFERROR(AY22/AY$4,"")=0,"",IFERROR(AY22/AY$4,"")) | BA22: =SUM(BA23:BA28) -> 0 | BB22: =IF(IFERROR(BA22/BA$4,"")=0,"",IFERROR(BA22/BA$4,"")) | BC22: =+Расходы!H248/1000 -> 0 | BD22: =IF(IFERROR(BC22/BC$4,"")=0,"",IFERROR(BC22/BC$4,"")) | BE22: =IF(IFERROR(BC22/BA22-1,"")=0,"",IFERROR(+BC22/BA22-1,"")) | BF22: =IF(IFERROR(BC22/AY22-1,"")=0,"",IFERROR(+BC22/AY22-1,"")) | BG22: =SUM(BG23:BG28) -> 0 | BH22: =IF(IFERROR(BG22/BG$4,"")=0,"",IFERROR(BG22/BG$4,"")) | BI22: =SUM(BI23:BI28) -> 0 | BJ22: =IF(IFERROR(BI22/BI$4,"")=0,"",IFERROR(BI22/BI$4,"")) | BK22: =+Расходы!I248/1000 -> 0 | BL22: =IF(IFERROR(BK22/BK$4,"")=0,"",IFERROR(BK22/BK$4,"")) | BM22: =IF(IFERROR(BK22/BI22-1,"")=0,"",IFERROR(+BK22/BI22-1,"")) | BN22: =IF(IFERROR(BK22/BG22-1,"")=0,"",IFERROR(+BK22/BG22-1,"")) | BO22: =SUM(BO23:BO28) -> 0 | BP22: =IF(IFERROR(BO22/BO$4,"")=0,"",IFERROR(BO22/BO$4,"")) | BQ22: =SUM(BQ23:BQ28) -> 0 | BR22: =IF(IFERROR(BQ22/BQ$4,"")=0,"",IFERROR(BQ22/BQ$4,"")) | BS22: =+Расходы!J248/1000 -> 0 | BT22: =IF(IFERROR(BS22/BS$4,"")=0,"",IFERROR(BS22/BS$4,"")) | BU22: =IF(IFERROR(BS22/BQ22-1,"")=0,"",IFERROR(+BS22/BQ22-1,"")) | BV22: =IF(IFERROR(BS22/BO22-1,"")=0,"",IFERROR(+BS22/BO22-1,"")) | BW22: =SUM(BW23:BW28) -> 0 | BX22: =IF(IFERROR(BW22/BW$4,"")=0,"",IFERROR(BW22/BW$4,"")) | BY22: =SUM(BY23:BY28) -> 0 | BZ22: =IF(IFERROR(BY22/BY$4,"")=0,"",IFERROR(BY22/BY$4,"")) | CA22: =+Расходы!K248/1000 -> 0 | CB22: =IF(IFERROR(CA22/CA$4,"")=0,"",IFERROR(CA22/CA$4,"")) | CC22: =IF(IFERROR(CA22/BY22-1,"")=0,"",IFERROR(+CA22/BY22-1,"")) | CD22: =IF(IFERROR(CA22/BW22-1,"")=0,"",IFERROR(+CA22/BW22-1,"")) | CE22: =SUM(CE23:CE28) -> 0 | CF22: =IF(IFERROR(CE22/CE$4,"")=0,"",IFERROR(CE22/CE$4,"")) | CG22: =SUM(CG23:CG28) -> 0 | CH22: =IF(IFERROR(CG22/CG$4,"")=0,"",IFERROR(CG22/CG$4,"")) | CI22: =+Расходы!L248/1000 -> 0 | CJ22: =IF(IFERROR(CI22/CI$4,"")=0,"",IFERROR(CI22/CI$4,"")) | CK22: =IF(IFERROR(CI22/CG22-1,"")=0,"",IFERROR(+CI22/CG22-1,"")) | CL22: =IF(IFERROR(CI22/CE22-1,"")=0,"",IFERROR(+CI22/CE22-1,"")) | CM22: =SUM(CM23:CM28) -> 0 | CN22: =IF(IFERROR(CM22/CM$4,"")=0,"",IFERROR(CM22/CM$4,"")) | CO22: =SUM(CO23:CO28) -> 0 | CP22: =IF(IFERROR(CO22/CO$4,"")=0,"",IFERROR(CO22/CO$4,"")) | CQ22: =+Расходы!M248/1000 -> 0 | CR22: =IF(IFERROR(CQ22/CQ$4,"")=0,"",IFERROR(CQ22/CQ$4,"")) | CS22: =IF(IFERROR(CQ22/CO22-1,"")=0,"",IFERROR(+CQ22/CO22-1,"")) | CT22: =IF(IFERROR(CQ22/CM22-1,"")=0,"",IFERROR(+CQ22/CM22-1,"")) | CU22: =SUM(C22,K22,S22,AA22,AI22,AQ22,AY22,BG22,BO22,BW22,CE22,CM22) -> 0 | CV22: =IFERROR(CU22/CU$4,"") | CW22: =SUM(E22,M22,U22,AC22,AK22,AS22,BA22,BI22,BQ22,BY22,CG22,CO22) -> 0 | CX22: =IFERROR(CW22/CW$4,"") -> 0 | CY22: =SUM(G22,O22,W22,AE22,AM22,AU22,BC22,BK22,BS22,CA22,CI22,CQ22) -> 18.23505 | CZ22: =IFERROR(CY22/CY$4,"") -> 0.00036757514 | DA22: =IF(IFERROR(CY22/CW22-1,"")=0,"",IFERROR(+CY22/CW22-1,"")) | DB22: =IF(IFERROR(CY22/CU22-1,"")=0,"",IFERROR(+CY22/CU22-1,""))
B23: =+Расходы!A249 -> Бракераж бар | D23: =IF(IFERROR(C23/C$4,"")=0,"",IFERROR(C23/C$4,"")) | F23: =IF(IFERROR(E23/E$4,"")=0,"",IFERROR(E23/E$4,"")) | G23: =+Расходы!B249/1000 -> 0 | H23: =IF(IFERROR(G23/G$4,"")=0,"",IFERROR(G23/G$4,"")) | I23: =IF(IFERROR(G23/E23-1,"")=0,"",IFERROR(+G23/E23-1,"")) | J23: =IF(IFERROR(G23/C23-1,"")=0,"",IFERROR(+G23/C23-1,"")) | L23: =IF(IFERROR(K23/K$4,"")=0,"",IFERROR(K23/K$4,"")) | N23: =IF(IFERROR(M23/M$4,"")=0,"",IFERROR(M23/M$4,"")) | O23: =+Расходы!C249/1000 -> 0 | P23: =IF(IFERROR(O23/O$4,"")=0,"",IFERROR(O23/O$4,"")) | Q23: =IF(IFERROR(O23/M23-1,"")=0,"",IFERROR(+O23/M23-1,"")) | R23: =IF(IFERROR(O23/K23-1,"")=0,"",IFERROR(+O23/K23-1,"")) | T23: =IF(IFERROR(S23/S$4,"")=0,"",IFERROR(S23/S$4,"")) | U23: 0 | V23: =IF(IFERROR(U23/U$4,"")=0,"",IFERROR(U23/U$4,"")) | W23: =+Расходы!D249/1000 -> 0 | X23: =IF(IFERROR(W23/W$4,"")=0,"",IFERROR(W23/W$4,"")) | Y23: =IF(IFERROR(W23/U23-1,"")=0,"",IFERROR(+W23/U23-1,"")) | Z23: =IF(IFERROR(W23/S23-1,"")=0,"",IFERROR(+W23/S23-1,"")) | AB23: =IF(IFERROR(AA23/AA$4,"")=0,"",IFERROR(AA23/AA$4,"")) | AC23: 0 | AD23: =IF(IFERROR(AC23/AC$4,"")=0,"",IFERROR(AC23/AC$4,"")) | AE23: =+Расходы!E249/1000 -> 0 | AF23: =IF(IFERROR(AE23/AE$4,"")=0,"",IFERROR(AE23/AE$4,"")) | AG23: =IF(IFERROR(AE23/AC23-1,"")=0,"",IFERROR(+AE23/AC23-1,"")) | AH23: =IF(IFERROR(AE23/AA23-1,"")=0,"",IFERROR(+AE23/AA23-1,"")) | AJ23: =IF(IFERROR(AI23/AI$4,"")=0,"",IFERROR(AI23/AI$4,"")) | AK23: 0 | AL23: =IF(IFERROR(AK23/AK$4,"")=0,"",IFERROR(AK23/AK$4,"")) | AM23: =+Расходы!F249/1000 -> 0 | AN23: =IF(IFERROR(AM23/AM$4,"")=0,"",IFERROR(AM23/AM$4,"")) | AO23: =IF(IFERROR(AM23/AK23-1,"")=0,"",IFERROR(+AM23/AK23-1,"")) | AP23: =IF(IFERROR(AM23/AI23-1,"")=0,"",IFERROR(+AM23/AI23-1,"")) | AR23: =IF(IFERROR(AQ23/AQ$4,"")=0,"",IFERROR(AQ23/AQ$4,"")) | AS23: 0 | AT23: =IF(IFERROR(AS23/AS$4,"")=0,"",IFERROR(AS23/AS$4,"")) | AU23: =+Расходы!G249/1000 -> 0 | AV23: =IF(IFERROR(AU23/AU$4,"")=0,"",IFERROR(AU23/AU$4,"")) | AW23: =IF(IFERROR(AU23/AS23-1,"")=0,"",IFERROR(+AU23/AS23-1,"")) | AX23: =IF(IFERROR(AU23/AQ23-1,"")=0,"",IFERROR(+AU23/AQ23-1,"")) | AZ23: =IF(IFERROR(AY23/AY$4,"")=0,"",IFERROR(AY23/AY$4,"")) | BA23: 0 | BB23: =IF(IFERROR(BA23/BA$4,"")=0,"",IFERROR(BA23/BA$4,"")) | BC23: =+Расходы!H249/1000 -> 0 | BD23: =IF(IFERROR(BC23/BC$4,"")=0,"",IFERROR(BC23/BC$4,"")) | BE23: =IF(IFERROR(BC23/BA23-1,"")=0,"",IFERROR(+BC23/BA23-1,"")) | BF23: =IF(IFERROR(BC23/AY23-1,"")=0,"",IFERROR(+BC23/AY23-1,"")) | BH23: =IF(IFERROR(BG23/BG$4,"")=0,"",IFERROR(BG23/BG$4,"")) | BI23: 0 | BJ23: =IF(IFERROR(BI23/BI$4,"")=0,"",IFERROR(BI23/BI$4,"")) | BK23: =+Расходы!I249/1000 -> 0 | BL23: =IF(IFERROR(BK23/BK$4,"")=0,"",IFERROR(BK23/BK$4,"")) | BM23: =IF(IFERROR(BK23/BI23-1,"")=0,"",IFERROR(+BK23/BI23-1,"")) | BN23: =IF(IFERROR(BK23/BG23-1,"")=0,"",IFERROR(+BK23/BG23-1,"")) | BP23: =IF(IFERROR(BO23/BO$4,"")=0,"",IFERROR(BO23/BO$4,"")) | BQ23: 0 | BR23: =IF(IFERROR(BQ23/BQ$4,"")=0,"",IFERROR(BQ23/BQ$4,"")) | BS23: =+Расходы!J249/1000 -> 0 | BT23: =IF(IFERROR(BS23/BS$4,"")=0,"",IFERROR(BS23/BS$4,"")) | BU23: =IF(IFERROR(BS23/BQ23-1,"")=0,"",IFERROR(+BS23/BQ23-1,"")) | BV23: =IF(IFERROR(BS23/BO23-1,"")=0,"",IFERROR(+BS23/BO23-1,"")) | BX23: =IF(IFERROR(BW23/BW$4,"")=0,"",IFERROR(BW23/BW$4,"")) | BY23: 0 | BZ23: =IF(IFERROR(BY23/BY$4,"")=0,"",IFERROR(BY23/BY$4,"")) | CA23: =+Расходы!K249/1000 -> 0 | CB23: =IF(IFERROR(CA23/CA$4,"")=0,"",IFERROR(CA23/CA$4,"")) | CC23: =IF(IFERROR(CA23/BY23-1,"")=0,"",IFERROR(+CA23/BY23-1,"")) | CD23: =IF(IFERROR(CA23/BW23-1,"")=0,"",IFERROR(+CA23/BW23-1,"")) | CF23: =IF(IFERROR(CE23/CE$4,"")=0,"",IFERROR(CE23/CE$4,"")) | CG23: 0 | CH23: =IF(IFERROR(CG23/CG$4,"")=0,"",IFERROR(CG23/CG$4,"")) | CI23: =+Расходы!L249/1000 -> 0 | CJ23: =IF(IFERROR(CI23/CI$4,"")=0,"",IFERROR(CI23/CI$4,"")) | CK23: =IF(IFERROR(CI23/CG23-1,"")=0,"",IFERROR(+CI23/CG23-1,"")) | CL23: =IF(IFERROR(CI23/CE23-1,"")=0,"",IFERROR(+CI23/CE23-1,"")) | CN23: =IF(IFERROR(CM23/CM$4,"")=0,"",IFERROR(CM23/CM$4,"")) | CO23: 0 | CP23: =IF(IFERROR(CO23/CO$4,"")=0,"",IFERROR(CO23/CO$4,"")) | CQ23: =+Расходы!M249/1000 -> 0 | CR23: =IF(IFERROR(CQ23/CQ$4,"")=0,"",IFERROR(CQ23/CQ$4,"")) | CS23: =IF(IFERROR(CQ23/CO23-1,"")=0,"",IFERROR(+CQ23/CO23-1,"")) | CT23: =IF(IFERROR(CQ23/CM23-1,"")=0,"",IFERROR(+CQ23/CM23-1,"")) | CU23: =SUM(C23,K23,S23,AA23,AI23,AQ23,AY23,BG23,BO23,BW23,CE23,CM23) -> 0 | CV23: =IFERROR(CU23/CU$4,"") | CW23: =SUM(E23,M23,U23,AC23,AK23,AS23,BA23,BI23,BQ23,BY23,CG23,CO23) -> 0 | CX23: =IFERROR(CW23/CW$4,"") -> 0 | CY23: =SUM(G23,O23,W23,AE23,AM23,AU23,BC23,BK23,BS23,CA23,CI23,CQ23) -> 0 | CZ23: =IFERROR(CY23/CY$4,"") -> 0 | DA23: =IF(IFERROR(CY23/CW23-1,"")=0,"",IFERROR(+CY23/CW23-1,"")) | DB23: =IF(IFERROR(CY23/CU23-1,"")=0,"",IFERROR(+CY23/CU23-1,""))
B24: =+Расходы!A250 -> Дегустация бар | D24: =IF(IFERROR(C24/C$4,"")=0,"",IFERROR(C24/C$4,"")) | F24: =IF(IFERROR(E24/E$4,"")=0,"",IFERROR(E24/E$4,"")) | G24: =+Расходы!B250/1000 -> 0 | H24: =IF(IFERROR(G24/G$4,"")=0,"",IFERROR(G24/G$4,"")) | I24: =IF(IFERROR(G24/E24-1,"")=0,"",IFERROR(+G24/E24-1,"")) | J24: =IF(IFERROR(G24/C24-1,"")=0,"",IFERROR(+G24/C24-1,"")) | L24: =IF(IFERROR(K24/K$4,"")=0,"",IFERROR(K24/K$4,"")) | N24: =IF(IFERROR(M24/M$4,"")=0,"",IFERROR(M24/M$4,"")) | O24: =+Расходы!C250/1000 -> 0 | P24: =IF(IFERROR(O24/O$4,"")=0,"",IFERROR(O24/O$4,"")) | Q24: =IF(IFERROR(O24/M24-1,"")=0,"",IFERROR(+O24/M24-1,"")) | R24: =IF(IFERROR(O24/K24-1,"")=0,"",IFERROR(+O24/K24-1,"")) | T24: =IF(IFERROR(S24/S$4,"")=0,"",IFERROR(S24/S$4,"")) | U24: 0 | V24: =IF(IFERROR(U24/U$4,"")=0,"",IFERROR(U24/U$4,"")) | W24: =+Расходы!D250/1000 -> 0 | X24: =IF(IFERROR(W24/W$4,"")=0,"",IFERROR(W24/W$4,"")) | Y24: =IF(IFERROR(W24/U24-1,"")=0,"",IFERROR(+W24/U24-1,"")) | Z24: =IF(IFERROR(W24/S24-1,"")=0,"",IFERROR(+W24/S24-1,"")) | AB24: =IF(IFERROR(AA24/AA$4,"")=0,"",IFERROR(AA24/AA$4,"")) | AC24: 0 | AD24: =IF(IFERROR(AC24/AC$4,"")=0,"",IFERROR(AC24/AC$4,"")) | AE24: =+Расходы!E250/1000 -> 0 | AF24: =IF(IFERROR(AE24/AE$4,"")=0,"",IFERROR(AE24/AE$4,"")) | AG24: =IF(IFERROR(AE24/AC24-1,"")=0,"",IFERROR(+AE24/AC24-1,"")) | AH24: =IF(IFERROR(AE24/AA24-1,"")=0,"",IFERROR(+AE24/AA24-1,"")) | AJ24: =IF(IFERROR(AI24/AI$4,"")=0,"",IFERROR(AI24/AI$4,"")) | AK24: 0 | AL24: =IF(IFERROR(AK24/AK$4,"")=0,"",IFERROR(AK24/AK$4,"")) | AM24: =+Расходы!F250/1000 -> 0 | AN24: =IF(IFERROR(AM24/AM$4,"")=0,"",IFERROR(AM24/AM$4,"")) | AO24: =IF(IFERROR(AM24/AK24-1,"")=0,"",IFERROR(+AM24/AK24-1,"")) | AP24: =IF(IFERROR(AM24/AI24-1,"")=0,"",IFERROR(+AM24/AI24-1,"")) | AR24: =IF(IFERROR(AQ24/AQ$4,"")=0,"",IFERROR(AQ24/AQ$4,"")) | AS24: 0 | AT24: =IF(IFERROR(AS24/AS$4,"")=0,"",IFERROR(AS24/AS$4,"")) | AU24: =+Расходы!G250/1000 -> 0 | AV24: =IF(IFERROR(AU24/AU$4,"")=0,"",IFERROR(AU24/AU$4,"")) | AW24: =IF(IFERROR(AU24/AS24-1,"")=0,"",IFERROR(+AU24/AS24-1,"")) | AX24: =IF(IFERROR(AU24/AQ24-1,"")=0,"",IFERROR(+AU24/AQ24-1,"")) | AZ24: =IF(IFERROR(AY24/AY$4,"")=0,"",IFERROR(AY24/AY$4,"")) | BA24: 0 | BB24: =IF(IFERROR(BA24/BA$4,"")=0,"",IFERROR(BA24/BA$4,"")) | BC24: =+Расходы!H250/1000 -> 0 | BD24: =IF(IFERROR(BC24/BC$4,"")=0,"",IFERROR(BC24/BC$4,"")) | BE24: =IF(IFERROR(BC24/BA24-1,"")=0,"",IFERROR(+BC24/BA24-1,"")) | BF24: =IF(IFERROR(BC24/AY24-1,"")=0,"",IFERROR(+BC24/AY24-1,"")) | BH24: =IF(IFERROR(BG24/BG$4,"")=0,"",IFERROR(BG24/BG$4,"")) | BI24: 0 | BJ24: =IF(IFERROR(BI24/BI$4,"")=0,"",IFERROR(BI24/BI$4,"")) | BK24: =+Расходы!I250/1000 -> 0 | BL24: =IF(IFERROR(BK24/BK$4,"")=0,"",IFERROR(BK24/BK$4,"")) | BM24: =IF(IFERROR(BK24/BI24-1,"")=0,"",IFERROR(+BK24/BI24-1,"")) | BN24: =IF(IFERROR(BK24/BG24-1,"")=0,"",IFERROR(+BK24/BG24-1,"")) | BP24: =IF(IFERROR(BO24/BO$4,"")=0,"",IFERROR(BO24/BO$4,"")) | BQ24: 0 | BR24: =IF(IFERROR(BQ24/BQ$4,"")=0,"",IFERROR(BQ24/BQ$4,"")) | BS24: =+Расходы!J250/1000 -> 0 | BT24: =IF(IFERROR(BS24/BS$4,"")=0,"",IFERROR(BS24/BS$4,"")) | BU24: =IF(IFERROR(BS24/BQ24-1,"")=0,"",IFERROR(+BS24/BQ24-1,"")) | BV24: =IF(IFERROR(BS24/BO24-1,"")=0,"",IFERROR(+BS24/BO24-1,"")) | BX24: =IF(IFERROR(BW24/BW$4,"")=0,"",IFERROR(BW24/BW$4,"")) | BY24: 0 | BZ24: =IF(IFERROR(BY24/BY$4,"")=0,"",IFERROR(BY24/BY$4,"")) | CA24: =+Расходы!K250/1000 -> 0 | CB24: =IF(IFERROR(CA24/CA$4,"")=0,"",IFERROR(CA24/CA$4,"")) | CC24: =IF(IFERROR(CA24/BY24-1,"")=0,"",IFERROR(+CA24/BY24-1,"")) | CD24: =IF(IFERROR(CA24/BW24-1,"")=0,"",IFERROR(+CA24/BW24-1,"")) | CF24: =IF(IFERROR(CE24/CE$4,"")=0,"",IFERROR(CE24/CE$4,"")) | CG24: 0 | CH24: =IF(IFERROR(CG24/CG$4,"")=0,"",IFERROR(CG24/CG$4,"")) | CI24: =+Расходы!L250/1000 -> 0 | CJ24: =IF(IFERROR(CI24/CI$4,"")=0,"",IFERROR(CI24/CI$4,"")) | CK24: =IF(IFERROR(CI24/CG24-1,"")=0,"",IFERROR(+CI24/CG24-1,"")) | CL24: =IF(IFERROR(CI24/CE24-1,"")=0,"",IFERROR(+CI24/CE24-1,"")) | CN24: =IF(IFERROR(CM24/CM$4,"")=0,"",IFERROR(CM24/CM$4,"")) | CO24: 0 | CP24: =IF(IFERROR(CO24/CO$4,"")=0,"",IFERROR(CO24/CO$4,"")) | CQ24: =+Расходы!M250/1000 -> 0 | CR24: =IF(IFERROR(CQ24/CQ$4,"")=0,"",IFERROR(CQ24/CQ$4,"")) | CS24: =IF(IFERROR(CQ24/CO24-1,"")=0,"",IFERROR(+CQ24/CO24-1,"")) | CT24: =IF(IFERROR(CQ24/CM24-1,"")=0,"",IFERROR(+CQ24/CM24-1,"")) | CU24: =SUM(C24,K24,S24,AA24,AI24,AQ24,AY24,BG24,BO24,BW24,CE24,CM24) -> 0 | CV24: =IFERROR(CU24/CU$4,"") | CW24: =SUM(E24,M24,U24,AC24,AK24,AS24,BA24,BI24,BQ24,BY24,CG24,CO24) -> 0 | CX24: =IFERROR(CW24/CW$4,"") -> 0 | CY24: =SUM(G24,O24,W24,AE24,AM24,AU24,BC24,BK24,BS24,CA24,CI24,CQ24) -> 0 | CZ24: =IFERROR(CY24/CY$4,"") -> 0 | DA24: =IF(IFERROR(CY24/CW24-1,"")=0,"",IFERROR(+CY24/CW24-1,"")) | DB24: =IF(IFERROR(CY24/CU24-1,"")=0,"",IFERROR(+CY24/CU24-1,""))
B25: =+Расходы!A251 -> Излишки бар | D25: =IF(IFERROR(C25/C$4,"")=0,"",IFERROR(C25/C$4,"")) | F25: =IF(IFERROR(E25/E$4,"")=0,"",IFERROR(E25/E$4,"")) | G25: =+Расходы!B251/1000 -> 0 | H25: =IF(IFERROR(G25/G$4,"")=0,"",IFERROR(G25/G$4,"")) | I25: =IF(IFERROR(G25/E25-1,"")=0,"",IFERROR(+G25/E25-1,"")) | J25: =IF(IFERROR(G25/C25-1,"")=0,"",IFERROR(+G25/C25-1,"")) | L25: =IF(IFERROR(K25/K$4,"")=0,"",IFERROR(K25/K$4,"")) | N25: =IF(IFERROR(M25/M$4,"")=0,"",IFERROR(M25/M$4,"")) | O25: =+Расходы!C251/1000 -> 0 | P25: =IF(IFERROR(O25/O$4,"")=0,"",IFERROR(O25/O$4,"")) | Q25: =IF(IFERROR(O25/M25-1,"")=0,"",IFERROR(+O25/M25-1,"")) | R25: =IF(IFERROR(O25/K25-1,"")=0,"",IFERROR(+O25/K25-1,"")) | T25: =IF(IFERROR(S25/S$4,"")=0,"",IFERROR(S25/S$4,"")) | U25: 0 | V25: =IF(IFERROR(U25/U$4,"")=0,"",IFERROR(U25/U$4,"")) | W25: =+Расходы!D251/1000 -> -7.59609 | X25: =IF(IFERROR(W25/W$4,"")=0,"",IFERROR(W25/W$4,"")) -> -0.0012809811 | Y25: =IF(IFERROR(W25/U25-1,"")=0,"",IFERROR(+W25/U25-1,"")) | Z25: =IF(IFERROR(W25/S25-1,"")=0,"",IFERROR(+W25/S25-1,"")) | AB25: =IF(IFERROR(AA25/AA$4,"")=0,"",IFERROR(AA25/AA$4,"")) | AC25: 0 | AD25: =IF(IFERROR(AC25/AC$4,"")=0,"",IFERROR(AC25/AC$4,"")) | AE25: =+Расходы!E251/1000 -> -27.43001 | AF25: =IF(IFERROR(AE25/AE$4,"")=0,"",IFERROR(AE25/AE$4,"")) -> -0.0020002633 | AG25: =IF(IFERROR(AE25/AC25-1,"")=0,"",IFERROR(+AE25/AC25-1,"")) | AH25: =IF(IFERROR(AE25/AA25-1,"")=0,"",IFERROR(+AE25/AA25-1,"")) | AJ25: =IF(IFERROR(AI25/AI$4,"")=0,"",IFERROR(AI25/AI$4,"")) | AK25: 0 | AL25: =IF(IFERROR(AK25/AK$4,"")=0,"",IFERROR(AK25/AK$4,"")) | AM25: =+Расходы!F251/1000 -> -22.15716 | AN25: =IF(IFERROR(AM25/AM$4,"")=0,"",IFERROR(AM25/AM$4,"")) -> -0.0014101533 | AO25: =IF(IFERROR(AM25/AK25-1,"")=0,"",IFERROR(+AM25/AK25-1,"")) | AP25: =IF(IFERROR(AM25/AI25-1,"")=0,"",IFERROR(+AM25/AI25-1,"")) | AR25: =IF(IFERROR(AQ25/AQ$4,"")=0,"",IFERROR(AQ25/AQ$4,"")) | AS25: 0 | AT25: =IF(IFERROR(AS25/AS$4,"")=0,"",IFERROR(AS25/AS$4,"")) | AU25: =+Расходы!G251/1000 -> -25.11308 | AV25: =IF(IFERROR(AU25/AU$4,"")=0,"",IFERROR(AU25/AU$4,"")) -> -0.0017619071 | AW25: =IF(IFERROR(AU25/AS25-1,"")=0,"",IFERROR(+AU25/AS25-1,"")) | AX25: =IF(IFERROR(AU25/AQ25-1,"")=0,"",IFERROR(+AU25/AQ25-1,"")) | AZ25: =IF(IFERROR(AY25/AY$4,"")=0,"",IFERROR(AY25/AY$4,"")) | BA25: 0 | BB25: =IF(IFERROR(BA25/BA$4,"")=0,"",IFERROR(BA25/BA$4,"")) | BC25: =+Расходы!H251/1000 -> 0 | BD25: =IF(IFERROR(BC25/BC$4,"")=0,"",IFERROR(BC25/BC$4,"")) | BE25: =IF(IFERROR(BC25/BA25-1,"")=0,"",IFERROR(+BC25/BA25-1,"")) | BF25: =IF(IFERROR(BC25/AY25-1,"")=0,"",IFERROR(+BC25/AY25-1,"")) | BH25: =IF(IFERROR(BG25/BG$4,"")=0,"",IFERROR(BG25/BG$4,"")) | BI25: 0 | BJ25: =IF(IFERROR(BI25/BI$4,"")=0,"",IFERROR(BI25/BI$4,"")) | BK25: =+Расходы!I251/1000 -> 0 | BL25: =IF(IFERROR(BK25/BK$4,"")=0,"",IFERROR(BK25/BK$4,"")) | BM25: =IF(IFERROR(BK25/BI25-1,"")=0,"",IFERROR(+BK25/BI25-1,"")) | BN25: =IF(IFERROR(BK25/BG25-1,"")=0,"",IFERROR(+BK25/BG25-1,"")) | BP25: =IF(IFERROR(BO25/BO$4,"")=0,"",IFERROR(BO25/BO$4,"")) | BQ25: 0 | BR25: =IF(IFERROR(BQ25/BQ$4,"")=0,"",IFERROR(BQ25/BQ$4,"")) | BS25: =+Расходы!J251/1000 -> 0 | BT25: =IF(IFERROR(BS25/BS$4,"")=0,"",IFERROR(BS25/BS$4,"")) | BU25: =IF(IFERROR(BS25/BQ25-1,"")=0,"",IFERROR(+BS25/BQ25-1,"")) | BV25: =IF(IFERROR(BS25/BO25-1,"")=0,"",IFERROR(+BS25/BO25-1,"")) | BX25: =IF(IFERROR(BW25/BW$4,"")=0,"",IFERROR(BW25/BW$4,"")) | BY25: 0 | BZ25: =IF(IFERROR(BY25/BY$4,"")=0,"",IFERROR(BY25/BY$4,"")) | CA25: =+Расходы!K251/1000 -> 0 | CB25: =IF(IFERROR(CA25/CA$4,"")=0,"",IFERROR(CA25/CA$4,"")) | CC25: =IF(IFERROR(CA25/BY25-1,"")=0,"",IFERROR(+CA25/BY25-1,"")) | CD25: =IF(IFERROR(CA25/BW25-1,"")=0,"",IFERROR(+CA25/BW25-1,"")) | CF25: =IF(IFERROR(CE25/CE$4,"")=0,"",IFERROR(CE25/CE$4,"")) | CG25: 0 | CH25: =IF(IFERROR(CG25/CG$4,"")=0,"",IFERROR(CG25/CG$4,"")) | CI25: =+Расходы!L251/1000 -> 0 | CJ25: =IF(IFERROR(CI25/CI$4,"")=0,"",IFERROR(CI25/CI$4,"")) | CK25: =IF(IFERROR(CI25/CG25-1,"")=0,"",IFERROR(+CI25/CG25-1,"")) | CL25: =IF(IFERROR(CI25/CE25-1,"")=0,"",IFERROR(+CI25/CE25-1,"")) | CN25: =IF(IFERROR(CM25/CM$4,"")=0,"",IFERROR(CM25/CM$4,"")) | CO25: 0 | CP25: =IF(IFERROR(CO25/CO$4,"")=0,"",IFERROR(CO25/CO$4,"")) | CQ25: =+Расходы!M251/1000 -> 0 | CR25: =IF(IFERROR(CQ25/CQ$4,"")=0,"",IFERROR(CQ25/CQ$4,"")) | CS25: =IF(IFERROR(CQ25/CO25-1,"")=0,"",IFERROR(+CQ25/CO25-1,"")) | CT25: =IF(IFERROR(CQ25/CM25-1,"")=0,"",IFERROR(+CQ25/CM25-1,"")) | CU25: =SUM(C25,K25,S25,AA25,AI25,AQ25,AY25,BG25,BO25,BW25,CE25,CM25) -> 0 | CV25: =IFERROR(CU25/CU$4,"") | CW25: =SUM(E25,M25,U25,AC25,AK25,AS25,BA25,BI25,BQ25,BY25,CG25,CO25) -> 0 | CX25: =IFERROR(CW25/CW$4,"") -> 0 | CY25: =SUM(G25,O25,W25,AE25,AM25,AU25,BC25,BK25,BS25,CA25,CI25,CQ25) -> -82.29634 | CZ25: =IFERROR(CY25/CY$4,"") -> -0.001658898 | DA25: =IF(IFERROR(CY25/CW25-1,"")=0,"",IFERROR(+CY25/CW25-1,"")) | DB25: =IF(IFERROR(CY25/CU25-1,"")=0,"",IFERROR(+CY25/CU25-1,""))
B26: =+Расходы!A252 -> Недостача бар | D26: =IF(IFERROR(C26/C$4,"")=0,"",IFERROR(C26/C$4,"")) | F26: =IF(IFERROR(E26/E$4,"")=0,"",IFERROR(E26/E$4,"")) | G26: =+Расходы!B252/1000 -> 0 | H26: =IF(IFERROR(G26/G$4,"")=0,"",IFERROR(G26/G$4,"")) | I26: =IF(IFERROR(G26/E26-1,"")=0,"",IFERROR(+G26/E26-1,"")) | J26: =IF(IFERROR(G26/C26-1,"")=0,"",IFERROR(+G26/C26-1,"")) | L26: =IF(IFERROR(K26/K$4,"")=0,"",IFERROR(K26/K$4,"")) | N26: =IF(IFERROR(M26/M$4,"")=0,"",IFERROR(M26/M$4,"")) | O26: =+Расходы!C252/1000 -> 0 | P26: =IF(IFERROR(O26/O$4,"")=0,"",IFERROR(O26/O$4,"")) | Q26: =IF(IFERROR(O26/M26-1,"")=0,"",IFERROR(+O26/M26-1,"")) | R26: =IF(IFERROR(O26/K26-1,"")=0,"",IFERROR(+O26/K26-1,"")) | T26: =IF(IFERROR(S26/S$4,"")=0,"",IFERROR(S26/S$4,"")) | U26: 0 | V26: =IF(IFERROR(U26/U$4,"")=0,"",IFERROR(U26/U$4,"")) | W26: =+Расходы!E252/1000 -> 12.82304 | X26: =IF(IFERROR(W26/W$4,"")=0,"",IFERROR(W26/W$4,"")) -> 0.0021624378 | Y26: =IF(IFERROR(W26/U26-1,"")=0,"",IFERROR(+W26/U26-1,"")) | Z26: =IF(IFERROR(W26/S26-1,"")=0,"",IFERROR(+W26/S26-1,"")) | AB26: =IF(IFERROR(AA26/AA$4,"")=0,"",IFERROR(AA26/AA$4,"")) | AC26: 0 | AD26: =IF(IFERROR(AC26/AC$4,"")=0,"",IFERROR(AC26/AC$4,"")) | AE26: =+Расходы!E252/1000 -> 12.82304 | AF26: =IF(IFERROR(AE26/AE$4,"")=0,"",IFERROR(AE26/AE$4,"")) -> 0.00093508736 | AG26: =IF(IFERROR(AE26/AC26-1,"")=0,"",IFERROR(+AE26/AC26-1,"")) | AH26: =IF(IFERROR(AE26/AA26-1,"")=0,"",IFERROR(+AE26/AA26-1,"")) | AJ26: =IF(IFERROR(AI26/AI$4,"")=0,"",IFERROR(AI26/AI$4,"")) | AK26: 0 | AL26: =IF(IFERROR(AK26/AK$4,"")=0,"",IFERROR(AK26/AK$4,"")) | AM26: =+Расходы!F252/1000 -> 6.41477 | AN26: =IF(IFERROR(AM26/AM$4,"")=0,"",IFERROR(AM26/AM$4,"")) -> 0.00040825669 | AO26: =IF(IFERROR(AM26/AK26-1,"")=0,"",IFERROR(+AM26/AK26-1,"")) | AP26: =IF(IFERROR(AM26/AI26-1,"")=0,"",IFERROR(+AM26/AI26-1,"")) | AR26: =IF(IFERROR(AQ26/AQ$4,"")=0,"",IFERROR(AQ26/AQ$4,"")) | AS26: 0 | AT26: =IF(IFERROR(AS26/AS$4,"")=0,"",IFERROR(AS26/AS$4,"")) | AU26: =+Расходы!G252/1000 -> 6.28339 | AV26: =IF(IFERROR(AU26/AU$4,"")=0,"",IFERROR(AU26/AU$4,"")) -> 0.00044083598 | AW26: =IF(IFERROR(AU26/AS26-1,"")=0,"",IFERROR(+AU26/AS26-1,"")) | AX26: =IF(IFERROR(AU26/AQ26-1,"")=0,"",IFERROR(+AU26/AQ26-1,"")) | AZ26: =IF(IFERROR(AY26/AY$4,"")=0,"",IFERROR(AY26/AY$4,"")) | BA26: 0 | BB26: =IF(IFERROR(BA26/BA$4,"")=0,"",IFERROR(BA26/BA$4,"")) | BC26: =+Расходы!H252/1000 -> 0 | BD26: =IF(IFERROR(BC26/BC$4,"")=0,"",IFERROR(BC26/BC$4,"")) | BE26: =IF(IFERROR(BC26/BA26-1,"")=0,"",IFERROR(+BC26/BA26-1,"")) | BF26: =IF(IFERROR(BC26/AY26-1,"")=0,"",IFERROR(+BC26/AY26-1,"")) | BH26: =IF(IFERROR(BG26/BG$4,"")=0,"",IFERROR(BG26/BG$4,"")) | BI26: 0 | BJ26: =IF(IFERROR(BI26/BI$4,"")=0,"",IFERROR(BI26/BI$4,"")) | BK26: =+Расходы!I252/1000 -> 0 | BL26: =IF(IFERROR(BK26/BK$4,"")=0,"",IFERROR(BK26/BK$4,"")) | BM26: =IF(IFERROR(BK26/BI26-1,"")=0,"",IFERROR(+BK26/BI26-1,"")) | BN26: =IF(IFERROR(BK26/BG26-1,"")=0,"",IFERROR(+BK26/BG26-1,"")) | BP26: =IF(IFERROR(BO26/BO$4,"")=0,"",IFERROR(BO26/BO$4,"")) | BQ26: 0 | BR26: =IF(IFERROR(BQ26/BQ$4,"")=0,"",IFERROR(BQ26/BQ$4,"")) | BS26: =+Расходы!J252/1000 -> 0 | BT26: =IF(IFERROR(BS26/BS$4,"")=0,"",IFERROR(BS26/BS$4,"")) | BU26: =IF(IFERROR(BS26/BQ26-1,"")=0,"",IFERROR(+BS26/BQ26-1,"")) | BV26: =IF(IFERROR(BS26/BO26-1,"")=0,"",IFERROR(+BS26/BO26-1,"")) | BX26: =IF(IFERROR(BW26/BW$4,"")=0,"",IFERROR(BW26/BW$4,"")) | BY26: 0 | BZ26: =IF(IFERROR(BY26/BY$4,"")=0,"",IFERROR(BY26/BY$4,"")) | CA26: =+Расходы!K252/1000 -> 0 | CB26: =IF(IFERROR(CA26/CA$4,"")=0,"",IFERROR(CA26/CA$4,"")) | CC26: =IF(IFERROR(CA26/BY26-1,"")=0,"",IFERROR(+CA26/BY26-1,"")) | CD26: =IF(IFERROR(CA26/BW26-1,"")=0,"",IFERROR(+CA26/BW26-1,"")) | CF26: =IF(IFERROR(CE26/CE$4,"")=0,"",IFERROR(CE26/CE$4,"")) | CG26: 0 | CH26: =IF(IFERROR(CG26/CG$4,"")=0,"",IFERROR(CG26/CG$4,"")) | CI26: =+Расходы!L252/1000 -> 0 | CJ26: =IF(IFERROR(CI26/CI$4,"")=0,"",IFERROR(CI26/CI$4,"")) | CK26: =IF(IFERROR(CI26/CG26-1,"")=0,"",IFERROR(+CI26/CG26-1,"")) | CL26: =IF(IFERROR(CI26/CE26-1,"")=0,"",IFERROR(+CI26/CE26-1,"")) | CN26: =IF(IFERROR(CM26/CM$4,"")=0,"",IFERROR(CM26/CM$4,"")) | CO26: 0 | CP26: =IF(IFERROR(CO26/CO$4,"")=0,"",IFERROR(CO26/CO$4,"")) | CQ26: =+Расходы!M252/1000 -> 0 | CR26: =IF(IFERROR(CQ26/CQ$4,"")=0,"",IFERROR(CQ26/CQ$4,"")) | CS26: =IF(IFERROR(CQ26/CO26-1,"")=0,"",IFERROR(+CQ26/CO26-1,"")) | CT26: =IF(IFERROR(CQ26/CM26-1,"")=0,"",IFERROR(+CQ26/CM26-1,"")) | CU26: =SUM(C26,K26,S26,AA26,AI26,AQ26,AY26,BG26,BO26,BW26,CE26,CM26) -> 0 | CV26: =IFERROR(CU26/CU$4,"") | CW26: =SUM(E26,M26,U26,AC26,AK26,AS26,BA26,BI26,BQ26,BY26,CG26,CO26) -> 0 | CX26: =IFERROR(CW26/CW$4,"") -> 0 | CY26: =SUM(G26,O26,W26,AE26,AM26,AU26,BC26,BK26,BS26,CA26,CI26,CQ26) -> 38.34424 | CZ26: =IFERROR(CY26/CY$4,"") -> 0.00077292847 | DA26: =IF(IFERROR(CY26/CW26-1,"")=0,"",IFERROR(+CY26/CW26-1,"")) | DB26: =IF(IFERROR(CY26/CU26-1,"")=0,"",IFERROR(+CY26/CU26-1,""))
B27: =+Расходы!A253 -> Проработка бар | D27: =IF(IFERROR(C27/C$4,"")=0,"",IFERROR(C27/C$4,"")) | F27: =IF(IFERROR(E27/E$4,"")=0,"",IFERROR(E27/E$4,"")) | G27: =+Расходы!B253/1000 -> 0 | H27: =IF(IFERROR(G27/G$4,"")=0,"",IFERROR(G27/G$4,"")) | I27: =IF(IFERROR(G27/E27-1,"")=0,"",IFERROR(+G27/E27-1,"")) | J27: =IF(IFERROR(G27/C27-1,"")=0,"",IFERROR(+G27/C27-1,"")) | L27: =IF(IFERROR(K27/K$4,"")=0,"",IFERROR(K27/K$4,"")) | N27: =IF(IFERROR(M27/M$4,"")=0,"",IFERROR(M27/M$4,"")) | O27: =+Расходы!C253/1000 -> 0 | P27: =IF(IFERROR(O27/O$4,"")=0,"",IFERROR(O27/O$4,"")) | Q27: =IF(IFERROR(O27/M27-1,"")=0,"",IFERROR(+O27/M27-1,"")) | R27: =IF(IFERROR(O27/K27-1,"")=0,"",IFERROR(+O27/K27-1,"")) | T27: =IF(IFERROR(S27/S$4,"")=0,"",IFERROR(S27/S$4,"")) | U27: 0 | V27: =IF(IFERROR(U27/U$4,"")=0,"",IFERROR(U27/U$4,"")) | W27: =+Расходы!E253/1000 -> 0.60105 | X27: =IF(IFERROR(W27/W$4,"")=0,"",IFERROR(W27/W$4,"")) -> 0.00010135921 | Y27: =IF(IFERROR(W27/U27-1,"")=0,"",IFERROR(+W27/U27-1,"")) | Z27: =IF(IFERROR(W27/S27-1,"")=0,"",IFERROR(+W27/S27-1,"")) | AB27: =IF(IFERROR(AA27/AA$4,"")=0,"",IFERROR(AA27/AA$4,"")) | AC27: 0 | AD27: =IF(IFERROR(AC27/AC$4,"")=0,"",IFERROR(AC27/AC$4,"")) | AE27: =+Расходы!E253/1000 -> 0.60105 | AF27: =IF(IFERROR(AE27/AE$4,"")=0,"",IFERROR(AE27/AE$4,"")) -> 4.3830032e-05 | AG27: =IF(IFERROR(AE27/AC27-1,"")=0,"",IFERROR(+AE27/AC27-1,"")) | AH27: =IF(IFERROR(AE27/AA27-1,"")=0,"",IFERROR(+AE27/AA27-1,"")) | AJ27: =IF(IFERROR(AI27/AI$4,"")=0,"",IFERROR(AI27/AI$4,"")) | AK27: 0 | AL27: =IF(IFERROR(AK27/AK$4,"")=0,"",IFERROR(AK27/AK$4,"")) | AM27: =+Расходы!F253/1000 -> 2.15407 | AN27: =IF(IFERROR(AM27/AM$4,"")=0,"",IFERROR(AM27/AM$4,"")) -> 0.00013709198 | AO27: =IF(IFERROR(AM27/AK27-1,"")=0,"",IFERROR(+AM27/AK27-1,"")) | AP27: =IF(IFERROR(AM27/AI27-1,"")=0,"",IFERROR(+AM27/AI27-1,"")) | AR27: =IF(IFERROR(AQ27/AQ$4,"")=0,"",IFERROR(AQ27/AQ$4,"")) | AS27: 0 | AT27: =IF(IFERROR(AS27/AS$4,"")=0,"",IFERROR(AS27/AS$4,"")) | AU27: =+Расходы!G253/1000 -> 1.41002 | AV27: =IF(IFERROR(AU27/AU$4,"")=0,"",IFERROR(AU27/AU$4,"")) -> 9.8925509e-05 | AW27: =IF(IFERROR(AU27/AS27-1,"")=0,"",IFERROR(+AU27/AS27-1,"")) | AX27: =IF(IFERROR(AU27/AQ27-1,"")=0,"",IFERROR(+AU27/AQ27-1,"")) | AZ27: =IF(IFERROR(AY27/AY$4,"")=0,"",IFERROR(AY27/AY$4,"")) | BA27: 0 | BB27: =IF(IFERROR(BA27/BA$4,"")=0,"",IFERROR(BA27/BA$4,"")) | BC27: =+Расходы!H253/1000 -> 0 | BD27: =IF(IFERROR(BC27/BC$4,"")=0,"",IFERROR(BC27/BC$4,"")) | BE27: =IF(IFERROR(BC27/BA27-1,"")=0,"",IFERROR(+BC27/BA27-1,"")) | BF27: =IF(IFERROR(BC27/AY27-1,"")=0,"",IFERROR(+BC27/AY27-1,"")) | BH27: =IF(IFERROR(BG27/BG$4,"")=0,"",IFERROR(BG27/BG$4,"")) | BI27: 0 | BJ27: =IF(IFERROR(BI27/BI$4,"")=0,"",IFERROR(BI27/BI$4,"")) | BK27: =+Расходы!I253/1000 -> 0 | BL27: =IF(IFERROR(BK27/BK$4,"")=0,"",IFERROR(BK27/BK$4,"")) | BM27: =IF(IFERROR(BK27/BI27-1,"")=0,"",IFERROR(+BK27/BI27-1,"")) | BN27: =IF(IFERROR(BK27/BG27-1,"")=0,"",IFERROR(+BK27/BG27-1,"")) | BP27: =IF(IFERROR(BO27/BO$4,"")=0,"",IFERROR(BO27/BO$4,"")) | BQ27: 0 | BR27: =IF(IFERROR(BQ27/BQ$4,"")=0,"",IFERROR(BQ27/BQ$4,"")) | BS27: =+Расходы!J253/1000 -> 0 | BT27: =IF(IFERROR(BS27/BS$4,"")=0,"",IFERROR(BS27/BS$4,"")) | BU27: =IF(IFERROR(BS27/BQ27-1,"")=0,"",IFERROR(+BS27/BQ27-1,"")) | BV27: =IF(IFERROR(BS27/BO27-1,"")=0,"",IFERROR(+BS27/BO27-1,"")) | BX27: =IF(IFERROR(BW27/BW$4,"")=0,"",IFERROR(BW27/BW$4,"")) | BY27: 0 | BZ27: =IF(IFERROR(BY27/BY$4,"")=0,"",IFERROR(BY27/BY$4,"")) | CA27: =+Расходы!K253/1000 -> 0 | CB27: =IF(IFERROR(CA27/CA$4,"")=0,"",IFERROR(CA27/CA$4,"")) | CC27: =IF(IFERROR(CA27/BY27-1,"")=0,"",IFERROR(+CA27/BY27-1,"")) | CD27: =IF(IFERROR(CA27/BW27-1,"")=0,"",IFERROR(+CA27/BW27-1,"")) | CF27: =IF(IFERROR(CE27/CE$4,"")=0,"",IFERROR(CE27/CE$4,"")) | CG27: 0 | CH27: =IF(IFERROR(CG27/CG$4,"")=0,"",IFERROR(CG27/CG$4,"")) | CI27: =+Расходы!L253/1000 -> 0 | CJ27: =IF(IFERROR(CI27/CI$4,"")=0,"",IFERROR(CI27/CI$4,"")) | CK27: =IF(IFERROR(CI27/CG27-1,"")=0,"",IFERROR(+CI27/CG27-1,"")) | CL27: =IF(IFERROR(CI27/CE27-1,"")=0,"",IFERROR(+CI27/CE27-1,"")) | CN27: =IF(IFERROR(CM27/CM$4,"")=0,"",IFERROR(CM27/CM$4,"")) | CO27: 0 | CP27: =IF(IFERROR(CO27/CO$4,"")=0,"",IFERROR(CO27/CO$4,"")) | CQ27: =+Расходы!M253/1000 -> 0 | CR27: =IF(IFERROR(CQ27/CQ$4,"")=0,"",IFERROR(CQ27/CQ$4,"")) | CS27: =IF(IFERROR(CQ27/CO27-1,"")=0,"",IFERROR(+CQ27/CO27-1,"")) | CT27: =IF(IFERROR(CQ27/CM27-1,"")=0,"",IFERROR(+CQ27/CM27-1,"")) | CU27: =SUM(C27,K27,S27,AA27,AI27,AQ27,AY27,BG27,BO27,BW27,CE27,CM27) -> 0 | CV27: =IFERROR(CU27/CU$4,"") | CW27: =SUM(E27,M27,U27,AC27,AK27,AS27,BA27,BI27,BQ27,BY27,CG27,CO27) -> 0 | CX27: =IFERROR(CW27/CW$4,"") -> 0 | CY27: =SUM(G27,O27,W27,AE27,AM27,AU27,BC27,BK27,BS27,CA27,CI27,CQ27) -> 4.76619 | CZ27: =IFERROR(CY27/CY$4,"") -> 9.6075028e-05 | DA27: =IF(IFERROR(CY27/CW27-1,"")=0,"",IFERROR(+CY27/CW27-1,"")) | DB27: =IF(IFERROR(CY27/CU27-1,"")=0,"",IFERROR(+CY27/CU27-1,""))
B28: =+Расходы!A254 -> Списание продуктов бар | D28: =IF(IFERROR(C28/C$4,"")=0,"",IFERROR(C28/C$4,"")) | F28: =IF(IFERROR(E28/E$4,"")=0,"",IFERROR(E28/E$4,"")) | G28: =+Расходы!B254/1000 -> 0 | H28: =IF(IFERROR(G28/G$4,"")=0,"",IFERROR(G28/G$4,"")) | I28: =IF(IFERROR(G28/E28-1,"")=0,"",IFERROR(+G28/E28-1,"")) | J28: =IF(IFERROR(G28/C28-1,"")=0,"",IFERROR(+G28/C28-1,"")) | L28: =IF(IFERROR(K28/K$4,"")=0,"",IFERROR(K28/K$4,"")) | N28: =IF(IFERROR(M28/M$4,"")=0,"",IFERROR(M28/M$4,"")) | O28: =+Расходы!C254/1000 -> 0 | P28: =IF(IFERROR(O28/O$4,"")=0,"",IFERROR(O28/O$4,"")) | Q28: =IF(IFERROR(O28/M28-1,"")=0,"",IFERROR(+O28/M28-1,"")) | R28: =IF(IFERROR(O28/K28-1,"")=0,"",IFERROR(+O28/K28-1,"")) | T28: =IF(IFERROR(S28/S$4,"")=0,"",IFERROR(S28/S$4,"")) | U28: 0 | V28: =IF(IFERROR(U28/U$4,"")=0,"",IFERROR(U28/U$4,"")) | W28: =+Расходы!E254/1000 -> 13.08698 | X28: =IF(IFERROR(W28/W$4,"")=0,"",IFERROR(W28/W$4,"")) -> 0.0022069478 | Y28: =IF(IFERROR(W28/U28-1,"")=0,"",IFERROR(+W28/U28-1,"")) | Z28: =IF(IFERROR(W28/S28-1,"")=0,"",IFERROR(+W28/S28-1,"")) | AB28: =IF(IFERROR(AA28/AA$4,"")=0,"",IFERROR(AA28/AA$4,"")) | AC28: 0 | AD28: =IF(IFERROR(AC28/AC$4,"")=0,"",IFERROR(AC28/AC$4,"")) | AE28: =+Расходы!E254/1000 -> 13.08698 | AF28: =IF(IFERROR(AE28/AE$4,"")=0,"",IFERROR(AE28/AE$4,"")) -> 0.00095433451 | AG28: =IF(IFERROR(AE28/AC28-1,"")=0,"",IFERROR(+AE28/AC28-1,"")) | AH28: =IF(IFERROR(AE28/AA28-1,"")=0,"",IFERROR(+AE28/AA28-1,"")) | AJ28: =IF(IFERROR(AI28/AI$4,"")=0,"",IFERROR(AI28/AI$4,"")) | AK28: 0 | AL28: =IF(IFERROR(AK28/AK$4,"")=0,"",IFERROR(AK28/AK$4,"")) | AM28: =+Расходы!F254/1000 -> 22.3002 | AN28: =IF(IFERROR(AM28/AM$4,"")=0,"",IFERROR(AM28/AM$4,"")) -> 0.0014192568 | AO28: =IF(IFERROR(AM28/AK28-1,"")=0,"",IFERROR(+AM28/AK28-1,"")) | AP28: =IF(IFERROR(AM28/AI28-1,"")=0,"",IFERROR(+AM28/AI28-1,"")) | AR28: =IF(IFERROR(AQ28/AQ$4,"")=0,"",IFERROR(AQ28/AQ$4,"")) | AS28: 0 | AT28: =IF(IFERROR(AS28/AS$4,"")=0,"",IFERROR(AS28/AS$4,"")) | AU28: =+Расходы!G254/1000 -> 17.19457 | AV28: =IF(IFERROR(AU28/AU$4,"")=0,"",IFERROR(AU28/AU$4,"")) -> 0.0012063528 | AW28: =IF(IFERROR(AU28/AS28-1,"")=0,"",IFERROR(+AU28/AS28-1,"")) | AX28: =IF(IFERROR(AU28/AQ28-1,"")=0,"",IFERROR(+AU28/AQ28-1,"")) | AZ28: =IF(IFERROR(AY28/AY$4,"")=0,"",IFERROR(AY28/AY$4,"")) | BA28: 0 | BB28: =IF(IFERROR(BA28/BA$4,"")=0,"",IFERROR(BA28/BA$4,"")) | BC28: =+Расходы!H254/1000 -> 0 | BD28: =IF(IFERROR(BC28/BC$4,"")=0,"",IFERROR(BC28/BC$4,"")) | BE28: =IF(IFERROR(BC28/BA28-1,"")=0,"",IFERROR(+BC28/BA28-1,"")) | BF28: =IF(IFERROR(BC28/AY28-1,"")=0,"",IFERROR(+BC28/AY28-1,"")) | BH28: =IF(IFERROR(BG28/BG$4,"")=0,"",IFERROR(BG28/BG$4,"")) | BI28: 0 | BJ28: =IF(IFERROR(BI28/BI$4,"")=0,"",IFERROR(BI28/BI$4,"")) | BK28: =+Расходы!I254/1000 -> 0 | BL28: =IF(IFERROR(BK28/BK$4,"")=0,"",IFERROR(BK28/BK$4,"")) | BM28: =IF(IFERROR(BK28/BI28-1,"")=0,"",IFERROR(+BK28/BI28-1,"")) | BN28: =IF(IFERROR(BK28/BG28-1,"")=0,"",IFERROR(+BK28/BG28-1,"")) | BP28: =IF(IFERROR(BO28/BO$4,"")=0,"",IFERROR(BO28/BO$4,"")) | BQ28: 0 | BR28: =IF(IFERROR(BQ28/BQ$4,"")=0,"",IFERROR(BQ28/BQ$4,"")) | BS28: =+Расходы!J254/1000 -> 0 | BT28: =IF(IFERROR(BS28/BS$4,"")=0,"",IFERROR(BS28/BS$4,"")) | BU28: =IF(IFERROR(BS28/BQ28-1,"")=0,"",IFERROR(+BS28/BQ28-1,"")) | BV28: =IF(IFERROR(BS28/BO28-1,"")=0,"",IFERROR(+BS28/BO28-1,"")) | BX28: =IF(IFERROR(BW28/BW$4,"")=0,"",IFERROR(BW28/BW$4,"")) | BY28: 0 | BZ28: =IF(IFERROR(BY28/BY$4,"")=0,"",IFERROR(BY28/BY$4,"")) | CA28: =+Расходы!K254/1000 -> 0 | CB28: =IF(IFERROR(CA28/CA$4,"")=0,"",IFERROR(CA28/CA$4,"")) | CC28: =IF(IFERROR(CA28/BY28-1,"")=0,"",IFERROR(+CA28/BY28-1,"")) | CD28: =IF(IFERROR(CA28/BW28-1,"")=0,"",IFERROR(+CA28/BW28-1,"")) | CF28: =IF(IFERROR(CE28/CE$4,"")=0,"",IFERROR(CE28/CE$4,"")) | CG28: 0 | CH28: =IF(IFERROR(CG28/CG$4,"")=0,"",IFERROR(CG28/CG$4,"")) | CI28: =+Расходы!L254/1000 -> 0 | CJ28: =IF(IFERROR(CI28/CI$4,"")=0,"",IFERROR(CI28/CI$4,"")) | CK28: =IF(IFERROR(CI28/CG28-1,"")=0,"",IFERROR(+CI28/CG28-1,"")) | CL28: =IF(IFERROR(CI28/CE28-1,"")=0,"",IFERROR(+CI28/CE28-1,"")) | CN28: =IF(IFERROR(CM28/CM$4,"")=0,"",IFERROR(CM28/CM$4,"")) | CO28: 0 | CP28: =IF(IFERROR(CO28/CO$4,"")=0,"",IFERROR(CO28/CO$4,"")) | CQ28: =+Расходы!M254/1000 -> 0 | CR28: =IF(IFERROR(CQ28/CQ$4,"")=0,"",IFERROR(CQ28/CQ$4,"")) | CS28: =IF(IFERROR(CQ28/CO28-1,"")=0,"",IFERROR(+CQ28/CO28-1,"")) | CT28: =IF(IFERROR(CQ28/CM28-1,"")=0,"",IFERROR(+CQ28/CM28-1,"")) | CU28: =SUM(C28,K28,S28,AA28,AI28,AQ28,AY28,BG28,BO28,BW28,CE28,CM28) -> 0 | CV28: =IFERROR(CU28/CU$4,"") | CW28: =SUM(E28,M28,U28,AC28,AK28,AS28,BA28,BI28,BQ28,BY28,CG28,CO28) -> 0 | CX28: =IFERROR(CW28/CW$4,"") -> 0 | CY28: =SUM(G28,O28,W28,AE28,AM28,AU28,BC28,BK28,BS28,CA28,CI28,CQ28) -> 65.66873 | CZ28: =IFERROR(CY28/CY$4,"") -> 0.001323725 | DA28: =IF(IFERROR(CY28/CW28-1,"")=0,"",IFERROR(+CY28/CW28-1,"")) | DB28: =IF(IFERROR(CY28/CU28-1,"")=0,"",IFERROR(+CY28/CU28-1,""))
B29: =+Расходы!A255 -> Производственные издержки Кухня | C29: =SUM(C30:C36) -> 0 | D29: =IF(IFERROR(C29/C$4,"")=0,"",IFERROR(C29/C$4,"")) | E29: =SUM(E30:E36) -> 0 | F29: =IF(IFERROR(E29/E$4,"")=0,"",IFERROR(E29/E$4,"")) | G29: =+Расходы!B255/1000 -> 0 | H29: =IF(IFERROR(G29/G$4,"")=0,"",IFERROR(G29/G$4,"")) | I29: =IF(IFERROR(G29/E29-1,"")=0,"",IFERROR(+G29/E29-1,"")) | J29: =IF(IFERROR(G29/C29-1,"")=0,"",IFERROR(+G29/C29-1,"")) | K29: =SUM(K30:K36) -> 0 | L29: =IF(IFERROR(K29/K$4,"")=0,"",IFERROR(K29/K$4,"")) | M29: =SUM(M30:M36) -> 0 | N29: =IF(IFERROR(M29/M$4,"")=0,"",IFERROR(M29/M$4,"")) | O29: =+Расходы!C255/1000 -> 0 | P29: =IF(IFERROR(O29/O$4,"")=0,"",IFERROR(O29/O$4,"")) | Q29: =IF(IFERROR(O29/M29-1,"")=0,"",IFERROR(+O29/M29-1,"")) | R29: =IF(IFERROR(O29/K29-1,"")=0,"",IFERROR(+O29/K29-1,"")) | S29: =SUM(S30:S36) -> 0 | T29: =IF(IFERROR(S29/S$4,"")=0,"",IFERROR(S29/S$4,"")) | U29: =SUM(U30:U36) -> 0 | V29: =IF(IFERROR(U29/U$4,"")=0,"",IFERROR(U29/U$4,"")) | W29: =+Расходы!D255/1000 -> 385.69872 | X29: =IF(IFERROR(W29/W$4,"")=0,"",IFERROR(W29/W$4,"")) -> 0.06504304 | Y29: =IF(IFERROR(W29/U29-1,"")=0,"",IFERROR(+W29/U29-1,"")) | Z29: =IF(IFERROR(W29/S29-1,"")=0,"",IFERROR(+W29/S29-1,"")) | AA29: =SUM(AA30:AA36) -> 0 | AB29: =IF(IFERROR(AA29/AA$4,"")=0,"",IFERROR(AA29/AA$4,"")) | AC29: =SUM(AC30:AC36) -> 0 | AD29: =IF(IFERROR(AC29/AC$4,"")=0,"",IFERROR(AC29/AC$4,"")) | AE29: =+Расходы!E255/1000 -> 182.14985 | AF29: =IF(IFERROR(AE29/AE$4,"")=0,"",IFERROR(AE29/AE$4,"")) -> 0.013282811 | AG29: =IF(IFERROR(AE29/AC29-1,"")=0,"",IFERROR(+AE29/AC29-1,"")) | AH29: =IF(IFERROR(AE29/AA29-1,"")=0,"",IFERROR(+AE29/AA29-1,"")) | AI29: =SUM(AI30:AI36) -> 0 | AJ29: =IF(IFERROR(AI29/AI$4,"")=0,"",IFERROR(AI29/AI$4,"")) | AK29: =SUM(AK30:AK36) -> 0 | AL29: =IF(IFERROR(AK29/AK$4,"")=0,"",IFERROR(AK29/AK$4,"")) | AM29: =+Расходы!F255/1000 -> 140.31102 | AN29: =IF(IFERROR(AM29/AM$4,"")=0,"",IFERROR(AM29/AM$4,"")) -> 0.0089298467 | AO29: =IF(IFERROR(AM29/AK29-1,"")=0,"",IFERROR(+AM29/AK29-1,"")) | AP29: =IF(IFERROR(AM29/AI29-1,"")=0,"",IFERROR(+AM29/AI29-1,"")) | AQ29: =SUM(AQ30:AQ36) -> 0 | AR29: =IF(IFERROR(AQ29/AQ$4,"")=0,"",IFERROR(AQ29/AQ$4,"")) | AS29: =SUM(AS30:AS36) -> 0 | AT29: =IF(IFERROR(AS29/AS$4,"")=0,"",IFERROR(AS29/AS$4,"")) | AU29: =+Расходы!G255/1000 -> 121.57009 | AV29: =IF(IFERROR(AU29/AU$4,"")=0,"",IFERROR(AU29/AU$4,"")) -> 0.0085292287 | AW29: =IF(IFERROR(AU29/AS29-1,"")=0,"",IFERROR(+AU29/AS29-1,"")) | AX29: =IF(IFERROR(AU29/AQ29-1,"")=0,"",IFERROR(+AU29/AQ29-1,"")) | AY29: =SUM(AY30:AY36) -> 0 | AZ29: =IF(IFERROR(AY29/AY$4,"")=0,"",IFERROR(AY29/AY$4,"")) | BA29: =SUM(BA30:BA36) -> 0 | BB29: =IF(IFERROR(BA29/BA$4,"")=0,"",IFERROR(BA29/BA$4,"")) | BC29: =+Расходы!H255/1000 -> 0 | BD29: =IF(IFERROR(BC29/BC$4,"")=0,"",IFERROR(BC29/BC$4,"")) | BE29: =IF(IFERROR(BC29/BA29-1,"")=0,"",IFERROR(+BC29/BA29-1,"")) | BF29: =IF(IFERROR(BC29/AY29-1,"")=0,"",IFERROR(+BC29/AY29-1,"")) | BG29: =SUM(BG30:BG36) -> 0 | BH29: =IF(IFERROR(BG29/BG$4,"")=0,"",IFERROR(BG29/BG$4,"")) | BI29: =SUM(BI30:BI36) -> 0 | BJ29: =IF(IFERROR(BI29/BI$4,"")=0,"",IFERROR(BI29/BI$4,"")) | BK29: =+Расходы!I255/1000 -> 0 | BL29: =IF(IFERROR(BK29/BK$4,"")=0,"",IFERROR(BK29/BK$4,"")) | BM29: =IF(IFERROR(BK29/BI29-1,"")=0,"",IFERROR(+BK29/BI29-1,"")) | BN29: =IF(IFERROR(BK29/BG29-1,"")=0,"",IFERROR(+BK29/BG29-1,"")) | BO29: =SUM(BO30:BO36) -> 0 | BP29: =IF(IFERROR(BO29/BO$4,"")=0,"",IFERROR(BO29/BO$4,"")) | BQ29: =SUM(BQ30:BQ36) -> 0 | BR29: =IF(IFERROR(BQ29/BQ$4,"")=0,"",IFERROR(BQ29/BQ$4,"")) | BS29: =+Расходы!J255/1000 -> 0 | BT29: =IF(IFERROR(BS29/BS$4,"")=0,"",IFERROR(BS29/BS$4,"")) | BU29: =IF(IFERROR(BS29/BQ29-1,"")=0,"",IFERROR(+BS29/BQ29-1,"")) | BV29: =IF(IFERROR(BS29/BO29-1,"")=0,"",IFERROR(+BS29/BO29-1,"")) | BW29: =SUM(BW30:BW36) -> 0 | BX29: =IF(IFERROR(BW29/BW$4,"")=0,"",IFERROR(BW29/BW$4,"")) | BY29: =SUM(BY30:BY36) -> 0 | BZ29: =IF(IFERROR(BY29/BY$4,"")=0,"",IFERROR(BY29/BY$4,"")) | CA29: =+Расходы!K255/1000 -> 0 | CB29: =IF(IFERROR(CA29/CA$4,"")=0,"",IFERROR(CA29/CA$4,"")) | CC29: =IF(IFERROR(CA29/BY29-1,"")=0,"",IFERROR(+CA29/BY29-1,"")) | CD29: =IF(IFERROR(CA29/BW29-1,"")=0,"",IFERROR(+CA29/BW29-1,"")) | CE29: =SUM(CE30:CE36) -> 0 | CF29: =IF(IFERROR(CE29/CE$4,"")=0,"",IFERROR(CE29/CE$4,"")) | CG29: =SUM(CG30:CG36) -> 0 | CH29: =IF(IFERROR(CG29/CG$4,"")=0,"",IFERROR(CG29/CG$4,"")) | CI29: =+Расходы!L255/1000 -> 0 | CJ29: =IF(IFERROR(CI29/CI$4,"")=0,"",IFERROR(CI29/CI$4,"")) | CK29: =IF(IFERROR(CI29/CG29-1,"")=0,"",IFERROR(+CI29/CG29-1,"")) | CL29: =IF(IFERROR(CI29/CE29-1,"")=0,"",IFERROR(+CI29/CE29-1,"")) | CM29: =SUM(CM30:CM36) -> 0 | CN29: =IF(IFERROR(CM29/CM$4,"")=0,"",IFERROR(CM29/CM$4,"")) | CO29: =SUM(CO30:CO36) -> 0 | CP29: =IF(IFERROR(CO29/CO$4,"")=0,"",IFERROR(CO29/CO$4,"")) | CQ29: =+Расходы!M255/1000 -> 0 | CR29: =IF(IFERROR(CQ29/CQ$4,"")=0,"",IFERROR(CQ29/CQ$4,"")) | CS29: =IF(IFERROR(CQ29/CO29-1,"")=0,"",IFERROR(+CQ29/CO29-1,"")) | CT29: =IF(IFERROR(CQ29/CM29-1,"")=0,"",IFERROR(+CQ29/CM29-1,"")) | CU29: =SUM(C29,K29,S29,AA29,AI29,AQ29,AY29,BG29,BO29,BW29,CE29,CM29) -> 0 | CV29: =IFERROR(CU29/CU$4,"") | CW29: =SUM(E29,M29,U29,AC29,AK29,AS29,BA29,BI29,BQ29,BY29,CG29,CO29) -> 0 | CX29: =IFERROR(CW29/CW$4,"") -> 0 | CY29: =SUM(G29,O29,W29,AE29,AM29,AU29,BC29,BK29,BS29,CA29,CI29,CQ29) -> 829.72968 | CZ29: =IFERROR(CY29/CY$4,"") -> 0.016725372 | DA29: =IF(IFERROR(CY29/CW29-1,"")=0,"",IFERROR(+CY29/CW29-1,"")) | DB29: =IF(IFERROR(CY29/CU29-1,"")=0,"",IFERROR(+CY29/CU29-1,""))
B30: =+Расходы!A256 -> Бракераж кухня | D30: =IF(IFERROR(C30/C$4,"")=0,"",IFERROR(C30/C$4,"")) | F30: =IF(IFERROR(E30/E$4,"")=0,"",IFERROR(E30/E$4,"")) | G30: =+Расходы!B256/1000 -> 0 | H30: =IF(IFERROR(G30/G$4,"")=0,"",IFERROR(G30/G$4,"")) | I30: =IF(IFERROR(G30/E30-1,"")=0,"",IFERROR(+G30/E30-1,"")) | J30: =IF(IFERROR(G30/C30-1,"")=0,"",IFERROR(+G30/C30-1,"")) | L30: =IF(IFERROR(K30/K$4,"")=0,"",IFERROR(K30/K$4,"")) | N30: =IF(IFERROR(M30/M$4,"")=0,"",IFERROR(M30/M$4,"")) | O30: =+Расходы!C256/1000 -> 0 | P30: =IF(IFERROR(O30/O$4,"")=0,"",IFERROR(O30/O$4,"")) | Q30: =IF(IFERROR(O30/M30-1,"")=0,"",IFERROR(+O30/M30-1,"")) | R30: =IF(IFERROR(O30/K30-1,"")=0,"",IFERROR(+O30/K30-1,"")) | T30: =IF(IFERROR(S30/S$4,"")=0,"",IFERROR(S30/S$4,"")) | U30: 0 | V30: =IF(IFERROR(U30/U$4,"")=0,"",IFERROR(U30/U$4,"")) | W30: =+Расходы!D256/1000 -> 0 | X30: =IF(IFERROR(W30/W$4,"")=0,"",IFERROR(W30/W$4,"")) | Y30: =IF(IFERROR(W30/U30-1,"")=0,"",IFERROR(+W30/U30-1,"")) | Z30: =IF(IFERROR(W30/S30-1,"")=0,"",IFERROR(+W30/S30-1,"")) | AB30: =IF(IFERROR(AA30/AA$4,"")=0,"",IFERROR(AA30/AA$4,"")) | AC30: 0 | AD30: =IF(IFERROR(AC30/AC$4,"")=0,"",IFERROR(AC30/AC$4,"")) | AE30: =+Расходы!E256/1000 -> 0 | AF30: =IF(IFERROR(AE30/AE$4,"")=0,"",IFERROR(AE30/AE$4,"")) | AG30: =IF(IFERROR(AE30/AC30-1,"")=0,"",IFERROR(+AE30/AC30-1,"")) | AH30: =IF(IFERROR(AE30/AA30-1,"")=0,"",IFERROR(+AE30/AA30-1,"")) | AJ30: =IF(IFERROR(AI30/AI$4,"")=0,"",IFERROR(AI30/AI$4,"")) | AK30: 0 | AL30: =IF(IFERROR(AK30/AK$4,"")=0,"",IFERROR(AK30/AK$4,"")) | AM30: =+Расходы!F256/1000 -> 0 | AN30: =IF(IFERROR(AM30/AM$4,"")=0,"",IFERROR(AM30/AM$4,"")) | AO30: =IF(IFERROR(AM30/AK30-1,"")=0,"",IFERROR(+AM30/AK30-1,"")) | AP30: =IF(IFERROR(AM30/AI30-1,"")=0,"",IFERROR(+AM30/AI30-1,"")) | AR30: =IF(IFERROR(AQ30/AQ$4,"")=0,"",IFERROR(AQ30/AQ$4,"")) | AS30: 0 | AT30: =IF(IFERROR(AS30/AS$4,"")=0,"",IFERROR(AS30/AS$4,"")) | AU30: =+Расходы!G256/1000 -> 0 | AV30: =IF(IFERROR(AU30/AU$4,"")=0,"",IFERROR(AU30/AU$4,"")) | AW30: =IF(IFERROR(AU30/AS30-1,"")=0,"",IFERROR(+AU30/AS30-1,"")) | AX30: =IF(IFERROR(AU30/AQ30-1,"")=0,"",IFERROR(+AU30/AQ30-1,"")) | AZ30: =IF(IFERROR(AY30/AY$4,"")=0,"",IFERROR(AY30/AY$4,"")) | BA30: 0 | BB30: =IF(IFERROR(BA30/BA$4,"")=0,"",IFERROR(BA30/BA$4,"")) | BC30: =+Расходы!H256/1000 -> 0 | BD30: =IF(IFERROR(BC30/BC$4,"")=0,"",IFERROR(BC30/BC$4,"")) | BE30: =IF(IFERROR(BC30/BA30-1,"")=0,"",IFERROR(+BC30/BA30-1,"")) | BF30: =IF(IFERROR(BC30/AY30-1,"")=0,"",IFERROR(+BC30/AY30-1,"")) | BH30: =IF(IFERROR(BG30/BG$4,"")=0,"",IFERROR(BG30/BG$4,"")) | BI30: 0 | BJ30: =IF(IFERROR(BI30/BI$4,"")=0,"",IFERROR(BI30/BI$4,"")) | BK30: =+Расходы!I256/1000 -> 0 | BL30: =IF(IFERROR(BK30/BK$4,"")=0,"",IFERROR(BK30/BK$4,"")) | BM30: =IF(IFERROR(BK30/BI30-1,"")=0,"",IFERROR(+BK30/BI30-1,"")) | BN30: =IF(IFERROR(BK30/BG30-1,"")=0,"",IFERROR(+BK30/BG30-1,"")) | BP30: =IF(IFERROR(BO30/BO$4,"")=0,"",IFERROR(BO30/BO$4,"")) | BQ30: 0 | BR30: =IF(IFERROR(BQ30/BQ$4,"")=0,"",IFERROR(BQ30/BQ$4,"")) | BS30: =+Расходы!J256/1000 -> 0 | BT30: =IF(IFERROR(BS30/BS$4,"")=0,"",IFERROR(BS30/BS$4,"")) | BU30: =IF(IFERROR(BS30/BQ30-1,"")=0,"",IFERROR(+BS30/BQ30-1,"")) | BV30: =IF(IFERROR(BS30/BO30-1,"")=0,"",IFERROR(+BS30/BO30-1,"")) | BX30: =IF(IFERROR(BW30/BW$4,"")=0,"",IFERROR(BW30/BW$4,"")) | BY30: 0 | BZ30: =IF(IFERROR(BY30/BY$4,"")=0,"",IFERROR(BY30/BY$4,"")) | CA30: =+Расходы!K256/1000 -> 0 | CB30: =IF(IFERROR(CA30/CA$4,"")=0,"",IFERROR(CA30/CA$4,"")) | CC30: =IF(IFERROR(CA30/BY30-1,"")=0,"",IFERROR(+CA30/BY30-1,"")) | CD30: =IF(IFERROR(CA30/BW30-1,"")=0,"",IFERROR(+CA30/BW30-1,"")) | CF30: =IF(IFERROR(CE30/CE$4,"")=0,"",IFERROR(CE30/CE$4,"")) | CG30: 0 | CH30: =IF(IFERROR(CG30/CG$4,"")=0,"",IFERROR(CG30/CG$4,"")) | CI30: =+Расходы!L256/1000 -> 0 | CJ30: =IF(IFERROR(CI30/CI$4,"")=0,"",IFERROR(CI30/CI$4,"")) | CK30: =IF(IFERROR(CI30/CG30-1,"")=0,"",IFERROR(+CI30/CG30-1,"")) | CL30: =IF(IFERROR(CI30/CE30-1,"")=0,"",IFERROR(+CI30/CE30-1,"")) | CN30: =IF(IFERROR(CM30/CM$4,"")=0,"",IFERROR(CM30/CM$4,"")) | CO30: 0 | CP30: =IF(IFERROR(CO30/CO$4,"")=0,"",IFERROR(CO30/CO$4,"")) | CQ30: =+Расходы!M256/1000 -> 0 | CR30: =IF(IFERROR(CQ30/CQ$4,"")=0,"",IFERROR(CQ30/CQ$4,"")) | CS30: =IF(IFERROR(CQ30/CO30-1,"")=0,"",IFERROR(+CQ30/CO30-1,"")) | CT30: =IF(IFERROR(CQ30/CM30-1,"")=0,"",IFERROR(+CQ30/CM30-1,"")) | CU30: =SUM(C30,K30,S30,AA30,AI30,AQ30,AY30,BG30,BO30,BW30,CE30,CM30) -> 0 | CV30: =IFERROR(CU30/CU$4,"") | CW30: =SUM(E30,M30,U30,AC30,AK30,AS30,BA30,BI30,BQ30,BY30,CG30,CO30) -> 0 | CX30: =IFERROR(CW30/CW$4,"") -> 0 | CY30: =SUM(G30,O30,W30,AE30,AM30,AU30,BC30,BK30,BS30,CA30,CI30,CQ30) -> 0 | CZ30: =IFERROR(CY30/CY$4,"") -> 0 | DA30: =IF(IFERROR(CY30/CW30-1,"")=0,"",IFERROR(+CY30/CW30-1,"")) | DB30: =IF(IFERROR(CY30/CU30-1,"")=0,"",IFERROR(+CY30/CU30-1,""))
B31: =+Расходы!A257 -> Дегустация кухня | D31: =IF(IFERROR(C31/C$4,"")=0,"",IFERROR(C31/C$4,"")) | F31: =IF(IFERROR(E31/E$4,"")=0,"",IFERROR(E31/E$4,"")) | G31: =+Расходы!B257/1000 -> 0 | H31: =IF(IFERROR(G31/G$4,"")=0,"",IFERROR(G31/G$4,"")) | I31: =IF(IFERROR(G31/E31-1,"")=0,"",IFERROR(+G31/E31-1,"")) | J31: =IF(IFERROR(G31/C31-1,"")=0,"",IFERROR(+G31/C31-1,"")) | L31: =IF(IFERROR(K31/K$4,"")=0,"",IFERROR(K31/K$4,"")) | N31: =IF(IFERROR(M31/M$4,"")=0,"",IFERROR(M31/M$4,"")) | O31: =+Расходы!C257/1000 -> 0 | P31: =IF(IFERROR(O31/O$4,"")=0,"",IFERROR(O31/O$4,"")) | Q31: =IF(IFERROR(O31/M31-1,"")=0,"",IFERROR(+O31/M31-1,"")) | R31: =IF(IFERROR(O31/K31-1,"")=0,"",IFERROR(+O31/K31-1,"")) | T31: =IF(IFERROR(S31/S$4,"")=0,"",IFERROR(S31/S$4,"")) | U31: 0 | V31: =IF(IFERROR(U31/U$4,"")=0,"",IFERROR(U31/U$4,"")) | W31: =+Расходы!D257/1000 -> 0 | X31: =IF(IFERROR(W31/W$4,"")=0,"",IFERROR(W31/W$4,"")) | Y31: =IF(IFERROR(W31/U31-1,"")=0,"",IFERROR(+W31/U31-1,"")) | Z31: =IF(IFERROR(W31/S31-1,"")=0,"",IFERROR(+W31/S31-1,"")) | AB31: =IF(IFERROR(AA31/AA$4,"")=0,"",IFERROR(AA31/AA$4,"")) | AC31: 0 | AD31: =IF(IFERROR(AC31/AC$4,"")=0,"",IFERROR(AC31/AC$4,"")) | AE31: =+Расходы!E257/1000 -> 0 | AF31: =IF(IFERROR(AE31/AE$4,"")=0,"",IFERROR(AE31/AE$4,"")) | AG31: =IF(IFERROR(AE31/AC31-1,"")=0,"",IFERROR(+AE31/AC31-1,"")) | AH31: =IF(IFERROR(AE31/AA31-1,"")=0,"",IFERROR(+AE31/AA31-1,"")) | AJ31: =IF(IFERROR(AI31/AI$4,"")=0,"",IFERROR(AI31/AI$4,"")) | AK31: 0 | AL31: =IF(IFERROR(AK31/AK$4,"")=0,"",IFERROR(AK31/AK$4,"")) | AM31: =+Расходы!F257/1000 -> 0 | AN31: =IF(IFERROR(AM31/AM$4,"")=0,"",IFERROR(AM31/AM$4,"")) | AO31: =IF(IFERROR(AM31/AK31-1,"")=0,"",IFERROR(+AM31/AK31-1,"")) | AP31: =IF(IFERROR(AM31/AI31-1,"")=0,"",IFERROR(+AM31/AI31-1,"")) | AR31: =IF(IFERROR(AQ31/AQ$4,"")=0,"",IFERROR(AQ31/AQ$4,"")) | AS31: 0 | AT31: =IF(IFERROR(AS31/AS$4,"")=0,"",IFERROR(AS31/AS$4,"")) | AU31: =+Расходы!G257/1000 -> 0 | AV31: =IF(IFERROR(AU31/AU$4,"")=0,"",IFERROR(AU31/AU$4,"")) | AW31: =IF(IFERROR(AU31/AS31-1,"")=0,"",IFERROR(+AU31/AS31-1,"")) | AX31: =IF(IFERROR(AU31/AQ31-1,"")=0,"",IFERROR(+AU31/AQ31-1,"")) | AZ31: =IF(IFERROR(AY31/AY$4,"")=0,"",IFERROR(AY31/AY$4,"")) | BA31: 0 | BB31: =IF(IFERROR(BA31/BA$4,"")=0,"",IFERROR(BA31/BA$4,"")) | BC31: =+Расходы!H257/1000 -> 0 | BD31: =IF(IFERROR(BC31/BC$4,"")=0,"",IFERROR(BC31/BC$4,"")) | BE31: =IF(IFERROR(BC31/BA31-1,"")=0,"",IFERROR(+BC31/BA31-1,"")) | BF31: =IF(IFERROR(BC31/AY31-1,"")=0,"",IFERROR(+BC31/AY31-1,"")) | BH31: =IF(IFERROR(BG31/BG$4,"")=0,"",IFERROR(BG31/BG$4,"")) | BI31: 0 | BJ31: =IF(IFERROR(BI31/BI$4,"")=0,"",IFERROR(BI31/BI$4,"")) | BK31: =+Расходы!I257/1000 -> 0 | BL31: =IF(IFERROR(BK31/BK$4,"")=0,"",IFERROR(BK31/BK$4,"")) | BM31: =IF(IFERROR(BK31/BI31-1,"")=0,"",IFERROR(+BK31/BI31-1,"")) | BN31: =IF(IFERROR(BK31/BG31-1,"")=0,"",IFERROR(+BK31/BG31-1,"")) | BP31: =IF(IFERROR(BO31/BO$4,"")=0,"",IFERROR(BO31/BO$4,"")) | BQ31: 0 | BR31: =IF(IFERROR(BQ31/BQ$4,"")=0,"",IFERROR(BQ31/BQ$4,"")) | BS31: =+Расходы!J257/1000 -> 0 | BT31: =IF(IFERROR(BS31/BS$4,"")=0,"",IFERROR(BS31/BS$4,"")) | BU31: =IF(IFERROR(BS31/BQ31-1,"")=0,"",IFERROR(+BS31/BQ31-1,"")) | BV31: =IF(IFERROR(BS31/BO31-1,"")=0,"",IFERROR(+BS31/BO31-1,"")) | BX31: =IF(IFERROR(BW31/BW$4,"")=0,"",IFERROR(BW31/BW$4,"")) | BY31: 0 | BZ31: =IF(IFERROR(BY31/BY$4,"")=0,"",IFERROR(BY31/BY$4,"")) | CA31: =+Расходы!K257/1000 -> 0 | CB31: =IF(IFERROR(CA31/CA$4,"")=0,"",IFERROR(CA31/CA$4,"")) | CC31: =IF(IFERROR(CA31/BY31-1,"")=0,"",IFERROR(+CA31/BY31-1,"")) | CD31: =IF(IFERROR(CA31/BW31-1,"")=0,"",IFERROR(+CA31/BW31-1,"")) | CF31: =IF(IFERROR(CE31/CE$4,"")=0,"",IFERROR(CE31/CE$4,"")) | CG31: 0 | CH31: =IF(IFERROR(CG31/CG$4,"")=0,"",IFERROR(CG31/CG$4,"")) | CI31: =+Расходы!L257/1000 -> 0 | CJ31: =IF(IFERROR(CI31/CI$4,"")=0,"",IFERROR(CI31/CI$4,"")) | CK31: =IF(IFERROR(CI31/CG31-1,"")=0,"",IFERROR(+CI31/CG31-1,"")) | CL31: =IF(IFERROR(CI31/CE31-1,"")=0,"",IFERROR(+CI31/CE31-1,"")) | CN31: =IF(IFERROR(CM31/CM$4,"")=0,"",IFERROR(CM31/CM$4,"")) | CO31: 0 | CP31: =IF(IFERROR(CO31/CO$4,"")=0,"",IFERROR(CO31/CO$4,"")) | CQ31: =+Расходы!M257/1000 -> 0 | CR31: =IF(IFERROR(CQ31/CQ$4,"")=0,"",IFERROR(CQ31/CQ$4,"")) | CS31: =IF(IFERROR(CQ31/CO31-1,"")=0,"",IFERROR(+CQ31/CO31-1,"")) | CT31: =IF(IFERROR(CQ31/CM31-1,"")=0,"",IFERROR(+CQ31/CM31-1,"")) | CU31: =SUM(C31,K31,S31,AA31,AI31,AQ31,AY31,BG31,BO31,BW31,CE31,CM31) -> 0 | CV31: =IFERROR(CU31/CU$4,"") | CW31: =SUM(E31,M31,U31,AC31,AK31,AS31,BA31,BI31,BQ31,BY31,CG31,CO31) -> 0 | CX31: =IFERROR(CW31/CW$4,"") -> 0 | CY31: =SUM(G31,O31,W31,AE31,AM31,AU31,BC31,BK31,BS31,CA31,CI31,CQ31) -> 0 | CZ31: =IFERROR(CY31/CY$4,"") -> 0 | DA31: =IF(IFERROR(CY31/CW31-1,"")=0,"",IFERROR(+CY31/CW31-1,"")) | DB31: =IF(IFERROR(CY31/CU31-1,"")=0,"",IFERROR(+CY31/CU31-1,""))
B32: =+Расходы!A258 -> Излишки кухня | D32: =IF(IFERROR(C32/C$4,"")=0,"",IFERROR(C32/C$4,"")) | F32: =IF(IFERROR(E32/E$4,"")=0,"",IFERROR(E32/E$4,"")) | G32: =+Расходы!B258/1000 -> 0 | H32: =IF(IFERROR(G32/G$4,"")=0,"",IFERROR(G32/G$4,"")) | I32: =IF(IFERROR(G32/E32-1,"")=0,"",IFERROR(+G32/E32-1,"")) | J32: =IF(IFERROR(G32/C32-1,"")=0,"",IFERROR(+G32/C32-1,"")) | L32: =IF(IFERROR(K32/K$4,"")=0,"",IFERROR(K32/K$4,"")) | N32: =IF(IFERROR(M32/M$4,"")=0,"",IFERROR(M32/M$4,"")) | O32: =+Расходы!C258/1000 -> 0 | P32: =IF(IFERROR(O32/O$4,"")=0,"",IFERROR(O32/O$4,"")) | Q32: =IF(IFERROR(O32/M32-1,"")=0,"",IFERROR(+O32/M32-1,"")) | R32: =IF(IFERROR(O32/K32-1,"")=0,"",IFERROR(+O32/K32-1,"")) | T32: =IF(IFERROR(S32/S$4,"")=0,"",IFERROR(S32/S$4,"")) | U32: 0 | V32: =IF(IFERROR(U32/U$4,"")=0,"",IFERROR(U32/U$4,"")) | W32: =+Расходы!D258/1000 -> -27.98817 | X32: =IF(IFERROR(W32/W$4,"")=0,"",IFERROR(W32/W$4,"")) -> -0.0047198384 | Y32: =IF(IFERROR(W32/U32-1,"")=0,"",IFERROR(+W32/U32-1,"")) | Z32: =IF(IFERROR(W32/S32-1,"")=0,"",IFERROR(+W32/S32-1,"")) | AB32: =IF(IFERROR(AA32/AA$4,"")=0,"",IFERROR(AA32/AA$4,"")) | AC32: 0 | AD32: =IF(IFERROR(AC32/AC$4,"")=0,"",IFERROR(AC32/AC$4,"")) | AE32: =+Расходы!E258/1000 -> -95.47284 | AF32: =IF(IFERROR(AE32/AE$4,"")=0,"",IFERROR(AE32/AE$4,"")) -> -0.0069621124 | AG32: =IF(IFERROR(AE32/AC32-1,"")=0,"",IFERROR(+AE32/AC32-1,"")) | AH32: =IF(IFERROR(AE32/AA32-1,"")=0,"",IFERROR(+AE32/AA32-1,"")) | AJ32: =IF(IFERROR(AI32/AI$4,"")=0,"",IFERROR(AI32/AI$4,"")) | AK32: 0 | AL32: =IF(IFERROR(AK32/AK$4,"")=0,"",IFERROR(AK32/AK$4,"")) | AM32: =+Расходы!F258/1000 -> -99.07914 | AN32: =IF(IFERROR(AM32/AM$4,"")=0,"",IFERROR(AM32/AM$4,"")) -> -0.0063057166 | AO32: =IF(IFERROR(AM32/AK32-1,"")=0,"",IFERROR(+AM32/AK32-1,"")) | AP32: =IF(IFERROR(AM32/AI32-1,"")=0,"",IFERROR(+AM32/AI32-1,"")) | AR32: =IF(IFERROR(AQ32/AQ$4,"")=0,"",IFERROR(AQ32/AQ$4,"")) | AS32: 0 | AT32: =IF(IFERROR(AS32/AS$4,"")=0,"",IFERROR(AS32/AS$4,"")) | AU32: =+Расходы!G258/1000 -> -98.99695 | AV32: =IF(IFERROR(AU32/AU$4,"")=0,"",IFERROR(AU32/AU$4,"")) -> -0.0069455211 | AW32: =IF(IFERROR(AU32/AS32-1,"")=0,"",IFERROR(+AU32/AS32-1,"")) | AX32: =IF(IFERROR(AU32/AQ32-1,"")=0,"",IFERROR(+AU32/AQ32-1,"")) | AZ32: =IF(IFERROR(AY32/AY$4,"")=0,"",IFERROR(AY32/AY$4,"")) | BA32: 0 | BB32: =IF(IFERROR(BA32/BA$4,"")=0,"",IFERROR(BA32/BA$4,"")) | BC32: =+Расходы!H258/1000 -> 0 | BD32: =IF(IFERROR(BC32/BC$4,"")=0,"",IFERROR(BC32/BC$4,"")) | BE32: =IF(IFERROR(BC32/BA32-1,"")=0,"",IFERROR(+BC32/BA32-1,"")) | BF32: =IF(IFERROR(BC32/AY32-1,"")=0,"",IFERROR(+BC32/AY32-1,"")) | BH32: =IF(IFERROR(BG32/BG$4,"")=0,"",IFERROR(BG32/BG$4,"")) | BI32: 0 | BJ32: =IF(IFERROR(BI32/BI$4,"")=0,"",IFERROR(BI32/BI$4,"")) | BK32: =+Расходы!I258/1000 -> 0 | BL32: =IF(IFERROR(BK32/BK$4,"")=0,"",IFERROR(BK32/BK$4,"")) | BM32: =IF(IFERROR(BK32/BI32-1,"")=0,"",IFERROR(+BK32/BI32-1,"")) | BN32: =IF(IFERROR(BK32/BG32-1,"")=0,"",IFERROR(+BK32/BG32-1,"")) | BP32: =IF(IFERROR(BO32/BO$4,"")=0,"",IFERROR(BO32/BO$4,"")) | BQ32: 0 | BR32: =IF(IFERROR(BQ32/BQ$4,"")=0,"",IFERROR(BQ32/BQ$4,"")) | BS32: =+Расходы!J258/1000 -> 0 | BT32: =IF(IFERROR(BS32/BS$4,"")=0,"",IFERROR(BS32/BS$4,"")) | BU32: =IF(IFERROR(BS32/BQ32-1,"")=0,"",IFERROR(+BS32/BQ32-1,"")) | BV32: =IF(IFERROR(BS32/BO32-1,"")=0,"",IFERROR(+BS32/BO32-1,"")) | BX32: =IF(IFERROR(BW32/BW$4,"")=0,"",IFERROR(BW32/BW$4,"")) | BY32: 0 | BZ32: =IF(IFERROR(BY32/BY$4,"")=0,"",IFERROR(BY32/BY$4,"")) | CA32: =+Расходы!K258/1000 -> 0 | CB32: =IF(IFERROR(CA32/CA$4,"")=0,"",IFERROR(CA32/CA$4,"")) | CC32: =IF(IFERROR(CA32/BY32-1,"")=0,"",IFERROR(+CA32/BY32-1,"")) | CD32: =IF(IFERROR(CA32/BW32-1,"")=0,"",IFERROR(+CA32/BW32-1,"")) | CF32: =IF(IFERROR(CE32/CE$4,"")=0,"",IFERROR(CE32/CE$4,"")) | CG32: 0 | CH32: =IF(IFERROR(CG32/CG$4,"")=0,"",IFERROR(CG32/CG$4,"")) | CI32: =+Расходы!L258/1000 -> 0 | CJ32: =IF(IFERROR(CI32/CI$4,"")=0,"",IFERROR(CI32/CI$4,"")) | CK32: =IF(IFERROR(CI32/CG32-1,"")=0,"",IFERROR(+CI32/CG32-1,"")) | CL32: =IF(IFERROR(CI32/CE32-1,"")=0,"",IFERROR(+CI32/CE32-1,"")) | CN32: =IF(IFERROR(CM32/CM$4,"")=0,"",IFERROR(CM32/CM$4,"")) | CO32: 0 | CP32: =IF(IFERROR(CO32/CO$4,"")=0,"",IFERROR(CO32/CO$4,"")) | CQ32: =+Расходы!M258/1000 -> 0 | CR32: =IF(IFERROR(CQ32/CQ$4,"")=0,"",IFERROR(CQ32/CQ$4,"")) | CS32: =IF(IFERROR(CQ32/CO32-1,"")=0,"",IFERROR(+CQ32/CO32-1,"")) | CT32: =IF(IFERROR(CQ32/CM32-1,"")=0,"",IFERROR(+CQ32/CM32-1,"")) | CU32: =SUM(C32,K32,S32,AA32,AI32,AQ32,AY32,BG32,BO32,BW32,CE32,CM32) -> 0 | CV32: =IFERROR(CU32/CU$4,"") | CW32: =SUM(E32,M32,U32,AC32,AK32,AS32,BA32,BI32,BQ32,BY32,CG32,CO32) -> 0 | CX32: =IFERROR(CW32/CW$4,"") -> 0 | CY32: =SUM(G32,O32,W32,AE32,AM32,AU32,BC32,BK32,BS32,CA32,CI32,CQ32) -> -321.5371 | CZ32: =IFERROR(CY32/CY$4,"") -> -0.0064814214 | DA32: =IF(IFERROR(CY32/CW32-1,"")=0,"",IFERROR(+CY32/CW32-1,"")) | DB32: =IF(IFERROR(CY32/CU32-1,"")=0,"",IFERROR(+CY32/CU32-1,""))
B33: =+Расходы!A259 -> Недостача кухня | D33: =IF(IFERROR(C33/C$4,"")=0,"",IFERROR(C33/C$4,"")) | F33: =IF(IFERROR(E33/E$4,"")=0,"",IFERROR(E33/E$4,"")) | G33: =+Расходы!B259/1000 -> 0 | H33: =IF(IFERROR(G33/G$4,"")=0,"",IFERROR(G33/G$4,"")) | I33: =IF(IFERROR(G33/E33-1,"")=0,"",IFERROR(+G33/E33-1,"")) | J33: =IF(IFERROR(G33/C33-1,"")=0,"",IFERROR(+G33/C33-1,"")) | L33: =IF(IFERROR(K33/K$4,"")=0,"",IFERROR(K33/K$4,"")) | N33: =IF(IFERROR(M33/M$4,"")=0,"",IFERROR(M33/M$4,"")) | O33: =+Расходы!C259/1000 -> 0 | P33: =IF(IFERROR(O33/O$4,"")=0,"",IFERROR(O33/O$4,"")) | Q33: =IF(IFERROR(O33/M33-1,"")=0,"",IFERROR(+O33/M33-1,"")) | R33: =IF(IFERROR(O33/K33-1,"")=0,"",IFERROR(+O33/K33-1,"")) | T33: =IF(IFERROR(S33/S$4,"")=0,"",IFERROR(S33/S$4,"")) | U33: 0 | V33: =IF(IFERROR(U33/U$4,"")=0,"",IFERROR(U33/U$4,"")) | W33: =+Расходы!E259/1000 -> 170.31923 | X33: =IF(IFERROR(W33/W$4,"")=0,"",IFERROR(W33/W$4,"")) -> 0.028722108 | Y33: =IF(IFERROR(W33/U33-1,"")=0,"",IFERROR(+W33/U33-1,"")) | Z33: =IF(IFERROR(W33/S33-1,"")=0,"",IFERROR(+W33/S33-1,"")) | AB33: =IF(IFERROR(AA33/AA$4,"")=0,"",IFERROR(AA33/AA$4,"")) | AC33: 0 | AD33: =IF(IFERROR(AC33/AC$4,"")=0,"",IFERROR(AC33/AC$4,"")) | AE33: =+Расходы!E259/1000 -> 170.31923 | AF33: =IF(IFERROR(AE33/AE$4,"")=0,"",IFERROR(AE33/AE$4,"")) -> 0.012420094 | AG33: =IF(IFERROR(AE33/AC33-1,"")=0,"",IFERROR(+AE33/AC33-1,"")) | AH33: =IF(IFERROR(AE33/AA33-1,"")=0,"",IFERROR(+AE33/AA33-1,"")) | AJ33: =IF(IFERROR(AI33/AI$4,"")=0,"",IFERROR(AI33/AI$4,"")) | AK33: 0 | AL33: =IF(IFERROR(AK33/AK$4,"")=0,"",IFERROR(AK33/AK$4,"")) | AM33: =+Расходы!F259/1000 -> 157.02642 | AN33: =IF(IFERROR(AM33/AM$4,"")=0,"",IFERROR(AM33/AM$4,"")) -> 0.0099936688 | AO33: =IF(IFERROR(AM33/AK33-1,"")=0,"",IFERROR(+AM33/AK33-1,"")) | AP33: =IF(IFERROR(AM33/AI33-1,"")=0,"",IFERROR(+AM33/AI33-1,"")) | AR33: =IF(IFERROR(AQ33/AQ$4,"")=0,"",IFERROR(AQ33/AQ$4,"")) | AS33: 0 | AT33: =IF(IFERROR(AS33/AS$4,"")=0,"",IFERROR(AS33/AS$4,"")) | AU33: =+Расходы!G259/1000 -> 95.80633 | AV33: =IF(IFERROR(AU33/AU$4,"")=0,"",IFERROR(AU33/AU$4,"")) -> 0.0067216706 | AW33: =IF(IFERROR(AU33/AS33-1,"")=0,"",IFERROR(+AU33/AS33-1,"")) | AX33: =IF(IFERROR(AU33/AQ33-1,"")=0,"",IFERROR(+AU33/AQ33-1,"")) | AZ33: =IF(IFERROR(AY33/AY$4,"")=0,"",IFERROR(AY33/AY$4,"")) | BA33: 0 | BB33: =IF(IFERROR(BA33/BA$4,"")=0,"",IFERROR(BA33/BA$4,"")) | BC33: =+Расходы!H259/1000 -> 0 | BD33: =IF(IFERROR(BC33/BC$4,"")=0,"",IFERROR(BC33/BC$4,"")) | BE33: =IF(IFERROR(BC33/BA33-1,"")=0,"",IFERROR(+BC33/BA33-1,"")) | BF33: =IF(IFERROR(BC33/AY33-1,"")=0,"",IFERROR(+BC33/AY33-1,"")) | BH33: =IF(IFERROR(BG33/BG$4,"")=0,"",IFERROR(BG33/BG$4,"")) | BI33: 0 | BJ33: =IF(IFERROR(BI33/BI$4,"")=0,"",IFERROR(BI33/BI$4,"")) | BK33: =+Расходы!I259/1000 -> 0 | BL33: =IF(IFERROR(BK33/BK$4,"")=0,"",IFERROR(BK33/BK$4,"")) | BM33: =IF(IFERROR(BK33/BI33-1,"")=0,"",IFERROR(+BK33/BI33-1,"")) | BN33: =IF(IFERROR(BK33/BG33-1,"")=0,"",IFERROR(+BK33/BG33-1,"")) | BP33: =IF(IFERROR(BO33/BO$4,"")=0,"",IFERROR(BO33/BO$4,"")) | BQ33: 0 | BR33: =IF(IFERROR(BQ33/BQ$4,"")=0,"",IFERROR(BQ33/BQ$4,"")) | BS33: =+Расходы!J259/1000 -> 0 | BT33: =IF(IFERROR(BS33/BS$4,"")=0,"",IFERROR(BS33/BS$4,"")) | BU33: =IF(IFERROR(BS33/BQ33-1,"")=0,"",IFERROR(+BS33/BQ33-1,"")) | BV33: =IF(IFERROR(BS33/BO33-1,"")=0,"",IFERROR(+BS33/BO33-1,"")) | BX33: =IF(IFERROR(BW33/BW$4,"")=0,"",IFERROR(BW33/BW$4,"")) | BY33: 0 | BZ33: =IF(IFERROR(BY33/BY$4,"")=0,"",IFERROR(BY33/BY$4,"")) | CA33: =+Расходы!K259/1000 -> 0 | CB33: =IF(IFERROR(CA33/CA$4,"")=0,"",IFERROR(CA33/CA$4,"")) | CC33: =IF(IFERROR(CA33/BY33-1,"")=0,"",IFERROR(+CA33/BY33-1,"")) | CD33: =IF(IFERROR(CA33/BW33-1,"")=0,"",IFERROR(+CA33/BW33-1,"")) | CF33: =IF(IFERROR(CE33/CE$4,"")=0,"",IFERROR(CE33/CE$4,"")) | CG33: 0 | CH33: =IF(IFERROR(CG33/CG$4,"")=0,"",IFERROR(CG33/CG$4,"")) | CI33: =+Расходы!L259/1000 -> 0 | CJ33: =IF(IFERROR(CI33/CI$4,"")=0,"",IFERROR(CI33/CI$4,"")) | CK33: =IF(IFERROR(CI33/CG33-1,"")=0,"",IFERROR(+CI33/CG33-1,"")) | CL33: =IF(IFERROR(CI33/CE33-1,"")=0,"",IFERROR(+CI33/CE33-1,"")) | CN33: =IF(IFERROR(CM33/CM$4,"")=0,"",IFERROR(CM33/CM$4,"")) | CO33: 0 | CP33: =IF(IFERROR(CO33/CO$4,"")=0,"",IFERROR(CO33/CO$4,"")) | CQ33: =+Расходы!M259/1000 -> 0 | CR33: =IF(IFERROR(CQ33/CQ$4,"")=0,"",IFERROR(CQ33/CQ$4,"")) | CS33: =IF(IFERROR(CQ33/CO33-1,"")=0,"",IFERROR(+CQ33/CO33-1,"")) | CT33: =IF(IFERROR(CQ33/CM33-1,"")=0,"",IFERROR(+CQ33/CM33-1,"")) | CU33: =SUM(C33,K33,S33,AA33,AI33,AQ33,AY33,BG33,BO33,BW33,CE33,CM33) -> 0 | CV33: =IFERROR(CU33/CU$4,"") | CW33: =SUM(E33,M33,U33,AC33,AK33,AS33,BA33,BI33,BQ33,BY33,CG33,CO33) -> 0 | CX33: =IFERROR(CW33/CW$4,"") -> 0 | CY33: =SUM(G33,O33,W33,AE33,AM33,AU33,BC33,BK33,BS33,CA33,CI33,CQ33) -> 593.47121 | CZ33: =IFERROR(CY33/CY$4,"") -> 0.011962965 | DA33: =IF(IFERROR(CY33/CW33-1,"")=0,"",IFERROR(+CY33/CW33-1,"")) | DB33: =IF(IFERROR(CY33/CU33-1,"")=0,"",IFERROR(+CY33/CU33-1,""))
